Workbook
Name _meses: OFFSET(SUELDOS!XER1048551,SUELDOS!$K$28,0,SUELDOS!$K$29,1)
Name _sueldo: OFFSET(SUELDOS!$H$3,[1]DOS!$K$28,0,SUELDOS!$K$29,1)

Sheet HORARIOS DE CONSULTAS Y CX
A1: HORARIOS DE CONSULTAS Y PROCEDIMIENTOS EN LAS CLINICAS
B2: LUNES | C2: MARTES | D2: MIERCOLES | E2: JUEVES | F2: VIERNES | G2: OBSERVACION
A3: 8-10 AM | B3: COROMINAS | C3: Marvesa | D3: INTEGRAL 3 | E3: INTEGRAL 3
A4: 10-12 AM | E4: GRUMED
A5: 2-4 PM | B5: Marvesa | C5: HCFFAA | D5: MARVESA | E5: HCFFAA | F5: HCFFAA
A6: 4-6 PM | B6: GMSM | C6: HMNSA | D6: GMSM | E6: GMSM | F6: HMNSA
B11: DIA DE CIRUGIA GMSM
B12: DIA DE CIRUGIA GRUMED
B13: DIA DE CIRUGIA MONUMENTAL Y/O INTEGRAL 3
B14: AYUDANTIA EN LA INTEGRAL A PAULINO
A18: HORARIOS DE CONSULTAS Y PROCEDIMIENTOS EN LOS HOSPITALES
B19: LUNES | C19: MARTES | D19: MIERCOLES | E19: JUEVES | F19: VIERNES | G19: OBSERVACION
A20: 7-10 AM | C20: MARVESA
A21: 10-12 AM | C21: MARVESA
A22: 1-4 PM | B22: MARVESA | C22: HCFF | D22: MARVESA | E22: HCFF | F22: HCFF
A23: 4-6 PM | B23: MHMNSA | C23: HMNSA | D23: HMNSA | E23: HMNSA | F23: HCFF
B28: DIA DE CONSUTA
B29: DIA DE CIRUGIA
B30: VISITA EN SALA Y/O CIRUGIA

Sheet consolidacion de pago bien 
A1: FECHA | B1: ARS | C1: RNC | D1: MONTO FACTURADO | E1: MONTO RETENIDO(RENTA) | F1: TOTAL A PAGAR | G1: FECHA DE ENTREGA | H1: FECHA DE PAGO | I1: Estatus | J1: OBSERVACIONES
A2: 44382 | B2: SENASA | C2: B1500000156 | D2: 12300 | E2: 1230 | F2: 11070 | G2: 44383 | H2: 10-12/AGOSTO | I2: Pagada
A3: 44382 | B3: HUMANO | C3: B0100000060 | D3: 8640 | E3: 864 | F3: 7776 | G3: 44382 | H3: 44413 | I3: Pagada
A4: 44382 | B4: MAPFRE | C4: B0100000062 | D4: 31170 | E4: 3117 | F4: =+D4-E4 -> 28053 | G4: 44384 | H4: 44428 | I4: Pagada
A5: 44382 | B5: P-HUMANO | C5: B01000000059 | D5: 1445 | E5: 144.5 | F5: =+D5-E5 -> 1300.5 | G5: 44382 | H5: 44413 | I5: Pagada
A6: 44382 | B6: SEMMA | C6: B0100000058 | D6: 10000 | E6: 1000 | F6: 9000 | G6: 44384 | H6: 44440 | I6: Pagada
A7: 44382 | B7: UNIVERSAL | C7: B0100000061 | D7: 4717.5 | E7: 471.75 | F7: =+D7-E7 -> 4245.75 | G7: 44382 | H7: 44413 | I7: Pagada
A8: 44413 | B8: SENASA | C8: B1500000157 | D8: 224460 | E8: =+D8*10% -> 22446 | F8: =+D8-E8 -> 202014 | G8: 44412 | H8: 10-12/septiembre | I8: Pagada
A9: 44413 | B9: HUMANO | C9: B0100000067 | D9: 14208.75 | E9: =+D9*10% -> 1420.875 | F9: =+D9-E9 -> 12787.875 | G9: 44412 | H9: 44444 | I9: Pagada
A10: 44413 | B10: MAPFRE | C10: B0100000069 | D10: 47449.48 | E10: =+D10*10% -> 4744.948 | F10: =+D10-E10 -> 42704.532 | G10: 44412 | H10: 44459 | I10: Pagada
A11: 44413 | B11: P-HUMANO | C11: B01000000066 | D11: 30220 | E11: =+D11*10% -> 3022 | F11: =+D11-E11 -> 27198 | G11: 44320 | H11: 44444 | I11: Pagada
A12: 44413 | B12: SEMMA | C12: B0100000065 | D12: 9100 | E12: =+D12*10% -> 910 | F12: =+D12-E12 -> 8190 | G12: 44412 | H12: 10-12/septiembre | I12: Pagada
A13: 44413 | B13: UNIVERSAL | C13: B0100000068 | D13: 43354 | E13: =+D13*10% -> 4335.4 | F13: =+D13-E13 -> 39018.6 | G13: 44412 | H13: 44444 | I13: Pagada
A14: 44444 | B14: SENASA | C14: B1500000158 | D14: 25780 | E14: =+D14*10% -> 2578 | F14: =+D14-E14 -> 23202 | G14: 44442 | H14: 10-12/OCTUBTE | I14: Pagada
A15: 44444 | B15: MAPFRE | C15: B0100000075 | D15: 8835 | E15: =+D15*10% -> 883.5 | F15: =+D15-E15 -> 7951.5 | G15: 44442 | H15: 44489 | I15: Pagada
A16: 44444 | B16: P-HUMANO | C16: B01000000073 | D16: 11790 | E16: =+D16*10% -> 1179 | F16: =+D16-E16 -> 10611 | G16: 44442 | H16: 44474 | I16: Pagada
A17: 44444 | B17: SEMMA | C17: B0100000072 | D17: 17500 | E17: =+D17*10% -> 1750 | F17: =+D17-E17 -> 15750 | G17: 44442 | H17: 10-12/OCTUBTE | I17: Pagada
A18: 44444 | B18: UNIVERSAL | C18: B0100000074 | D18: 87730.16 | E18: =+D18*10% -> 8773.016 | F18: =+D18-E18 -> 78957.144 | G18: 44442 | H18: 44474 | I18: Pagada
A19: 44444 | B19: GMA | C19: B0100000070 | D19: 10464 | E19: =+D19*10% -> 1046.4 | F19: =+D19-E19 -> 9417.6 | G19: 44442 | H19: 44479 | I19: Pagada
A20: 44444 | B20: FUTURO | C20: B0100000077 | D20: 4037 | E20: =+D20*10% -> 403.7 | F20: =+D20-E20 -> 3633.3 | G20: 44442 | H20: 44479 | I20: Pagada
A21: 44444 | B21: Yunen | C21: B0100000076 | D21: 8230 | E21: =+D21*10% -> 823 | F21: =+D21-E21 -> 7407 | G21: 44442 | H21: 44479 | I21: Pagada
A22: 44444 | B22: RENACER | C22: B0100000078 | D22: 9500 | E22: =+D22*10% -> 950 | F22: =+D22-E22 -> 8550 | G22: 44442 | H22: 44479 | I22: Pagada | J22: cta BHD-LEON
A23: 44444 | B23: YUNEN | C23: B0100000063 | D23: 32815 | E23: =+D23*10% -> 3281.5 | F23: =+D23-E23 -> 29533.5 | G23: 44383 | H23: 44479 | I23: Pagada
A24: 44474 | B24: SENASA | C24: B1500000159 | D24: 54765 | E24: =+D24*10% -> 5476.5 | F24: =+D24-E24 -> 49288.5 | G24: 44473 | H24: 10-12/NOV | I24: Pagada
A25: 44474 | B25: RENACER | C25: B0100000079 | D25: 2025 | E25: =+D25*10% -> 202.5 | F25: =+D25-E25 -> 1822.5 | G25: 04/102021 | H25: 44510 | I25: Pagada
A26: 44474 | B26: APS | C26: B0100000080 | D26: 5500 | E26: =+D26*10% -> 550 | F26: =+D26-E26 -> 4950 | G26: 44473 | H26: 44520 | I26: Pagada
A27: 44474 | B27: P-HUMANO | C27: B01000000081 | D27: 9532.5 | E27: =+D27*10% -> 953.25 | F27: =+D27-E27 -> 8579.25 | G27: 44473 | H27: 44505 | I27: Pagada
A28: 44474 | B28: HUMANO | C28: B0100000082 | D28: 1000 | E28: =+D28*10% -> 100 | F28: =+D28-E28 -> 900 | G28: 44473 | H28: 44505 | I28: Pagada
A29: 44474 | B29: ASEMAP | C29: B0100000083 | D29: 15500 | E29: =+D29*10% -> 1550 | F29: =+D29-E29 -> 13950 | G29: 44473 | H29: 44505 | I29: Pagada
A30: 44474 | B30: MAPFRE | C30: B0100000084 | D30: 7667.5 | E30: =+D30*10% -> 766.75 | F30: =+D30-E30 -> 6900.75 | G30: 44473 | H30: 44520 | I30: Pagada
A31: 44474 | B31: FUTURO | C31: B0100000085 | D31: 32697.5 | E31: =+D31*10% -> 3269.75 | F31: =+D31-E31 -> 29427.75 | G31: 44473 | H31: 44510 | I31: Pagada
A32: 44474 | B32: Yunen | C32: B0100000086 | D32: 2000 | E32: =+D32*10% -> 200 | F32: =+D32-E32 -> 1800 | G32: 44473 | H32: 44510 | I32: Pagada
A33: 44474 | B33: UNIVERSAL | C33: B0100000087 | D33: 2892.46 | E33: =+D33*10% -> 289.246 | F33: =+D33-E33 -> 2603.214 | G33: 44473 | H33: 44505 | I33: Pagada
A34: 44474 | B34: MONUMENTAL | C34: B0100000088 | D34: 3650 | E34: =+D34*10% -> 365 | F34: =+D34-E34 -> 3285 | G34: 44473 | H34: 44510 | I34: Pagada
A35: 44505 | B35: SENASA | C35: B1500000160 | D35: 72975 | E35: =+D35*10% -> 7297.5 | F35: =+D35-E35 -> 65677.5 | G35: 44503 | H35: 10-12/disc | I35: Pagada
A36: 44505 | B36: P-HUMANO | C36: B01000000089 | D36: 5930 | E36: =+D36*10% -> 593 | F36: =+D36-E36 -> 5337 | G36: 44503 | H36: 44535 | I36: Pagada
A37: 44505 | B37: MAPFRE | C37: B0100000090 | D37: 30550 | E37: =+D37*10% -> 3055 | F37: =+D37-E37 -> 27495 | G37: 44503 | H37: 44550 | I37: Pagada
A38: 44505 | B38: RENACER | C38: B0100000091 | D38: 2430 | E38: =+D38*10% -> 243 | F38: =+D38-E38 -> 2187 | G38: 043/112021 | H38: 44540 | I38: Pagada
A39: 44505 | B39: RESERVAS | C39: B0100000092 | D39: 1900 | E39: =+D39*10% -> 190 | F39: =+D39-E39 -> 1710 | G39: 44503 | H39: 44540 | I39: Pagada
A40: 44535 | B40: SENASA | C40: B1500000161 | D40: 7533.39 | E40: =+D40*10% -> 753.339 | F40: =+D40-E40 -> 6780.051 | G40: 44532 | H40: 10-12/enero | I40: Pagada
A41: 44535 | B41: Integral III | C41: B0100000093 | D41: 2216.5 | E41: =+D41*10% -> 221.65 | F41: =+D41-E41 -> 1994.85 | I41: Pagada
A42: 44535 | B42: P-HUMANO | C42: B0100000094 | D42: 12179 | E42: =+D42*10% -> 1217.9 | F42: =+D42-E42 -> 10961.1 | G42: 44532 | H42: 44566 | I42: Pagada
A43: 44535 | B43: HUMANO | C43: B0100000095 | D43: 20310 | E43: =+D43*10% -> 2031 | F43: =+D43-E43 -> 18279 | G43: 44532 | H43: 44566 | I43: Pagada
A44: 44535 | B44: MAPFRE | C44: B0100000096 | D44: 30692.3 | E44: =+D44*10% -> 3069.23 | F44: =+D44-E44 -> 27623.07 | G44: 44532 | H44: 44581 | I44: Pagada
A45: 44535 | B45: YUNEN | C45: B0100000097 | D45: 17021 | E45: =+D45*10% -> 1702.1 | F45: =+D45-E45 -> 15318.9 | G45: 44532 | H45: 44571 | I45: Pagada
A46: 44566 | B46: SENASA | C46: B1500000162 | D46: 61052.5 | E46: =+D46*10% -> 6105.25 | F46: =+D46-E46 -> 54947.25 | G46: 44564 | H46: 10-12/febrero | I46: Pagada
A47: 44566 | B47: P-HUMANO | C47: B0100000098 | D47: 19778 | E47: =+D47*10% -> 1977.8 | F47: =+D47-E47 -> 17800.2 | G47: 44564 | H47: 44597 | I47: Pagada
A48: 44566 | B48: HUMANO | C48: B0100000099 | D48: 1000 | E48: =+D48*10% -> 100 | F48: =+D48-E48 -> 900 | G48: 44564 | H48: 44597 | I48: Pagada
A49: 44566 | B49: MAPFRE | C49: B0100000100 | D49: 1958 | E49: =+D49*10% -> 195.8 | F49: =+D49-E49 -> 1762.2 | G49: 44564 | H49: 44612 | I49: Pagada
A50: 44597 | B50: SENASA | C50: B1500000163 | D50: 80658 | E50: =+D50*10% -> 8065.8 | F50: =+D50-E50 -> 72592.2 | G50: 44596 | H50: 10-12/MARZO | I50: Pagada
A51: 44597 | B51: P-HUMANO | C51: B0100000101 | D51: 1634 | E51: =+D51*10% -> 163.4 | F51: =+D51-E51 -> 1470.6 | G51: 44596 | H51: 44625 | I51: Pagada
A52: 44597 | B52: HUMANO | C52: B0100000102 | D52: 20778 | E52: =+D52*10% -> 2077.8 | F52: =+D52-E52 -> 18700.2 | G52: 44596 | H52: 44625 | I52: Pagada
A53: 44597 | B53: MAPFRE | C53: B0100000103 | D53: 4780 | E53: =+D53*10% -> 478 | F53: =+D53-E53 -> 4302 | G53: 44596 | H53: 44640 | I53: Pagada
A54: 44597 | B54: YUNEN | C54: B0100000104 | D54: 28100 | E54: =+D54*10% -> 2810 | F54: =+D54-E54 -> 25290 | G54: 44596 | H54: 44641 | I54: Pagada
A55: 44597 | B55: FUTURO | C55: B0100000105 | D55: 4500 | E55: =+D55*10% -> 450 | F55: =+D55-E55 -> 4050 | G55: 44596 | H55: 44642 | I55: Pagada
A56: 44597 | B56: META SALUD | C56: B0100000106 | D56: 3240 | E56: =+D56*10% -> 324 | F56: =+D56-E56 -> 2916 | G56: 44596 | H56: 44643 | I56: Pagada
A57: 44625 | B57: SENASA | C57: B1500000164 | D57: 9390 | E57: =+D57*10% -> 939 | F57: =+D57-E57 -> 8451 | G57: 44596 | H57: 10-12/MARZO | I57: Pagada
A58: 44625 | B58: P-HUMANO | C58: B0100000107 | D58: 27015 | E58: =+D58*10% -> 2701.5 | F58: =+D58-E58 -> 24313.5 | G58: 44596 | H58: 44625 | I58: Pagada
A59: 44625 | B59: HUMANO | C59: B0100000108 | D59: 3340 | E59: =+D59*10% -> 334 | F59: =+D59-E59 -> 3006 | G59: 44596 | H59: 44625 | I59: Pagada
A60: 44625 | B60: MAPFRE | C60: B0100000109 | D60: =13475.35+28281.96 -> 41757.31 | E60: =+D60*10% -> 4175.731 | F60: =+D60-E60 -> 37581.579 | G60: 44596 | H60: 44640 | I60: Pagada
A61: 44625 | B61: YUNEN | C61: B0100000110 | D61: 2950 | E61: =+D61*10% -> 295 | F61: =+D61-E61 -> 2655 | G61: 44596 | H61: 44641 | I61: Pagada
A62: 44625 | B62: Universal | C62: B0100000111 | D62: 10450 | E62: =+D62*10% -> 1045 | F62: =+D62-E62 -> 9405 | G62: 44596 | H62: 44642 | I62: Pagada
A63: 44625 | B63: clinica integral 3 | C63: B0100000112 | I63: Pagada
A64: 44656 | B64: SENASA | C64: B1500000165 | D64: 74150 | E64: =+D64*10% -> 7415 | F64: =+D64-E64 -> 66735 | G64: 44655 | H64: 10-12/mayo | I64: Pagada
A65: 44656 | B65: P-HUMANO | C65: B0100000113 | D65: =60310.8+20412 -> 80722.8 | E65: =+D65*10% -> 8072.28 | F65: =+D65-E65 -> 72650.52 | G65: 44655 | H65: 44686 | I65: Pagada
A66: 44656 | B66: HUMANO | C66: B0100000114 | D66: =24472-20412 -> 4060 | E66: =+D66*10% -> 406 | F66: =+D66-E66 -> 3654 | G66: 44655 | H66: 44686 | I66: Pagada
A67: 44656 | B67: MAPFRE | C67: B0100000115 | D67: 9375 | E67: =+D67*10% -> 937.5 | F67: =+D67-E67 -> 8437.5 | G67: 44596 | H67: 44640 | I67: Pagada
A68: 44656 | B68: Universal | C68: B0100000116 | D68: 20310 | E68: =+D68*10% -> 2031 | F68: =+D68-E68 -> 18279 | G68: 44596 | H68: 44642 | I68: Pagada
A69: 44686 | B69: SENASA | C69: B1500000166 | D69: 68432 | E69: =+D69*10% -> 6843.2 | F69: =+D69-E69 -> 61588.8 | G69: 44685 | H69: 10-12/JUNIO | I69: Pagada
A70: 44686 | B70: P-HUMANO | C70: B0100000117 | D70: 26381 | E70: =+D70*10% -> 2638.1 | F70: =+D70-E70 -> 23742.9 | G70: 44685 | H70: 44717 | I70: Pagada
A71: 44686 | B71: HUMANO | C71: B0100000118 | D71: 20412 | E71: =+D71*10% -> 2041.2 | F71: =+D71-E71 -> 18370.8 | G71: 44685 | H71: 44717 | I71: Pagada
A72: 44686 | B72: MAPFRE | C72: B0100000119 | D72: 22176 | E72: =+D72*10% -> 2217.6 | F72: =+D72-E72 -> 19958.4 | G72: 44685 | H72: 44732 | I72: Pagada
A73: 44686 | B73: RESERVAS | C73: B0100000120 | D73: 4975 | E73: =+D73*10% -> 497.5 | F73: =+D73-E73 -> 4477.5 | G73: 44685 | H73: 44734 | I73: Pagada
A74: 44686 | B74: APS | C74: B0100000121 | D74: 2800 | E74: =+D74*10% -> 280 | F74: =+D74-E74 -> 2520 | G74: 44685 | H74: 44722 | I74: Pagada
A75: 44717 | B75: SENASA | C75: B1500000167 | D75: 8320 | E75: =+D75*10% -> 832 | F75: =+D75-E75 -> 7488 | G75: 44714 | H75: 10-12/JULIO | I75: Pagada
A76: 44717 | B76: P-HUMANO | C76: B0100000122 | D76: 4036 | E76: =+D76*10% -> 403.6 | F76: =+D76-E76 -> 3632.4 | G76: 44714 | H76: 44747 | I76: Pagada
A77: 44717 | B77: HUMANO | C77: B0100000123 | D77: 8854 | E77: =+D77*10% -> 885.4 | F77: =+D77-E77 -> 7968.6 | G77: 44714 | H77: 44747 | I77: Pagada
A78: 44717 | B78: MAPFRE | C78: B0100000124 | D78: 8910 | E78: =+D78*10% -> 891 | F78: =+D78-E78 -> 8019 | G78: 44714 | H78: 44762 | I78: Pagada
A79: 44717 | B79: RESERVAS | C79: B0100000125 | D79: 5472 | E79: =+D79*10% -> 547.2 | F79: =+D79-E79 -> 4924.8 | G79: 44714 | H79: 44764 | I79: Pagada
A80: 44717 | B80: Futuro | C80: B0100000126 | D80: 2577 | E80: =+D80*10% -> 257.7 | F80: =+D80-E80 -> 2319.3 | G80: 44714 | H80: 44752 | I80: Pagada
A81: 44717 | B81: Renacer | C81: B0100000127 | D81: 6210 | E81: =+D81*10% -> 621 | F81: =+D81-E81 -> 5589 | I81: Pagada
A82: 44717 | B82: integral 3 | C82: B0100000128 | I82: Pagada
A83: 44717 | B83: integral 3 | C83: B0100000129 | I83: Pagada
A84: 44747 | B84: SENASA | C84: B1500000168 | D84: 42368 | E84: =+D84*10% -> 4236.8 | F84: =+D84-E84 -> 38131.2 | G84: 44747 | H84: 10-12/AGOSTO | I84: Pagada
A85: 44747 | B85: P-HUMANO | C85: B0100000130 | D85: 8650 | E85: =+D85*10% -> 865 | F85: =+D85-E85 -> 7785 | G85: 44747 | H85: 44778 | I85: Pagada
A86: 44747 | B86: HUMANO | C86: B0100000131 | D86: 11648 | E86: =+D86*10% -> 1164.8 | F86: =+D86-E86 -> 10483.2 | G86: 44747 | H86: 44778 | I86: Pagada
A87: 44747 | B87: MAPFRE | C87: B0100000132 | D87: 5302 | E87: =+D87*10% -> 530.2 | F87: =+D87-E87 -> 4771.8 | G87: 44747 | H87: 44793 | I87: Pagada
A88: 44747 | B88: METASALUD | C88: B0100000133 | D88: 2430 | E88: =+D88*10% -> 243 | F88: =+D88-E88 -> 2187 | G88: 44747 | H88: 44795 | I88: Pagada
A89: 44747 | B89: YUNEN | C89: B0100000134 | D89: 2592 | E89: =+D89*10% -> 259.2 | F89: =+D89-E89 -> 2332.8 | G89: 44747 | H89: 44783 | I89: Pagada
A90: 44778 | B90: SENASA | C90: B1500000169 | D90: 88600 | E90: =+D90*10% -> 8860 | F90: =+D90-E90 -> 79740 | G90: 44777 | H90: 10-12/octubre | I90: Pagada
A91: 44778 | B91: P-HUMANO | C91: B0100000135 | D91: 100773.5 | E91: =+D91*10% -> 10077.35 | F91: =+D91-E91 -> 90696.15 | G91: 44777 | H91: 44809 | I91: Pagada
A92: 44778 | B92: MAPFRE | C92: B0100000136 | D92: 50021.96 | E92: =+D92*10% -> 5002.196 | F92: =+D92-E92 -> 45019.764 | G92: 44777 | H92: 44824 | I92: Pagada | J92: se pago 19,000
A93: 44778 | B93: Renacer | C93: B0100000137 | D93: 20300 | E93: =+D93*10% -> 2030 | F93: =+D93-E93 -> 18270 | G93: 44777 | H93: 44826 | I93: Pagada
A94: 44778 | B94: Universal | C94: B0100000138 | D94: 12394.4 | E94: =+D94*10% -> 1239.44 | F94: =+D94-E94 -> 11154.96 | G94: 44777 | H94: 44809 | I94: Pagada
A95: 44778 | B95: BANCO CENTRAL | C95: B1500000170 | D95: 1560 | E95: =+D95*10% -> 156 | F95: =+D95-E95 -> 1404 | G95: 44777 | H95: 44809 | I95: Pagada
A96: 44809 | B96: SENASA | C96: B1500000171 | D96: 649016 | E96: =+D96*10% -> 64901.6 | F96: =+D96-E96 -> 584114.4 | G96: 44809 | H96: 10-12/octubre | I96: Pagada
A97: 44809 | B97: P-HUMANO | C97: B0100000139 | D97: 67136.12 | E97: =+D97*10% -> 6713.612 | F97: =+D97-E97 -> 60422.508 | G97: 44809 | H97: 44839 | I97: Pagada
A98: 44809 | B98: HUMANO | C98: B0100000140 | D98: 11580 | E98: =+D98*10% -> 1158 | F98: =+D98-E98 -> 10422 | G98: 44809 | H98: 44839 | I98: Pagada
A99: 44809 | B99: MAPFRE | C99: B0100000141 | D99: 84098 | E99: =+D99*10% -> 8409.8 | F99: =+D99-E99 -> 75688.2 | G99: 44809 | H99: 44854 | I99: Pagada
A100: 44809 | B100: Metasalud | C100: B0100000142 | D100: 22600 | E100: =+D100*10% -> 2260 | F100: =+D100-E100 -> 20340 | G100: 44809 | H100: 44856 | I100: Pagada
...

Sheet CONSOLIDADOS DE PAGOS
A1: CONSOLIDADOS DE PAGOS POR ARS
A2: ARS | B2: RNC | C2: MONTO FACTURADO | D2: MONTO RETENIDO(RENTA) | E2: TOTAL A PAGAR | F2: FECHA DE ENTREGA | G2: FECHA DE PAGO | H2: OBSERVACIONES
A3: SENASA | B3: B1500000156 | C3: 12300 | D3: 1230 | E3: 11070 | F3: 44383 | G3: 10-12/AGOSTO
A4: HUMANO | B4: B0100000060 | C4: 8640 | D4: 864 | E4: 7776 | F4: 44382 | G4: 44413 | L4: ENCABEZADO
A5: MAPFRE | B5: B0100000062 | C5: 31170 | D5: 3117 | E5: =+C5-D5 -> 28053 | F5: 44384 | G5: 44428 | L5: FACTURA PENDIENTE POR PAGO
A6: P-HUMANO | B6: B01000000059 | C6: 1445 | D6: 144.5 | E6: =+C6-D6 -> 1300.5 | F6: 44382 | G6: 44413 | L6: FACTURA DEVUELTA
A7: SEMMA | B7: B0100000058 | C7: 10000 | D7: 1000 | E7: 9000 | F7: 44384 | G7: 44440 | L7: FACTURA PAGADA
A8: UNIVERSAL | B8: B0100000061 | C8: 4717.5 | D8: 471.75 | E8: =+C8-D8 -> 4245.75 | F8: 44382 | G8: 44413
A9: TOTAL | C9: =SUM(C3:C8) -> 68272.5 | D9: =SUM(D3:D8) -> 6827.25 | E9: =SUM(E3:E8) -> 61445.25
C11: Mes de Julio-Agosto | G11: 2
A12: ARS | B12: RNC | C12: MONTO FACTURADO | D12: MONTO RETENIDO(RENTA) | E12: TOTAL A PAGAR | F12: FECHA DE ENTREGA | G12: FECHA DE PAGO | H12: OBSERVACIONES
A13: SENASA | B13: B1500000157 | C13: 224460 | D13: =+C13*10% -> 22446 | E13: =+C13-D13 -> 202014 | F13: 44412 | G13: 10-12/septiembre
A14: HUMANO | B14: B0100000067 | C14: 14208.75 | D14: =+C14*10% -> 1420.875 | E14: =+C14-D14 -> 12787.875 | F14: 44412 | G14: 44444
A15: MAPFRE | B15: B0100000069 | C15: 47449.48 | D15: =+C15*10% -> 4744.948 | E15: =+C15-D15 -> 42704.532 | F15: 44412 | G15: 44459
A16: P-HUMANO | B16: B01000000066 | C16: 30220 | D16: =+C16*10% -> 3022 | E16: =+C16-D16 -> 27198 | F16: 44320 | G16: 44444
A17: SEMMA | B17: B0100000065 | C17: 9100 | D17: =+C17*10% -> 910 | E17: =+C17-D17 -> 8190 | F17: 44412 | G17: 10-12/septiembre
A18: UNIVERSAL | B18: B0100000068 | C18: 43354 | D18: =+C18*10% -> 4335.4 | E18: =+C18-D18 -> 39018.6 | F18: 44412 | G18: 44444
A19: TOTAL | C19: =SUM(C13:C18) -> 368792.23 | D19: =SUM(D13:D18) -> 36879.223 | E19: =SUM(E13:E18) -> 331913.01
C21: MES AGOSTO-SEPTIEMBRE
A23: ARS | B23: RNC | C23: MONTO FACTURADO | D23: MONTO RETENIDO(RENTA) | E23: TOTAL A PAGAR | F23: FECHA DE ENTREGA | G23: FECHA DE PAGO | H23: OBSERVACIONES
A24: SENASA | B24: B1500000158 | C24: 25780 | D24: =+C24*10% -> 2578 | E24: =+C24-D24 -> 23202 | F24: 44442 | G24: 10-12/OCTUBTE
A25: MAPFRE | B25: B0100000075 | C25: 8835 | D25: =+C25*10% -> 883.5 | E25: =+C25-D25 -> 7951.5 | F25: 44442 | G25: 44489
A26: P-HUMANO | B26: B01000000073 | C26: 11790 | D26: =+C26*10% -> 1179 | E26: =+C26-D26 -> 10611 | F26: 44442 | G26: 44474
A27: SEMMA | B27: B0100000072 | C27: 17500 | D27: =+C27*10% -> 1750 | E27: =+C27-D27 -> 15750 | F27: 44442 | G27: 10-12/OCTUBTE
A28: UNIVERSAL | B28: B0100000074 | C28: 87730.16 | D28: =+C28*10% -> 8773.016 | E28: =+C28-D28 -> 78957.144 | F28: 44442 | G28: 44474
A29: GMA | B29: B0100000070 | C29: 10464 | D29: =+C29*10% -> 1046.4 | E29: =+C29-D29 -> 9417.6 | F29: 44442 | G29: 44479
A30: FUTURO | B30: B0100000077 | C30: 4037 | D30: =+C30*10% -> 403.7 | E30: =+C30-D30 -> 3633.3 | F30: 44442 | G30: 44479
A31: Yunen | B31: B0100000076 | C31: 8230 | D31: =+C31*10% -> 823 | E31: =+C31-D31 -> 7407 | F31: 44442 | G31: 44479
A32: RENACER | B32: B0100000078 | C32: 9500 | D32: =+C32*10% -> 950 | E32: =+C32-D32 -> 8550 | F32: 44442 | G32: 44479 | H32: cta BHD-LEON
A33: YUNEN | B33: B0100000063 | C33: 32815 | D33: =+C33*10% -> 3281.5 | E33: =+C33-D33 -> 29533.5 | F33: 44383 | G33: 44479
A34: TOTAL | C34: =SUM(C24:C33) -> 216681.16 | D34: =SUM(D24:D33) -> 21668.116 | E34: =SUM(E24:E33) -> 195013.04
C40: MES SEPTIEMBRE-OCTUBRE 2021
A42: ARS | B42: RNC | C42: MONTO FACTURADO | D42: MONTO RETENIDO(RENTA) | E42: TOTAL A PAGAR | F42: FECHA DE ENTREGA | G42: FECHA DE PAGO | H42: OBSERVACIONES
A43: SENASA | B43: B1500000159 | C43: 54765 | D43: =+C43*10% -> 5476.5 | E43: =+C43-D43 -> 49288.5 | F43: 44473 | G43: 10-12/NOV
A44: RENACER | B44: B0100000079 | C44: 2025 | D44: =+C44*10% -> 202.5 | E44: =+C44-D44 -> 1822.5 | F44: 04/102021 | G44: 44510
A45: APS | B45: B0100000080 | C45: 5500 | D45: =+C45*10% -> 550 | E45: =+C45-D45 -> 4950 | F45: 44473 | G45: 44520
A46: P-HUMANO | B46: B01000000081 | C46: 9532.5 | D46: =+C46*10% -> 953.25 | E46: =+C46-D46 -> 8579.25 | F46: 44473 | G46: 44505
A47: HUMANO | B47: B0100000082 | C47: 1000 | D47: =+C47*10% -> 100 | E47: =+C47-D47 -> 900 | F47: 44473 | G47: 44505
A48: ASEMAP | B48: B0100000083 | C48: 15500 | D48: =+C48*10% -> 1550 | E48: =+C48-D48 -> 13950 | F48: 44473 | G48: 44505
A49: MAPFRE | B49: B0100000084 | C49: 7667.5 | D49: =+C49*10% -> 766.75 | E49: =+C49-D49 -> 6900.75 | F49: 44473 | G49: 44520
A50: FUTURO | B50: B0100000085 | C50: 32697.5 | D50: =+C50*10% -> 3269.75 | E50: =+C50-D50 -> 29427.75 | F50: 44473 | G50: 44510
A51: Yunen | B51: B0100000086 | C51: 2000 | D51: =+C51*10% -> 200 | E51: =+C51-D51 -> 1800 | F51: 44473 | G51: 44510
A52: UNIVERSAL | B52: B0100000087 | C52: 2892.46 | D52: =+C52*10% -> 289.246 | E52: =+C52-D52 -> 2603.214 | F52: 44473 | G52: 44505
A53: MONUMENTAL | B53: B0100000088 | C53: 3650 | D53: =+C53*10% -> 365 | E53: =+C53-D53 -> 3285 | F53: 44473 | G53: 44510
A54: TOTAL | C54: =SUM(C43:C53) -> 137229.96 | D54: =SUM(D43:D53) -> 13722.996 | E54: =SUM(E43:E53) -> 123506.96
C58: MES octubre - Noviembre 2021
A60: ARS | B60: RNC | C60: MONTO FACTURADO | D60: MONTO RETENIDO(RENTA) | E60: TOTAL A PAGAR | F60: FECHA DE ENTREGA | G60: FECHA DE PAGO | H60: OBSERVACIONES
A61: SENASA | B61: B1500000160 | C61: 72975 | D61: =+C61*10% -> 7297.5 | E61: =+C61-D61 -> 65677.5 | F61: 44503 | G61: 10-12/disc
A62: P-HUMANO | B62: B01000000089 | C62: 5930 | D62: =+C62*10% -> 593 | E62: =+C62-D62 -> 5337 | F62: 44503 | G62: 44535
A63: MAPFRE | B63: B0100000090 | C63: 30550 | D63: =+C63*10% -> 3055 | E63: =+C63-D63 -> 27495 | F63: 44503 | G63: 44550
A64: RENACER | B64: B0100000091 | C64: 2430 | D64: =+C64*10% -> 243 | E64: =+C64-D64 -> 2187 | F64: 043/112021 | G64: 44540
A65: RESERVAS | B65: B0100000092 | C65: 1900 | D65: =+C65*10% -> 190 | E65: =+C65-D65 -> 1710 | F65: 44503 | G65: 44540
A66: TOTAL | C66: =SUM(C61:C65) -> 113785 | D66: =SUM(D61:D65) -> 11378.5 | E66: =SUM(E61:E65) -> 102406.5
C70: MES NOVIEMBRE -DICIEMBRE 2021
A72: ARS | B72: RNC | C72: MONTO FACTURADO | D72: MONTO RETENIDO(RENTA) | E72: TOTAL A PAGAR | F72: FECHA DE ENTREGA | G72: FECHA DE PAGO | H72: OBSERVACIONES
A73: SENASA | B73: B1500000161 | C73: 7533.39 | D73: =+C73*10% -> 753.339 | E73: =+C73-D73 -> 6780.051 | F73: 44532 | G73: 10-12/enero
A74: Integral III | B74: B0100000093 | C74: 2216.5 | D74: =+C74*10% -> 221.65 | E74: =+C74-D74 -> 1994.85
A75: P-HUMANO | B75: B0100000094 | C75: 12179 | D75: =+C75*10% -> 1217.9 | E75: =+C75-D75 -> 10961.1 | F75: 44532 | G75: 44566
A76: HUMANO | B76: B0100000095 | C76: 20310 | D76: =+C76*10% -> 2031 | E76: =+C76-D76 -> 18279 | F76: 44532 | G76: 44566
A77: MAPFRE | B77: B0100000096 | C77: 30692.3 | D77: =+C77*10% -> 3069.23 | E77: =+C77-D77 -> 27623.07 | F77: 44532 | G77: 44581
A78: YUNEN | B78: B0100000097 | C78: 17021 | D78: =+C78*10% -> 1702.1 | E78: =+C78-D78 -> 15318.9 | F78: 44532 | G78: 44571
A79: TOTAL | C79: =SUM(C73:C78) -> 89952.19 | D79: =SUM(D73:D78) -> 8995.219 | E79: =SUM(E73:E78) -> 80956.971
B84: Nuevo Año
C86: MES Enero 2022
A88: ARS | B88: RNC | C88: MONTO FACTURADO | D88: MONTO RETENIDO(RENTA) | E88: TOTAL A PAGAR | F88: FECHA DE ENTREGA | G88: FECHA DE PAGO | H88: OBSERVACIONES
A89: SENASA | B89: B1500000162 | C89: 61052.5 | D89: =+C89*10% -> 6105.25 | E89: =+C89-D89 -> 54947.25 | F89: 44564 | G89: 10-12/febrero
A90: P-HUMANO | B90: B0100000098 | C90: 19778 | D90: =+C90*10% -> 1977.8 | E90: =+C90-D90 -> 17800.2 | F90: 44564 | G90: 44597
A91: HUMANO | B91: B0100000099 | C91: 1000 | D91: =+C91*10% -> 100 | E91: =+C91-D91 -> 900 | F91: 44564 | G91: 44597
A92: MAPFRE | B92: B0100000100 | C92: 1958 | D92: =+C92*10% -> 195.8 | E92: =+C92-D92 -> 1762.2 | F92: 44564 | G92: 44612
A93: TOTAL | C93: =SUM(C89:C92) -> 83788.5 | D93: =SUM(D89:D92) -> 8378.85 | E93: =SUM(E89:E92) -> 75409.65
C96: MES FEBRERO 2022
A98: ARS | B98: RNC | C98: MONTO FACTURADO | D98: MONTO RETENIDO(RENTA) | E98: TOTAL A PAGAR | F98: FECHA DE ENTREGA | G98: FECHA DE PAGO | H98: OBSERVACIONES
A99: SENASA | B99: B1500000163 | C99: 80658 | D99: =+C99*10% -> 8065.8 | E99: =+C99-D99 -> 72592.2 | F99: 44596 | G99: 10-12/MARZO
A100: P-HUMANO | B100: B0100000101 | C100: 1634 | D100: =+C100*10% -> 163.4 | E100: =+C100-D100 -> 1470.6 | F100: 44596 | G100: 44625
A101: HUMANO | B101: B0100000102 | C101: 20778 | D101: =+C101*10% -> 2077.8 | E101: =+C101-D101 -> 18700.2 | F101: 44596 | G101: 44625
A102: MAPFRE | B102: B0100000103 | C102: 4780 | D102: =+C102*10% -> 478 | E102: =+C102-D102 -> 4302 | F102: 44596 | G102: 44640
A103: YUNEN | B103: B0100000104 | C103: 28100 | D103: =+C103*10% -> 2810 | E103: =+C103-D103 -> 25290 | F103: 44596 | G103: 44641
A104: FUTURO | B104: B0100000105 | C104: 4500 | D104: =+C104*10% -> 450 | E104: =+C104-D104 -> 4050 | F104: 44596 | G104: 44642
A105: META SALUD | B105: B0100000106 | C105: 3240 | D105: =+C105*10% -> 324 | E105: =+C105-D105 -> 2916 | F105: 44596 | G105: 44643
A106: TOTAL | C106: =SUM(C99:C105) -> 143690 | D106: =SUM(D99:D105) -> 14369 | E106: =SUM(E99:E105) -> 129321
C110: Mes de marzo 2022
A112: ARS | B112: RNC | C112: MONTO FACTURADO | D112: MONTO RETENIDO(RENTA) | E112: TOTAL A PAGAR | F112: FECHA DE ENTREGA | G112: FECHA DE PAGO | H112: OBSERVACIONES
A113: SENASA | B113: B1500000164 | C113: 9390 | D113: =+C113*10% -> 939 | E113: =+C113-D113 -> 8451 | F113: 44596 | G113: 10-12/MARZO
A114: P-HUMANO | B114: B0100000107 | C114: 27015 | D114: =+C114*10% -> 2701.5 | E114: =+C114-D114 -> 24313.5 | F114: 44596 | G114: 44625
A115: HUMANO | B115: B0100000108 | C115: 3340 | D115: =+C115*10% -> 334 | E115: =+C115-D115 -> 3006 | F115: 44596 | G115: 44625
A116: MAPFRE | B116: B0100000109 | C116: =13475.35+28281.96 -> 41757.31 | D116: =+C116*10% -> 4175.731 | E116: =+C116-D116 -> 37581.579 | F116: 44596 | G116: 44640
A117: YUNEN | B117: B0100000110 | C117: 2950 | D117: =+C117*10% -> 295 | E117: =+C117-D117 -> 2655 | F117: 44596 | G117: 44641
A118: Universal | B118: B0100000111 | C118: 10450 | D118: =+C118*10% -> 1045 | E118: =+C118-D118 -> 9405 | F118: 44596 | G118: 44642
A119: clinica integral 3 | B119: B0100000112 | J119: factura mes de febrero
A120: TOTAL | C120: =SUM(C113:C118) -> 94902.31 | D120: =SUM(D113:D118) -> 9490.231 | E120: =SUM(E113:E118) -> 85412.079
C125: Mes de Abril 2022
A127: ARS | B127: RNC | C127: MONTO FACTURADO | D127: MONTO RETENIDO(RENTA) | E127: TOTAL A PAGAR | F127: FECHA DE ENTREGA | G127: FECHA DE PAGO | H127: OBSERVACIONES
A128: SENASA | B128: B1500000165 | C128: 74150 | D128: =+C128*10% -> 7415 | E128: =+C128-D128 -> 66735 | F128: 44655 | G128: 10-12/mayo
A129: P-HUMANO | B129: B0100000113 | C129: =60310.8+20412 -> 80722.8 | D129: =+C129*10% -> 8072.28 | E129: =+C129-D129 -> 72650.52 | F129: 44655 | G129: 44686
A130: HUMANO | B130: B0100000114 | C130: =24472-20412 -> 4060 | D130: =+C130*10% -> 406 | E130: =+C130-D130 -> 3654 | F130: 44655 | G130: 44686
A131: MAPFRE | B131: B0100000115 | C131: 9375 | D131: =+C131*10% -> 937.5 | E131: =+C131-D131 -> 8437.5 | F131: 44596 | G131: 44640
A132: Universal | B132: B0100000116 | C132: 20310 | D132: =+C132*10% -> 2031 | E132: =+C132-D132 -> 18279 | F132: 44596 | G132: 44642
A133: TOTAL | C133: =SUM(C128:C132) -> 188617.8 | D133: =SUM(D128:D132) -> 18861.78 | E133: =SUM(E128:E132) -> 169756.02
C136: MES DE MAYO 2022
A138: ARS | B138: RNC | C138: MONTO FACTURADO | D138: MONTO RETENIDO(RENTA) | E138: TOTAL A PAGAR | F138: FECHA DE ENTREGA | G138: FECHA DE PAGO | H138: OBSERVACIONES
...

Sheet SUELDOS
B1: SUELDOS Y/O HONORARIOS PRIVADOS
A2: Año | B2: Mes | C2: ERD | D2: MARVESA | E2: HMNSA | F2: HONORARIOS | G2: CONSULTAS | H2: TOTAL DEL MES
A3: 2021 | B3: Julio | C3: 35925 | D3: 58466.92 | E3: 34954.57 | F3: 121000 | H3: =SUM(C3:F3) -> 250346.49
A4: 2021 | B4: Agosto | C4: 35925 | D4: 58466.92 | E4: 34954.57 | F4: =+'CONSOLIDADOS DE PAGOS'!E9 -> 61445.25 | H4: =SUM(C4:F4) -> 190791.74 | K4: Mes | L4: Total
A5: 2021 | B5: Septiembre | C5: 35925 | D5: 58466.92 | E5: 34954.57 | F5: 331913.01 | H5: =SUM(C5:F5) -> 461259.5 | K5: Enero | L5: 1349555.6
A6: 2021 | B6: Octubre | C6: 35925 | D6: 58466.92 | E6: 34954.57 | F6: =+'CONSOLIDADOS DE PAGOS'!E34 -> 195013.04 | H6: =SUM(C6:F6) -> 324359.53 | K6: Febrero | L6: 1189739.8
A7: 2021 | B7: Noviembre | C7: 26500 | D7: 58886.92 | E7: 57700 | F7: =+'CONSOLIDADOS DE PAGOS'!E54 -> 123506.96 | H7: =SUM(C7:F7) -> 266593.88 | K7: Marzo | L7: 1285348.1
A8: 2021 | B8: Diciembre | C8: 26500 | D8: 58466.92 | E8: 57700 | F8: =+'CONSOLIDADOS DE PAGOS'!E66 -> 102406.5 | H8: =SUM(C8:F8) -> 245073.42 | K8: Abril | L8: 1508792
A9: 2022 | B9: Enero | C9: 26500 | D9: 58889.87 | E9: 57365.93 | F9: =+'CONSOLIDADOS DE PAGOS'!E79 -> 80956.971 | H9: =SUM(C9:F9) -> 223712.77 | K9: Mayo | L9: 1348325.6
A10: 2022 | B10: Febrero | C10: 26500 | D10: 58886 | E10: 57365.93 | F10: =+'CONSOLIDADOS DE PAGOS'!E93 -> 75409.65 | H10: =SUM(C10:F10) -> 218161.58 | K10: Junio | L10: 1319047.3
A11: 2022 | B11: Marzo | C11: 71300 | D11: 74886 | E11: 57365.93 | F11: 129321 | H11: =+C11+D11+E11+F11 -> 332872.93 | K11: Julio | L11: 1387573.1
A12: 2022 | B12: Abril | C12: 72655.11 | D12: 58886 | E12: 57365.93 | F12: 169756.02 | H12: =SUM(C12:F12) -> 358663.06 | K12: Agosto | L12: 1875101.7
A13: 2022 | B13: Mayo | C13: 72655.11 | D13: 58886 | E13: 57365.93 | F13: 130658.4 | H13: =SUM(C13:F13) -> 319565.44 | K13: Septiembre | L13: 2714837.9
A14: 2022 | B14: Junio | C14: 72655.11 | D14: 58886 | E14: 57365.93 | F14: 39941.1 | H14: =SUM(C14:F14) -> 228848.14 | K14: Octubre | L14: 1852981.1
A15: 2022 | B15: Julio | C15: 72655.11 | D15: 58886 | E15: 57365.93 | F15: =+'CONSOLIDADOS DE PAGOS'!E177 -> 65691 | H15: =SUM(C15:F15) -> 254598.04 | K15: Noviembre | L15: 1789729.8
A16: 2022 | B16: Agosto | C16: 72655.11 | D16: 58886 | E16: 57365.93 | F16: =+'CONSOLIDADOS DE PAGOS'!E188 -> 246284.87 | H16: =SUM(C16:F16) -> 435191.91 | K16: Diciembre | L16: 1566250.6
A17: 2022 | B17: Septiembre | C17: 72655.11 | D17: 58886 | E17: 57365.93 | F17: =+'CONSOLIDADOS DE PAGOS'!E204 -> 829822.24 | H17: =SUM(C17:F17) -> 1018729.3
A18: 2022 | B18: Octubre | C18: 72655.11 | D18: 58886 | E18: 57365.93 | F18: =+'CONSOLIDADOS DE PAGOS'!E214 -> 200775.01 | H18: =SUM(C18:F18) -> 389682.05
A19: 2022 | B19: Noviembre | C19: 72655.11 | D19: 58886 | E19: 57365.93 | F19: =+'CONSOLIDADOS DE PAGOS'!E230 -> 308422.82 | H19: =SUM(C19:F19) -> 497329.86
A20: 2022 | B20: Diciembre | C20: 72655.11 | D20: 58886 | E20: 57365.93 | F20: =+'CONSOLIDADOS DE PAGOS'!E241 -> 309126.6 | H20: =SUM(C20:F20) -> 498033.64
A21: 2023 | B21: Enero | C21: 72655.11 | D21: 58889.87 | E21: 57365.93 | F21: 160148.53 | G21: 6000 | H21: =+C21+D21+E21+F21+G21 -> 355059.44
A22: 2023 | B22: Febrero | C22: 72655.11 | D22: 58886 | E22: 57365.93 | F22: =+'CONSOLIDADOS DE PAGOS'!E260 -> 23911.2 | G22: 30000 | H22: =+C22+D22+E22+F22+G22 -> 242818.24
A23: 2023 | B23: Marzo | C23: 72655.11 | D23: 58886 | E23: 57365.93 | F23: =+'CONSOLIDADOS DE PAGOS'!E270 -> 230489.53 | G23: 30000 | H23: =+C23+D23+E23+F23+G23 -> 449396.57
A24: 2023 | B24: Abril | C24: 72655.11 | D24: 58886 | E24: 57365.93 | F24: =+'CONSOLIDADOS DE PAGOS'!E281 -> 260954.33 | G24: 0 | H24: =+C24+D24+E24+F24+G24 -> 449861.36
A25: 2023 | B25: Mayo | C25: 72655.11 | D25: 58886 | E25: 57365.93 | F25: =+'CONSOLIDADOS DE PAGOS'!E290 -> 278545.14 | G25: 10000 | H25: =+C25+D25+E25+F25+G25 -> 477452.18
A26: 2023 | B26: Junio | C26: 72655.11 | D26: 58886 | E26: 57365.93 | F26: =+'CONSOLIDADOS DE PAGOS'!E305 -> 286613.1 | G26: 20000 | H26: =+C26+D26+E26+F26+G26 -> 495520.14
A27: 2023 | B27: Julio | C27: 72655.11 | D27: 58886 | E27: 57365.93 | F27: =+'CONSOLIDADOS DE PAGOS'!E316 -> 189596.16 | H27: =+C27+D27+E27+F27+G27 -> 378503.2
A28: 2023 | B28: Agosto | C28: 72655.11 | D28: 58886 | E28: 57365.93 | F28: ='CONSOLIDADOS DE PAGOS'!E329 -> 403213.05 | G28: 10000 | H28: =+C28+D28+E28+F28+G28 -> 602120.09 | J28: Desplazamiento | K28: 44 | O28: Meses | P28: Sueldo
A29: 2023 | B29: Septiembre | C29: 72655.11 | D29: 58886 | E29: 57365.93 | F29: =+'CONSOLIDADOS DE PAGOS'!E343 -> 372549.78 | G29: 20000 | H29: =+C29+D29+E29+F29+G29 -> 581456.82 | J29: Acercamiento | K29: 54 | O29: {=OFFSET(SUELDOS!B3,SUELDOS!K28,0,SUELDOS!K29,1)} -> Marzo | P29: {=OFFSET(SUELDOS!H3,SUELDOS!K28,0,SUELDOS!K29,1)} -> 314171.59
A30: 2023 | B30: Octubre | C30: 72655.11 | D30: 58886 | E30: 57365.93 | F30: =+'CONSOLIDADOS DE PAGOS'!E357 -> 208166.22 | G30: 5000 | H30: =+C30+D30+E30+F30+G30 -> 402073.26 | O30: Abril | P30: 230005.25
A31: 2023 | B31: Noviembre | C31: 89000 | D31: 58886 | E31: 57365.93 | F31: =+'CONSOLIDADOS DE PAGOS'!E364 -> 285923.55 | G31: 0 | H31: =+C31+D31+E31+F31+G31 -> 491175.48 | O31: Mayo | P31: 218550.29
A32: 2023 | B32: Diciembre | C32: 72655.11 | D32: 58886 | E32: 57365.93 | F32: =+'CONSOLIDADOS DE PAGOS'!E373 -> 193207.5 | G32: 0 | H32: =+C32+D32+E32+F32+G32 -> 382114.54 | O32: Junio | P32: 212893.48
A33: 2024 | B33: Enero | C33: 72655.11 | D33: 58889.87 | E33: 57365.93 | F33: =+'CONSOLIDADOS DE PAGOS'!E380 -> 369322.2 | G33: 2000 | H33: =+C33+D33+E33+F33+G33 -> 560233.11 | O33: Julio | P33: 256216.09
A34: 2024 | B34: Febrero | C34: 72655.11 | D34: 58886 | E34: 57365.93 | F34: =+'CONSOLIDADOS DE PAGOS'!E388 -> 255045.6 | H34: =+C34+D34+E34+F34+G34 -> 443952.64 | O34: Agosto | P34: 332299.39
A35: 2024 | B35: Marzo | C35: 72655.11 | D35: 58886 | E35: 57365.93 | F35: 0 | H35: =+C35+D35+E35+F35+G35 -> 188907.04 | O35: Septiembre | P35: 399297.18
A36: 2024 | B36: Abril | C36: 72655.11 | D36: 58886 | E36: 57365.93 | F36: =+'CONSOLIDADOS DE PAGOS'!E401 -> 281355.3 | H36: =+C36+D36+E36+F36+G36 -> 470262.34 | O36: Octubre | P36: 309713.89
A37: 2024 | B37: Mayo | C37: 72655.11 | D37: 58886 | E37: 57365.93 | F37: =+'CONSOLIDADOS DE PAGOS'!E412 -> 143850.6 | H37: =+C37+D37+E37+F37+G37 -> 332757.64 | O37: Noviembre | P37: 208550.29
A38: 2024 | B38: Junio | C38: 72655.11 | D38: 58886 | E38: 57365.93 | F38: =+'CONSOLIDADOS DE PAGOS'!E424 -> 197221.71 | H38: =+C38+D38+E38+F38+G38 -> 386128.75 | O38: Diciembre/doble | P38: 265588.72
A39: 2024 | B39: Julio | C39: 72655.11 | D39: 58886 | E39: 57365.93 | F39: =+'CONSOLIDADOS DE PAGOS'!E430 -> 106668 | H39: =+C39+D39+E39+F39+G39 -> 295575.04 | O39: Diciembre | P39: 220443.68
A40: 2024 | B40: Agosto | C40: 72655.11 | D40: 58886 | E40: 57365.93 | F40: =+'CONSOLIDADOS DE PAGOS'!E441 -> 249540.59 | H40: =+C40+D40+E40+F40+G40 -> 438447.63 | O40: Enero | P40: 354326.49
A41: 2024 | B41: Septiembre | C41: 72655.11 | D41: 58886 | E41: 57365.93 | F41: ='CONSOLIDADOS DE PAGOS'!E454 -> 255935 | H41: =+C41+D41+E41+F41+G41 -> 444842.04 | O41: Febrero | P41: 270322.68
A42: 2024 | B42: Octubre | C42: 72655.11 | D42: 58886 | E42: 57365.93 | F42: ='CONSOLIDADOS DE PAGOS'!E464 -> 339408.9 | H42: =+C42+D42+E42+F42+G42 -> 528315.94 | O42: Marzo | P42: 276386.23
A43: 2024 | B43: Noviembre | C43: 89000 | D43: 58886 | E43: 57365.93 | F43: =+'CONSOLIDADOS DE PAGOS'!E474 -> 120828.32 | H43: =+C43+D43+E43+F43+G43 -> 326080.25 | O43: Abril | P43: 313009.92
A44: 2024 | B44: Diciembre | C44: 72655.11 | D44: 58886 | E44: 57365.93 | F44: =+'CONSOLIDADOS DE PAGOS'!E484 -> 43571.7 | H44: =+C44+D44+E44+F44+G44 -> 232478.74 | O44: Mayo | P44: 354606.98
A45: 2025 | B45: Enero | C45: =57960.94+23200.87 -> 81161.81 | D45: 64778.86 | E45: 62609.62 | F45: 0 | G45: 2000 | H45: =+C45+D45+E45+F45+G45 -> 210550.29 | O45: Junio | P45: 226980.68
A46: 2025 | B46: Febrero | C46: =57960.94+23200.87 -> 81161.81 | D46: 64778.86 | E46: 62609.62 | F46: =+'CONSOLIDADOS DE PAGOS'!E493 -> 76257 | H46: =+C46+D46+E46+F46+G46 -> 284807.29 | O46: Julio | P46: 226980.68
A47: 2025 | B47: Marzo | C47: =57960.94+23200.87 -> 81161.81 | D47: 64778.86 | E47: 62609.62 | F47: =+'CONSOLIDADOS DE PAGOS'!E500 -> 105621.3 | H47: =+C47+D47+E47+F47+G47 -> 314171.59 | O47: Agosto | P47: 226980.68
A48: 2025 | B48: Abril | C48: =57960.94+23200.87 -> 81161.81 | D48: 64778.86 | E48: 62609.62 | F48: =+'CONSOLIDADOS DE PAGOS'!E508 -> 21454.956 | H48: =+C48+D48+E48+F48+G48 -> 230005.25 | O48: Septiembre | P48: 226980.68
A49: 2025 | B49: Mayo | C49: =57960.94+23200.87 -> 81161.81 | D49: 64778.86 | E49: 62609.62 | F49: 10000 | H49: =+C49+D49+E49+F49+G49 -> 218550.29 | O49: Octubre | P49: 226980.68
A50: 2025 | B50: Junio | C50: =57960.94+23200.87 -> 81161.81 | D50: 64778.86 | E50: 62609.62 | F50: =+'CONSOLIDADOS DE PAGOS'!E514 -> 4343.193 | H50: =+C50+D50+E50+F50+G50 -> 212893.48 | O50: Noviembre | P50: 226980.68
A51: 2025 | B51: Julio | C51: =57960.94+23200.87 -> 81161.81 | D51: 64778.86 | E51: 62609.62 | F51: =+'CONSOLIDADOS DE PAGOS'!E524 -> 47665.8 | H51: =+C51+D51+E51+F51+G51 -> 256216.09 | O51: Diciembre | P51: 226980.68
A52: 2025 | B52: Agosto | C52: =57960.94+23200.87 -> 81161.81 | D52: 64778.86 | E52: 62609.62 | F52: =+'CONSOLIDADOS DE PAGOS'!E535 -> 123749.1 | H52: =+C52+D52+E52+F52+G52 -> 332299.39 | O52: Diciembre/doble | P52: 0
A53: 2025 | B53: Septiembre | C53: =57960.94+23200.87 -> 81161.81 | D53: 64778.86 | E53: 62609.62 | F53: =+'CONSOLIDADOS DE PAGOS'!E545 -> 190746.89 | H53: =+C53+D53+E53+F53+G53 -> 399297.18 | O53: 0 | P53: 3463087.4
A54: 2025 | B54: Octubre | C54: =57960.94+23200.87 -> 81161.81 | D54: 64778.86 | E54: 62609.62 | F54: =+'CONSOLIDADOS DE PAGOS'!E555 -> 101163.6 | H54: =+C54+D54+E54+F54+G54 -> 309713.89 | O54: 0 | P54: 0
A55: 2025 | B55: Noviembre | C55: =57960.94+23200.87 -> 81161.81 | D55: 64778.86 | E55: 62609.62 | F55: 0 | H55: =+C55+D55+E55+F55+G55 -> 208550.29 | O55: 0 | P55: 0
A56: 2025 | B56: Diciembre/doble | C56: 109552.5 | D56: 75575.34 | E56: 80460.88 | F56: 0 | H56: =+C56+D56+E56+F56+G56 -> 265588.72 | O56: 0 | P56: 0
A57: 2025 | B57: Diciembre | C57: =57960.94+23200.87 -> 81161.81 | D57: 71256.74 | E57: 68025.13 | F57: 0 | H57: =+C57+D57+E57+F57+G57 -> 220443.68 | O57: 0 | P57: 0
A58: 2026 | B58: Enero | C58: =57960.94+23200.87 -> 81161.81 | D58: 71256.74 | E58: 68025.13 | F58: =+'CONSOLIDADOS DE PAGOS'!E566 -> 133882.81 | H58: =+C58+D58+E58+F58+G58 -> 354326.49 | O58: 0 | P58: 0
A59: 2026 | B59: Febrero | C59: =57960.94+23200.87 -> 81161.81 | D59: 74819.58 | E59: 70999.29 | F59: =+'CONSOLIDADOS DE PAGOS'!E572 -> 36342 | G59: 7000 | H59: =+C59+D59+E59+F59+G59 -> 270322.68 | O59: 0 | P59: 0
A60: 2026 | B60: Marzo | C60: =57960.94+23200.87 -> 81161.81 | D60: 74819.58 | E60: 70999.29 | F60: =+'CONSOLIDADOS DE PAGOS'!E583 -> 39405.555 | G60: 10000 | H60: =+C60+D60+E60+F60+G60 -> 276386.23 | O60: 0 | P60: 0
A61: 2026 | B61: Abril | C61: =57960.94+23200.87 -> 81161.81 | D61: 74819.58 | E61: 70999.29 | F61: =+'CONSOLIDADOS DE PAGOS'!E592 -> 86029.236 | H61: =+C61+D61+E61+F61+G61 -> 313009.92 | O61: 0 | P61: 0
A62: 2026 | B62: Mayo | C62: =57960.94+23200.87 -> 81161.81 | D62: 74819.58 | E62: 70999.29 | F62: =+'CONSOLIDADOS DE PAGOS'!E602 -> 127626.3 | H62: =+C62+D62+E62+F62+G62 -> 354606.98 | O62: 0 | P62: 0
A63: 2026 | B63: Junio | C63: =57960.94+23200.87 -> 81161.81 | D63: 74819.58 | E63: 70999.29 | H63: =+C63+D63+E63+F63+G63 -> 226980.68 | O63: 0 | P63: 0
A64: 2026 | B64: Julio | C64: =57960.94+23200.87 -> 81161.81 | D64: 74819.58 | E64: 70999.29 | H64: =+C64+D64+E64+F64+G64 -> 226980.68 | O64: 0 | P64: 0
A65: 2026 | B65: Agosto | C65: =57960.94+23200.87 -> 81161.81 | D65: 74819.58 | E65: 70999.29 | H65: =+C65+D65+E65+F65+G65 -> 226980.68 | O65: 0 | P65: 0
A66: 2026 | B66: Septiembre | C66: =57960.94+23200.87 -> 81161.81 | D66: 74819.58 | E66: 70999.29 | H66: =+C66+D66+E66+F66+G66 -> 226980.68 | O66: 0 | P66: 0
A67: 2026 | B67: Octubre | C67: =57960.94+23200.87 -> 81161.81 | D67: 74819.58 | E67: 70999.29 | H67: =+C67+D67+E67+F67+G67 -> 226980.68 | O67: 0 | P67: 0
A68: 2026 | B68: Noviembre | C68: =57960.94+23200.87 -> 81161.81 | D68: 74819.58 | E68: 70999.29 | H68: =+C68+D68+E68+F68+G68 -> 226980.68 | O68: 0 | P68: 0
A69: 2026 | B69: Diciembre | C69: =57960.94+23200.87 -> 81161.81 | D69: 74819.58 | E69: 70999.29 | H69: =+C69+D69+E69+F69+G69 -> 226980.68 | O69: 0 | P69: 0
A70: 20226 | B70: Diciembre/doble | H70: =+C70+D70+E70+F70+G70 -> 0 | O70: 0 | P70: 0
H71: =SUM(H45:H57) -> 3463087.4 | O71: 0 | P71: 0
O72: 0 | P72: 0
O73: 0 | P73: 0
O74: 0 | P74: 0
O75: 0 | P75: 0
O76: 0 | P76: 0
O77: 0 | P77: 0
O78: 0 | P78: 0
O79: 0 | P79: 0
O80: 0 | P80: 0
O81: 0 | P81: 0
O82: 0 | P82: 0

Sheet Dashboard Sueldos
A1: DASHBOARD DE SUELDOS Y HONORARIOS
A2: Período: Julio 2021 — Diciembre 2026 | Incluye Proyecciones | Fuente: Hoja SUELDOS
A4: TOTAL PAGADO (Histórico) | C4: PROMEDIO MENSUAL | E4: MES MÁS ALTO | G4: MES MÁS BAJO | I4: TOTAL ERD (Histórico) | K4: TOTAL HONORARIOS (Histórico) | M4: PROY. TOTAL 2026 | O4: VARIACIÓN 2025 vs 2024
A5: =SUM(SUELDOS!H3:H57) -> 19932433 | C5: =AVERAGE(SUELDOS!H3:H57) -> 362407.88 | E5: =MAX(SUELDOS!H3:H57) -> 1018729.3 | G5: =_xlfn.MINIFS(SUELDOS!H3:H57,SUELDOS!H3:H57,">0") -> 188907.04 | I5: =SUM(SUELDOS!C3:C57) -> 3834802.6 | K5: =SUM(SUELDOS!F3:F57) -> 9458518.3 | M5: {=SUMPRODUCT((SUELDOS!A3:A68=2026)*SUELDOS!H3:H68)} -> 2930536.4 | O5: {=SUMPRODUCT((SUELDOS!A3:A57=2025)*SUELDOS!H3:H57)/SUMPRODUCT((SUELDOS!A3:A57=2024)*SUELDOS!H3:H57)-1} -> -0.25492653
A7: RESUMEN ANUAL | J7: COMPOSICIÓN PROMEDIO DEL INGRESO MENSUAL | N7: GRÁFICO ANUAL | Q7: DESGLOSE ANUAL
A8: Año | B8: ERD | C8: MARVESA | D8: HMNSA | E8: Honorarios | F8: Consultas | G8: Total Año | H8: Var. vs Anterior | J8: Componente | K8: Promedio Mensual | L8: % del Total | N8: Año | O8: Total | Q8: Año | R8: ERD | S8: MARVESA | T8: HMNSA | U8: Honorarios
A9: 2021 | B9: {=SUMPRODUCT((SUELDOS!A$3:A$68=2021)*SUELDOS!C$3:C$68)} -> 196700 | C9: {=SUMPRODUCT((SUELDOS!A$3:A$68=2021)*SUELDOS!D$3:D$68)} -> 351221.52 | D9: {=SUMPRODUCT((SUELDOS!A$3:A$68=2021)*SUELDOS!E$3:E$68)} -> 255218.28 | E9: {=SUMPRODUCT((SUELDOS!A$3:A$68=2021)*SUELDOS!F$3:F$68)} -> 935284.77 | F9: {=SUMPRODUCT((SUELDOS!A$3:A$68=2021)*SUELDOS!G$3:G$68)} -> 0 | G9: {=SUMPRODUCT((SUELDOS!A$3:A$68=2021)*SUELDOS!H$3:H$68)} -> 1738424.6 | H9: — | J9: ERD | K9: =AVERAGE(SUELDOS!C$3:C$56) -> 69511.867 | L9: =K9/SUM(K$9:K$13) -> 0.18639814 | N9: =A9 -> 2021 | O9: =G9 -> 1738424.6 | Q9: =A9 -> 2021 | R9: =B9 -> 196700 | S9: =C9 -> 351221.52 | T9: =D9 -> 255218.28 | U9: =E9 -> 935284.77
A10: 2022 | B10: {=SUMPRODUCT((SUELDOS!A$3:A$68=2022)*SUELDOS!C$3:C$68)} -> 778195.99 | C10: {=SUMPRODUCT((SUELDOS!A$3:A$68=2022)*SUELDOS!D$3:D$68)} -> 722635.87 | D10: {=SUMPRODUCT((SUELDOS!A$3:A$68=2022)*SUELDOS!E$3:E$68)} -> 688391.16 | E10: {=SUMPRODUCT((SUELDOS!A$3:A$68=2022)*SUELDOS!F$3:F$68)} -> 2586165.7 | F10: {=SUMPRODUCT((SUELDOS!A$3:A$68=2022)*SUELDOS!G$3:G$68)} -> 0 | G10: {=SUMPRODUCT((SUELDOS!A$3:A$68=2022)*SUELDOS!H$3:H$68)} -> 4775388.7 | H10: =IF(G9=0,"—",G10/G9-1) -> 1.7469634 | J10: MARVESA | K10: =AVERAGE(SUELDOS!D$3:D$56) -> 60653.184 | L10: =K10/SUM(K$9:K$13) -> 0.16264332 | N10: =A10 -> 2022 | O10: =G10 -> 4775388.7 | Q10: =A10 -> 2022 | R10: =B10 -> 778195.99 | S10: =C10 -> 722635.87 | T10: =D10 -> 688391.16 | U10: =E10 -> 2586165.7
A11: 2023 | B11: {=SUMPRODUCT((SUELDOS!A$3:A$68=2023)*SUELDOS!C$3:C$68)} -> 888206.21 | C11: {=SUMPRODUCT((SUELDOS!A$3:A$68=2023)*SUELDOS!D$3:D$68)} -> 706635.87 | D11: {=SUMPRODUCT((SUELDOS!A$3:A$68=2023)*SUELDOS!E$3:E$68)} -> 688391.16 | E11: {=SUMPRODUCT((SUELDOS!A$3:A$68=2023)*SUELDOS!F$3:F$68)} -> 2893318.1 | F11: {=SUMPRODUCT((SUELDOS!A$3:A$68=2023)*SUELDOS!G$3:G$68)} -> 131000 | G11: {=SUMPRODUCT((SUELDOS!A$3:A$68=2023)*SUELDOS!H$3:H$68)} -> 5307551.3 | H11: =IF(G10=0,"—",G11/G10-1) -> 0.1114386 | J11: HMNSA | K11: =AVERAGE(SUELDOS!E$3:E$56) -> 57214.046 | L11: =K11/SUM(K$9:K$13) -> 0.15342117 | N11: =A11 -> 2023 | O11: =G11 -> 5307551.3 | Q11: =A11 -> 2023 | R11: =B11 -> 888206.21 | S11: =C11 -> 706635.87 | T11: =D11 -> 688391.16 | U11: =E11 -> 2893318.1
A12: 2024 | B12: {=SUMPRODUCT((SUELDOS!A$3:A$68=2024)*SUELDOS!C$3:C$68)} -> 888206.21 | C12: {=SUMPRODUCT((SUELDOS!A$3:A$68=2024)*SUELDOS!D$3:D$68)} -> 706635.87 | D12: {=SUMPRODUCT((SUELDOS!A$3:A$68=2024)*SUELDOS!E$3:E$68)} -> 688391.16 | E12: {=SUMPRODUCT((SUELDOS!A$3:A$68=2024)*SUELDOS!F$3:F$68)} -> 2362747.9 | F12: {=SUMPRODUCT((SUELDOS!A$3:A$68=2024)*SUELDOS!G$3:G$68)} -> 2000 | G12: {=SUMPRODUCT((SUELDOS!A$3:A$68=2024)*SUELDOS!H$3:H$68)} -> 4647981.2 | H12: =IF(G11=0,"—",G12/G11-1) -> -0.12427014 | J12: HONORARIOS | K12: =AVERAGE(SUELDOS!F$3:F$56) -> 175157.75 | L12: =K12/SUM(K$9:K$13) -> 0.46969071 | N12: =A12 -> 2024 | O12: =G12 -> 4647981.2 | Q12: =A12 -> 2024 | R12: =B12 -> 888206.21 | S12: =C12 -> 706635.87 | T12: =D12 -> 688391.16 | U12: =E12 -> 2362747.9
A13: 2025 | B13: {=SUMPRODUCT((SUELDOS!A$3:A$68=2025)*SUELDOS!C$3:C$68)} -> 1083494.2 | C13: {=SUMPRODUCT((SUELDOS!A$3:A$68=2025)*SUELDOS!D$3:D$68)} -> 859399.54 | D13: {=SUMPRODUCT((SUELDOS!A$3:A$68=2025)*SUELDOS!E$3:E$68)} -> 837191.83 | E13: {=SUMPRODUCT((SUELDOS!A$3:A$68=2025)*SUELDOS!F$3:F$68)} -> 681001.84 | F13: {=SUMPRODUCT((SUELDOS!A$3:A$68=2025)*SUELDOS!G$3:G$68)} -> 2000 | G13: {=SUMPRODUCT((SUELDOS!A$3:A$68=2025)*SUELDOS!H$3:H$68)} -> 3463087.4 | H13: =IF(G12=0,"—",G13/G12-1) -> -0.25492653 | J13: CONSULTAS | K13: =AVERAGE(SUELDOS!G$3:G$56) -> 10384.615 | L13: =K13/SUM(K$9:K$13) -> 0.027846656 | N13: =A13 -> 2025 | O13: =G13 -> 3463087.4 | Q13: =A13 -> 2025 | R13: =B13 -> 1083494.2 | S13: =C13 -> 859399.54 | T13: =D13 -> 837191.83 | U13: =E13 -> 681001.84
A14: 2026 | B14: {=SUMPRODUCT((SUELDOS!A$3:A$68=2026)*SUELDOS!C$3:C$68)} -> 892779.91 | C14: {=SUMPRODUCT((SUELDOS!A$3:A$68=2026)*SUELDOS!D$3:D$68)} -> 819452.54 | D14: {=SUMPRODUCT((SUELDOS!A$3:A$68=2026)*SUELDOS!E$3:E$68)} -> 778018.03 | E14: {=SUMPRODUCT((SUELDOS!A$3:A$68=2026)*SUELDOS!F$3:F$68)} -> 423285.9 | F14: {=SUMPRODUCT((SUELDOS!A$3:A$68=2026)*SUELDOS!G$3:G$68)} -> 17000 | G14: {=SUMPRODUCT((SUELDOS!A$3:A$68=2026)*SUELDOS!H$3:H$68)} -> 2930536.4 | H14: =IF(G13=0,"—",G14/G13-1) -> -0.15377927 | J14: TOTAL | K14: =SUM(K9:K13) -> 372921.46 | L14: =SUM(L9:L13) -> 1 | N14: =A14 -> 2026 | O14: =G14 -> 2930536.4 | Q14: =A14 -> 2026 | R14: =B14 -> 892779.91 | S14: =C14 -> 819452.54 | T14: =D14 -> 778018.03 | U14: =E14 -> 423285.9
A16: EVOLUCIÓN MENSUAL — HISTÓRICO + PROYECCIONES | J16: ANÁLISIS DE PROYECCIONES 2026 | N16: COMPOSICIÓN
A17: Período | B17: Salario Base | C17: Honorarios | D17: Consultas | E17: Total | J17: Concepto | K17: 2025 Real | L17: 2026 Proyectado | N17: Componente | O17: Promedio
A18: =SUELDOS!B3&" "&SUELDOS!A3 -> Julio 2021 | B18: =SUELDOS!C3+SUELDOS!D3+SUELDOS!E3 -> 129346.49 | C18: =SUELDOS!F3 -> 121000 | D18: =SUELDOS!G3 -> 0 | E18: =SUELDOS!H3 -> 250346.49 | J18: Salario Base (ERD+MARV+HMNSA) | K18: {=SUMPRODUCT((SUELDOS!A3:A57=2025)*(SUELDOS!C3:C57+SUELDOS!D3:D57+SUELDOS!E3:E57))} -> 2780085.6 | L18: {=SUMPRODUCT((SUELDOS!A3:A68=2026)*(SUELDOS!C3:C68+SUELDOS!D3:D68+SUELDOS!E3:E68))} -> 2490250.5 | N18: =J9 -> ERD | O18: =K9 -> 69511.867
A19: =SUELDOS!B4&" "&SUELDOS!A4 -> Agosto 2021 | B19: =SUELDOS!C4+SUELDOS!D4+SUELDOS!E4 -> 129346.49 | C19: =SUELDOS!F4 -> 61445.25 | D19: =SUELDOS!G4 -> 0 | E19: =SUELDOS!H4 -> 190791.74 | J19: Honorarios (ARS) | K19: {=SUMPRODUCT((SUELDOS!A3:A57=2025)*SUELDOS!F3:F57)} -> 681001.84 | L19: {=SUMPRODUCT((SUELDOS!A3:A68=2026)*SUELDOS!F3:F68)} -> 423285.9 | N19: =J10 -> MARVESA | O19: =K10 -> 60653.184
A20: =SUELDOS!B5&" "&SUELDOS!A5 -> Septiembre 2021 | B20: =SUELDOS!C5+SUELDOS!D5+SUELDOS!E5 -> 129346.49 | C20: =SUELDOS!F5 -> 331913.01 | D20: =SUELDOS!G5 -> 0 | E20: =SUELDOS!H5 -> 461259.5 | J20: Consultas | K20: {=SUMPRODUCT((SUELDOS!A3:A57=2025)*SUELDOS!G3:G57)} -> 2000 | L20: {=SUMPRODUCT((SUELDOS!A3:A68=2026)*SUELDOS!G3:G68)} -> 17000 | N20: =J11 -> HMNSA | O20: =K11 -> 57214.046
A21: =SUELDOS!B6&" "&SUELDOS!A6 -> Octubre 2021 | B21: =SUELDOS!C6+SUELDOS!D6+SUELDOS!E6 -> 129346.49 | C21: =SUELDOS!F6 -> 195013.04 | D21: =SUELDOS!G6 -> 0 | E21: =SUELDOS!H6 -> 324359.53 | J21: TOTAL | K21: {=SUMPRODUCT((SUELDOS!A3:A57=2025)*SUELDOS!H3:H57)} -> 3463087.4 | L21: {=SUMPRODUCT((SUELDOS!A3:A68=2026)*SUELDOS!H3:H68)} -> 2930536.4 | N21: =J12 -> HONORARIOS | O21: =K12 -> 175157.75
A22: =SUELDOS!B7&" "&SUELDOS!A7 -> Noviembre 2021 | B22: =SUELDOS!C7+SUELDOS!D7+SUELDOS!E7 -> 143086.92 | C22: =SUELDOS!F7 -> 123506.96 | D22: =SUELDOS!G7 -> 0 | E22: =SUELDOS!H7 -> 266593.88 | J22: Variación % (2026 vs 2025) | K22: ="" | L22: =L21/K21-1 -> -0.15377927 | N22: =J13 -> CONSULTAS | O22: =K13 -> 10384.615
A23: =SUELDOS!B8&" "&SUELDOS!A8 -> Diciembre 2021 | B23: =SUELDOS!C8+SUELDOS!D8+SUELDOS!E8 -> 142666.92 | C23: =SUELDOS!F8 -> 102406.5 | D23: =SUELDOS!G8 -> 0 | E23: =SUELDOS!H8 -> 245073.42
A24: =SUELDOS!B9&" "&SUELDOS!A9 -> Enero 2022 | B24: =SUELDOS!C9+SUELDOS!D9+SUELDOS!E9 -> 142755.8 | C24: =SUELDOS!F9 -> 80956.971 | D24: =SUELDOS!G9 -> 0 | E24: =SUELDOS!H9 -> 223712.77
A25: =SUELDOS!B10&" "&SUELDOS!A10 -> Febrero 2022 | B25: =SUELDOS!C10+SUELDOS!D10+SUELDOS!E10 -> 142751.93 | C25: =SUELDOS!F10 -> 75409.65 | D25: =SUELDOS!G10 -> 0 | E25: =SUELDOS!H10 -> 218161.58
A26: =SUELDOS!B11&" "&SUELDOS!A11 -> Marzo 2022 | B26: =SUELDOS!C11+SUELDOS!D11+SUELDOS!E11 -> 203551.93 | C26: =SUELDOS!F11 -> 129321 | D26: =SUELDOS!G11 -> 0 | E26: =SUELDOS!H11 -> 332872.93
A27: =SUELDOS!B12&" "&SUELDOS!A12 -> Abril 2022 | B27: =SUELDOS!C12+SUELDOS!D12+SUELDOS!E12 -> 188907.04 | C27: =SUELDOS!F12 -> 169756.02 | D27: =SUELDOS!G12 -> 0 | E27: =SUELDOS!H12 -> 358663.06
A28: =SUELDOS!B13&" "&SUELDOS!A13 -> Mayo 2022 | B28: =SUELDOS!C13+SUELDOS!D13+SUELDOS!E13 -> 188907.04 | C28: =SUELDOS!F13 -> 130658.4 | D28: =SUELDOS!G13 -> 0 | E28: =SUELDOS!H13 -> 319565.44
A29: =SUELDOS!B14&" "&SUELDOS!A14 -> Junio 2022 | B29: =SUELDOS!C14+SUELDOS!D14+SUELDOS!E14 -> 188907.04 | C29: =SUELDOS!F14 -> 39941.1 | D29: =SUELDOS!G14 -> 0 | E29: =SUELDOS!H14 -> 228848.14
A30: =SUELDOS!B15&" "&SUELDOS!A15 -> Julio 2022 | B30: =SUELDOS!C15+SUELDOS!D15+SUELDOS!E15 -> 188907.04 | C30: =SUELDOS!F15 -> 65691 | D30: =SUELDOS!G15 -> 0 | E30: =SUELDOS!H15 -> 254598.04
A31: =SUELDOS!B16&" "&SUELDOS!A16 -> Agosto 2022 | B31: =SUELDOS!C16+SUELDOS!D16+SUELDOS!E16 -> 188907.04 | C31: =SUELDOS!F16 -> 246284.87 | D31: =SUELDOS!G16 -> 0 | E31: =SUELDOS!H16 -> 435191.91
A32: =SUELDOS!B17&" "&SUELDOS!A17 -> Septiembre 2022 | B32: =SUELDOS!C17+SUELDOS!D17+SUELDOS!E17 -> 188907.04 | C32: =SUELDOS!F17 -> 829822.24 | D32: =SUELDOS!G17 -> 0 | E32: =SUELDOS!H17 -> 1018729.3
A33: =SUELDOS!B18&" "&SUELDOS!A18 -> Octubre 2022 | B33: =SUELDOS!C18+SUELDOS!D18+SUELDOS!E18 -> 188907.04 | C33: =SUELDOS!F18 -> 200775.01 | D33: =SUELDOS!G18 -> 0 | E33: =SUELDOS!H18 -> 389682.05
A34: =SUELDOS!B19&" "&SUELDOS!A19 -> Noviembre 2022 | B34: =SUELDOS!C19+SUELDOS!D19+SUELDOS!E19 -> 188907.04 | C34: =SUELDOS!F19 -> 308422.82 | D34: =SUELDOS!G19 -> 0 | E34: =SUELDOS!H19 -> 497329.86
... A71: =SUELDOS!B56&" "&SUELDOS!A56 -> Diciembre/doble 2025 | B71: =SUELDOS!C56+SUELDOS!D56+SUELDOS!E56 -> 265588.72 | C71: =SUELDOS!F56 -> 0 | D71: =SUELDOS!G56 -> 0 | E71: =SUELDOS!H56 -> 265588.72
A72: 📋 NOTAS Y HALLAZGOS CLAVE
A73: 1. | B73: SENASA fue la ARS más rentable en honorarios (61% del total de pagos ARS). El pico fue septiembre 2022 ($926K facturados).
A74: 2. | B74: Los salarios base (ERD+MARVESA+HMNSA) se incrementaron ~15% en 2025 vs 2024, pasando de $688K a $837K anuales para HMNSA.
A75: 3. | B75: Los honorarios por ARS son altamente volátiles — varían de $0 a $926K por mes, creando alta incertidumbre en el ingreso total.
A76: 4. | B76: 2023 fue el año pico de ingresos totales ($5.31M), impulsado por honorarios ARS consistentemente altos todo el año.
A77: 5. | B77: PROYECCIÓN 2026: Caída estimada de -23.2% vs 2025, principalmente porque los honorarios de Mar-Dic 2026 aún no tienen valores.
A78: 6. | B78: Las filas en AMARILLO (Mar-Dic 2026) representan proyecciones basadas solo en salario base fijo, sin honorarios estimados.
A79: 7. | B79: RIESGO CLAVE: Los honorarios representan ~47% del ingreso total promedio — alta dependencia de la facturación a aseguradoras.
A80: 8. | B80: Las consultas privadas apenas aportan ~2.8% del ingreso — oportunidad de crecimiento si se incrementa esta fuente.
A81: =SUELDOS!B66&" "&SUELDOS!A66 -> Septiembre 2026 | B81: =SUELDOS!C66+SUELDOS!D66+SUELDOS!E66 -> 226980.68 | C81: =SUELDOS!F66 -> 0 | D81: =SUELDOS!G66 -> 0 | E81: =SUELDOS!H66 -> 226980.68
A82: =SUELDOS!B67&" "&SUELDOS!A67 -> Octubre 2026 | B82: =SUELDOS!C67+SUELDOS!D67+SUELDOS!E67 -> 226980.68 | C82: =SUELDOS!F67 -> 0 | D82: =SUELDOS!G67 -> 0 | E82: =SUELDOS!H67 -> 226980.68
A83: =SUELDOS!B68&" "&SUELDOS!A68 -> Noviembre 2026 | B83: =SUELDOS!C68+SUELDOS!D68+SUELDOS!E68 -> 226980.68 | C83: =SUELDOS!F68 -> 0 | D83: =SUELDOS!G68 -> 0 | E83: =SUELDOS!H68 -> 226980.68

Sheet Leyenda
B2: Columna1 | C2: Columna2 | E2: RNC | F2: Proveedor
B3: 1 | C3: GASTO DE PERSONAL | E3: 00100796911 | F3: Dr. Alejandro Soto Mendez
B4: 2 | C4: GASTOS POR TRABAJOS, SUMINISTROS Y SERVICIOS | E4: 00102420817 | F4: Manuel de Js. Sosa Sanchez
B5: 3 | C5: ARRENDAMIENTOS | E5: 01100286119 | F5: Lorenzo Ernesto Otaño Santiago
B6: 4 | C6: GASTOS DE ACTIVOS FIJO | E6: 401010062 | F6: Banco de Reservas de la República Dominicana Banco de Servicios Multiples//BanReservas
B7: 5 | C7: GASTOS DE REPRESENTACION | E7: 101136792 | F7: Banco Multiple BHD León, S. A.
B8: 6 | C8: OTRAS DEDUCCIONES ADMITIDAS | E8: 101010632 | F8: Banco Popular Dominicano, S. A. Banco Multiple
B9: 7 | C9: GASTOS FINANCIEROS | E9: 101043598 | F9: Banco Dominicano del Progreso, S. A.//Banco Multiple
B10: 8 | C10: GASTOS EXTRAORDINARIOS | E10: 101001577 | F10: CLARO//CODETEL
B11: 9 | C11: C.Y GTOS. QUE FORMAN PARTE DEL COSTO DE VENTA | E11: 101821248 | F11: EDESUR
B12: 10 | C12: ADQUISICIONES DE ACTIVOS | E12: 101502525 | F12: Tricom, S.A.
B13: 11 | C13: GASTOS DE SEGUROS | E13: 101019921 | F13: Centro Cuesta Nacional S.A.S.//Supermercados Nacional//Casa Cuesta//Ferretería Cuesta//JUMBO//Bebemundo
B14: 12 | C14: GASTOS MENORES | E14: 101796822 | F14: Grupo Ramos, S. A.//Super Pola//La Sirena
E15: 101793198 | F15: Mercatodo S.A.S.//Supermercados La Cadena
E16: 101602465 | F16: Bravo, S.A.//Supermercados Bravo
E17: 101035129 | F17: Supermercado El Dragon de Oro S. A.
E18: 101617871 | F18: El Cordel S.R.L.//Supermercado La Placita
E19: 101801875 | F19: Pricesmart Dominicana S. A.
E20: 101171111 | F20: Plaza Lama, S. A.
E21: 101532483 | F21: Hipermercados, Ole, S. A.
E22: 130265135 | F22: Inversiones Inmobiliarias E & D C. por A.//Supermercado Caribe
E23: 101600225 | F23: Comercial Gala, S.R.L. / Supermercado Gala
E24: 102000476 | F24: Daniel Espinal C. por A.//Farmax
E25: 101040302 | F25: Farmaco Quimica Nacional, S.A.//Farmaconal
E26: 101871865 | F26: Grupo Carol, S. A.//Farmacia Carol
... E118: 101819103 | F118: Centro EXPLORA de Educación Inicial, S.R.L.
E119: 22600032746 | F119: Jaime Velez Bello
E120: 00101133635 | F120: Hector Antonio Pereyra Espaillat//Pereyra Espaillat & Asocs.
E121: 07300002750 | F121: Maura Minaya
E122: 00101974616 | F122: Jenifer Duarte
E123: 00000000001 | F123: Bibiana Perez
E124: 00000000002 | F124: Delmaris Ramirez
E125: 00000000003 | F125: Dra. Martinez
E126: 00000000004 | F126: Mildred Jimenez
E127: 00000000005 | F127: Natalia Montero
E128: 130777871 | F128: Farmaland, S.R.L.
E129: 101605391 | F129: Hizpizza, S.R.L./Domino s Pizza
E130: 130060304 | F130: Tapas de Plata, S.R.L.
E131: 130950946 | F131: Farmacia del Parque, S.R.L.
... E315: 130652912 | F315: SUPER FARMACIA JOSE NEPO SRL
E316: 430078549 | F316: Fundacion Cristiana de Consolacion y Ayuda
E317: 101025794 | F317: Envasadora Gas Caribe Principal
E318: 131233465 | F318: NOCCIOLA FOOD HALL SRL
E319: 101820217 | F319: EDEESTE
E320: 130196796 | F320: ACADEMIA EUROPEA
E321: 430030341 | F321: COLEGIO SANTA ROSA DE LIMA
E322: 101651555 | F322: INDY PLAZA
E323: 132345657 | F323: MARYSOF IS GOOD SRL
E324: 131208371 | F324: U.S. POLO ASSN
E325: 131341136 | F325: Little Ceasars Pizza Alma Rosa
E326: 131436781 | F326: Floremch Importaciones SRL
E327: 131649122 | F327: Abastek Marketing SRL
E328: 131039499 | F328: Farmacia VIP Mendo SRL
... E333: 133025515 | F333: Ferreziro SRL

Sheet Gastos2024
A1: RNC o Cédula | B1: Tipo Id | C1: Tipo Bienes y Servicios Comprados | D1: Descripción | E1: NCF | F1: Fecha Comprobante | G1: Mes | H1: Dia | I1: Dia Semana | J1: Fecha | K1: Miembro Familia | L1: Producto | M1: Monto Facturado en Servicios | N1: Monto Facturado en Bienes | O1: Total Monto Facturado | P1: ITBIS Facturado | Q1: ITBIS Retenido | R1: Monto Propina Legal | S1: Forma de Pago | T1: Suplidor
A2: 430078549 | B2: 1 | C2: 12 | D2: =IF(C2=1,Leyenda!$C$3,IF(C2=2,Leyenda!$C$4,IF(C2=3,Leyenda!$C$5,IF(C2=4,Leyenda!$C$6,IF(C2=5,Leyenda!$C$7,IF(C2=6,Leyenda!$C$8,IF(C2=7,Leyenda!$C$9,IF(C2=8,Leyenda!$C$10," "))))))))&IF(C2=9,Leyenda!$C$11,IF(C2=10,Leyenda!$C$12,IF(C2=11,Leyenda!$C$13,IF(C2=12,Leyenda!$C$14," ")))) -> GASTOS MENORES | E2: 0 | F2: 45702 | G2: =TEXT(F2,"MMMM") -> febrero | H2: 14 | I2: =TEXT(gastos[[#This Row],[Fecha]],"DDDD") -> viernes | J2: =DATE(YEAR(F2),MONTH(F2),H2) -> 45702 | K2: Yahelis | L2: Seguimiento Odontologico Yahelis | M2: 1000 | N2: 0 | O2: =SUM(M2:N2) -> 1000 | P2: 0 | Q2: 0 | R2: 0 | S2: Tarjata de credito | T2: =IFERROR(VLOOKUP($A2,Tabla3[#All],2,0),"no esta registrado") -> Fundacion Cristiana de Consolacion y Ayuda
A3: 0 | B3: 1 | C3: 12 | D3: =IF(C3=1,Leyenda!$C$3,IF(C3=2,Leyenda!$C$4,IF(C3=3,Leyenda!$C$5,IF(C3=4,Leyenda!$C$6,IF(C3=5,Leyenda!$C$7,IF(C3=6,Leyenda!$C$8,IF(C3=7,Leyenda!$C$9,IF(C3=8,Leyenda!$C$10," "))))))))&IF(C3=9,Leyenda!$C$11,IF(C3=10,Leyenda!$C$12,IF(C3=11,Leyenda!$C$13,IF(C3=12,Leyenda!$C$14," ")))) -> GASTOS MENORES | E3: 0 | F3: 45745 | G3: =TEXT(F3,"MMMM") -> marzo | H3: 29 | I3: =TEXT(gastos[[#This Row],[Fecha]],"DDDD") -> sábado | J3: =DATE(YEAR(F3),MONTH(F3),H3) -> 45745 | K3: Andres | L3: Liga de baseball | M3: 2000 | N3: 0 | O3: =SUM(M3:N3) -> 2000 | P3: 0 | Q3: 0 | R3: 0 | S3: Transferencia bancaria | T3: =IFERROR(VLOOKUP($A3,Tabla3[#All],2,0),"no esta registrado") -> no esta registrado
A4: 0 | B4: 1 | C4: 12 | D4: =IF(C4=1,Leyenda!$C$3,IF(C4=2,Leyenda!$C$4,IF(C4=3,Leyenda!$C$5,IF(C4=4,Leyenda!$C$6,IF(C4=5,Leyenda!$C$7,IF(C4=6,Leyenda!$C$8,IF(C4=7,Leyenda!$C$9,IF(C4=8,Leyenda!$C$10," "))))))))&IF(C4=9,Leyenda!$C$11,IF(C4=10,Leyenda!$C$12,IF(C4=11,Leyenda!$C$13,IF(C4=12,Leyenda!$C$14," ")))) -> GASTOS MENORES | E4: 0 | F4: 45714 | G4: =TEXT(F4,"MMMM") -> febrero | H4: 29 | I4: =TEXT(gastos[[#This Row],[Fecha]],"DDDD") -> sábado | J4: =DATE(YEAR(F4),MONTH(F4),H4) -> 45717 | K4: Javier | L4: Liga de baseball | M4: 2000 | N4: 0 | O4: =SUM(M4:N4) -> 2000 | P4: 0 | Q4: 0 | R4: 0 | S4: Transferencia bancaria | T4: =IFERROR(VLOOKUP($A4,Tabla3[#All],2,0),"no esta registrado") -> no esta registrado
A5: 0 | B5: 1 | C5: 12 | D5: =IF(C5=1,Leyenda!$C$3,IF(C5=2,Leyenda!$C$4,IF(C5=3,Leyenda!$C$5,IF(C5=4,Leyenda!$C$6,IF(C5=5,Leyenda!$C$7,IF(C5=6,Leyenda!$C$8,IF(C5=7,Leyenda!$C$9,IF(C5=8,Leyenda!$C$10," "))))))))&IF(C5=9,Leyenda!$C$11,IF(C5=10,Leyenda!$C$12,IF(C5=11,Leyenda!$C$13,IF(C5=12,Leyenda!$C$14," ")))) -> GASTOS MENORES | E5: 0 | F5: 45714 | G5: =TEXT(F5,"MMMM") -> febrero | H5: 29 | I5: =TEXT(gastos[[#This Row],[Fecha]],"DDDD") -> sábado | J5: =DATE(YEAR(F5),MONTH(F5),H5) -> 45717 | K5: Andres | L5: Liga de baseball | M5: 2000 | N5: 0 | O5: =SUM(M5:N5) -> 2000 | P5: 0 | Q5: 0 | R5: 0 | S5: Transferencia bancaria | T5: =IFERROR(VLOOKUP($A5,Tabla3[#All],2,0),"no esta registrado") -> no esta registrado
A6: 0 | B6: 1 | C6: 12 | D6: =IF(C6=1,Leyenda!$C$3,IF(C6=2,Leyenda!$C$4,IF(C6=3,Leyenda!$C$5,IF(C6=4,Leyenda!$C$6,IF(C6=5,Leyenda!$C$7,IF(C6=6,Leyenda!$C$8,IF(C6=7,Leyenda!$C$9,IF(C6=8,Leyenda!$C$10," "))))))))&IF(C6=9,Leyenda!$C$11,IF(C6=10,Leyenda!$C$12,IF(C6=11,Leyenda!$C$13,IF(C6=12,Leyenda!$C$14," ")))) -> GASTOS MENORES | E6: 0 | F6: 45683 | G6: =TEXT(F6,"MMMM") -> enero | H6: 29 | I6: =TEXT(gastos[[#This Row],[Fecha]],"DDDD") -> miércoles | J6: =DATE(YEAR(F6),MONTH(F6),H6) -> 45686 | K6: Javier | L6: Liga de baseball | M6: 2000 | N6: 0 | O6: =SUM(M6:N6) -> 2000 | P6: 0 | Q6: 0 | R6: 0 | S6: Transferencia bancaria | T6: =IFERROR(VLOOKUP($A6,Tabla3[#All],2,0),"no esta registrado") -> no esta registrado
A7: 0 | B7: 1 | C7: 12 | D7: =IF(C7=1,Leyenda!$C$3,IF(C7=2,Leyenda!$C$4,IF(C7=3,Leyenda!$C$5,IF(C7=4,Leyenda!$C$6,IF(C7=5,Leyenda!$C$7,IF(C7=6,Leyenda!$C$8,IF(C7=7,Leyenda!$C$9,IF(C7=8,Leyenda!$C$10," "))))))))&IF(C7=9,Leyenda!$C$11,IF(C7=10,Leyenda!$C$12,IF(C7=11,Leyenda!$C$13,IF(C7=12,Leyenda!$C$14," ")))) -> GASTOS MENORES | E7: 0 | F7: 45683 | G7: =TEXT(F7,"MMMM") -> enero | H7: 29 | I7: =TEXT(gastos[[#This Row],[Fecha]],"DDDD") -> miércoles | J7: =DATE(YEAR(F7),MONTH(F7),H7) -> 45686 | K7: Andres | L7: Liga de baseball | M7: 2000 | N7: 0 | O7: =SUM(M7:N7) -> 2000 | P7: 0 | Q7: 0 | R7: 0 | S7: Transferencia bancaria | T7: =IFERROR(VLOOKUP($A7,Tabla3[#All],2,0),"no esta registrado") -> no esta registrado
A8: 0 | B8: 1 | C8: 12 | D8: =IF(C8=1,Leyenda!$C$3,IF(C8=2,Leyenda!$C$4,IF(C8=3,Leyenda!$C$5,IF(C8=4,Leyenda!$C$6,IF(C8=5,Leyenda!$C$7,IF(C8=6,Leyenda!$C$8,IF(C8=7,Leyenda!$C$9,IF(C8=8,Leyenda!$C$10," "))))))))&IF(C8=9,Leyenda!$C$11,IF(C8=10,Leyenda!$C$12,IF(C8=11,Leyenda!$C$13,IF(C8=12,Leyenda!$C$14," ")))) -> GASTOS MENORES | E8: 0 | F8: 45745 | G8: =TEXT(F8,"MMMM") -> marzo | H8: 29 | I8: =TEXT(gastos[[#This Row],[Fecha]],"DDDD") -> sábado | J8: =DATE(YEAR(F8),MONTH(F8),H8) -> 45745 | K8: Javier | L8: Liga de baseball | M8: 2000 | N8: 0 | O8: =SUM(M8:N8) -> 2000 | P8: 0 | Q8: 0 | R8: 0 | S8: Transferencia bancaria | T8: =IFERROR(VLOOKUP($A8,Tabla3[#All],2,0),"no esta registrado") -> no esta registrado
A9: 131233465 | B9: 1 | C9: 2 | D9: =IF(C9=1,Leyenda!$C$3,IF(C9=2,Leyenda!$C$4,IF(C9=3,Leyenda!$C$5,IF(C9=4,Leyenda!$C$6,IF(C9=5,Leyenda!$C$7,IF(C9=6,Leyenda!$C$8,IF(C9=7,Leyenda!$C$9,IF(C9=8,Leyenda!$C$10," "))))))))&IF(C9=9,Leyenda!$C$11,IF(C9=10,Leyenda!$C$12,IF(C9=11,Leyenda!$C$13,IF(C9=12,Leyenda!D74," ")))) -> GASTOS POR TRABAJOS, SUMINISTROS Y SERVICIOS | E9: B0100045296 | F9: 45701 | G9: =TEXT(F9,"MMMM") -> febrero | H9: 13 | I9: =TEXT(gastos[[#This Row],[Fecha]],"DDDD") -> jueves | J9: =DATE(YEAR(F9),MONTH(F9),H9) -> 45701 | K9: Ernesto | L9: Café | M9: 500 | N9: 0 | O9: =SUM(M9:N9) -> 500 | P9: 90 | Q9: 0 | R9: 50 | S9: Tarjata de credito | T9: =IFERROR(VLOOKUP($A9,Tabla3[#All],2,0),"no esta registrado") -> NOCCIOLA FOOD HALL SRL
A10: 130794987 | B10: 1 | C10: 4 | D10: =IF(C10=1,Leyenda!$C$3,IF(C10=2,Leyenda!$C$4,IF(C10=3,Leyenda!$C$5,IF(C10=4,Leyenda!$C$6,IF(C10=5,Leyenda!$C$7,IF(C10=6,Leyenda!$C$8,IF(C10=7,Leyenda!$C$9,IF(C10=8,Leyenda!$C$10," "))))))))&IF(C10=9,Leyenda!$C$11,IF(C10=10,Leyenda!$C$12,IF(C10=11,Leyenda!$C$13,IF(C10=12,Leyenda!D74," ")))) -> GASTOS DE ACTIVOS FIJO | E10: B0101396124 | F10: 45763 | G10: =TEXT(F10,"MMMM") -> abril | H10: 16 | I10: =TEXT(gastos[[#This Row],[Fecha]],"DDDD") -> miércoles | J10: =DATE(YEAR(F10),MONTH(F10),H10) -> 45763 | K10: Ernesto | L10: Diesel | M10: 4662 | N10: 0 | O10: =SUM(M10:N10) -> 4662 | P10: 0 | Q10: 0 | R10: 0 | S10: Tarjata de credito | T10: =IFERROR(VLOOKUP($A10,Tabla3[#All],2,0),"no esta registrado") -> Strata, S.R.L.
A11: 130794987 | B11: 1 | C11: 4 | D11: =IF(C11=1,Leyenda!$C$3,IF(C11=2,Leyenda!$C$4,IF(C11=3,Leyenda!$C$5,IF(C11=4,Leyenda!$C$6,IF(C11=5,Leyenda!$C$7,IF(C11=6,Leyenda!$C$8,IF(C11=7,Leyenda!$C$9,IF(C11=8,Leyenda!$C$10," "))))))))&IF(C11=9,Leyenda!$C$11,IF(C11=10,Leyenda!$C$12,IF(C11=11,Leyenda!$C$13,IF(C11=12,Leyenda!D74," ")))) -> GASTOS DE ACTIVOS FIJO | E11: B0101358304 | F11: 45675 | G11: =TEXT(F11,"MMMM") -> enero | H11: 18 | I11: =TEXT(gastos[[#This Row],[Fecha]],"DDDD") -> sábado | J11: =DATE(YEAR(F11),MONTH(F11),H11) -> 45675 | K11: Ernesto | L11: Diesel | M11: 4702 | N11: 0 | O11: =SUM(M11:N11) -> 4702 | P11: 0 | Q11: 0 | R11: 0 | S11: Tarjata de credito | T11: =IFERROR(VLOOKUP($A11,Tabla3[#All],2,0),"no esta registrado") -> Strata, S.R.L.
A12: 130794987 | B12: 1 | C12: 4 | D12: =IF(C12=1,Leyenda!$C$3,IF(C12=2,Leyenda!$C$4,IF(C12=3,Leyenda!$C$5,IF(C12=4,Leyenda!$C$6,IF(C12=5,Leyenda!$C$7,IF(C12=6,Leyenda!$C$8,IF(C12=7,Leyenda!$C$9,IF(C12=8,Leyenda!$C$10," "))))))))&IF(C12=9,Leyenda!$C$11,IF(C12=10,Leyenda!$C$12,IF(C12=11,Leyenda!$C$13,IF(C12=12,Leyenda!D74," ")))) -> GASTOS DE ACTIVOS FIJO | E12: B0101384645 | F12: 45738 | G12: =TEXT(F12,"MMMM") -> marzo | H12: 22 | I12: =TEXT(gastos[[#This Row],[Fecha]],"DDDD") -> sábado | J12: =DATE(YEAR(F12),MONTH(F12),H12) -> 45738 | K12: Ernesto | L12: Diesel | M12: 4822.9 | N12: 0 | O12: =SUM(M12:N12) -> 4822.9 | P12: 0 | Q12: 0 | R12: 0 | S12: Tarjata de credito | T12: =IFERROR(VLOOKUP($A12,Tabla3[#All],2,0),"no esta registrado") -> Strata, S.R.L.
A13: 130794987 | B13: 1 | C13: 4 | D13: =IF(C13=1,Leyenda!$C$3,IF(C13=2,Leyenda!$C$4,IF(C13=3,Leyenda!$C$5,IF(C13=4,Leyenda!$C$6,IF(C13=5,Leyenda!$C$7,IF(C13=6,Leyenda!$C$8,IF(C13=7,Leyenda!$C$9,IF(C13=8,Leyenda!$C$10," "))))))))&IF(C13=9,Leyenda!$C$11,IF(C13=10,Leyenda!$C$12,IF(C13=11,Leyenda!$C$13,IF(C13=12,Leyenda!D74," ")))) -> GASTOS DE ACTIVOS FIJO | E13: B0101377121 | F13: 45723 | G13: =TEXT(F13,"MMMM") -> marzo | H13: 7 | I13: =TEXT(gastos[[#This Row],[Fecha]],"DDDD") -> viernes | J13: =DATE(YEAR(F13),MONTH(F13),H13) -> 45723 | K13: Ernesto | L13: Diesel | M13: 4867 | N13: 0 | O13: =SUM(M13:N13) -> 4867 | P13: 0 | Q13: 0 | R13: 0 | S13: Tarjata de credito | T13: =IFERROR(VLOOKUP($A13,Tabla3[#All],2,0),"no esta registrado") -> Strata, S.R.L.
A14: 101008172 | B14: 1 | C14: 4 | D14: =IF(C14=1,Leyenda!$C$3,IF(C14=2,Leyenda!$C$4,IF(C14=3,Leyenda!$C$5,IF(C14=4,Leyenda!$C$6,IF(C14=5,Leyenda!$C$7,IF(C14=6,Leyenda!$C$8,IF(C14=7,Leyenda!$C$9,IF(C14=8,Leyenda!$C$10," "))))))))&IF(C14=9,Leyenda!$C$11,IF(C14=10,Leyenda!$C$12,IF(C14=11,Leyenda!$C$13,IF(C14=12,Leyenda!D74," ")))) -> GASTOS DE ACTIVOS FIJO | E14: B01018657107 | F14: 45692 | G14: =TEXT(F14,"MMMM") -> febrero | H14: 4 | I14: =TEXT(gastos[[#This Row],[Fecha]],"DDDD") -> martes | J14: =DATE(YEAR(F14),MONTH(F14),H14) -> 45692 | K14: Casa | L14: Gas Domestico | M14: 1458 | N14: 0 | O14: =SUM(M14:N14) -> 1458 | P14: 0 | Q14: 0 | R14: 0 | S14: Tarjata de credito | T14: =IFERROR(VLOOKUP($A14,Tabla3[#All],2,0),"no esta registrado") -> Isla Dominicana de Petroleo, Corp.
A15: 130794987 | B15: 1 | C15: 4 | D15: =IF(C15=1,Leyenda!$C$3,IF(C15=2,Leyenda!$C$4,IF(C15=3,Leyenda!$C$5,IF(C15=4,Leyenda!$C$6,IF(C15=5,Leyenda!$C$7,IF(C15=6,Leyenda!$C$8,IF(C15=7,Leyenda!$C$9,IF(C15=8,Leyenda!$C$10," "))))))))&IF(C15=9,Leyenda!$C$11,IF(C15=10,Leyenda!$C$12,IF(C15=11,Leyenda!$C$13,IF(C15=12,Leyenda!D74," ")))) -> GASTOS DE ACTIVOS FIJO | E15: B0101369091 | F15: 45700 | G15: =TEXT(F15,"MMMM") -> febrero | H15: 12 | I15: =TEXT(gastos[[#This Row],[Fecha]],"DDDD") -> miércoles | J15: =DATE(YEAR(F15),MONTH(F15),H15) -> 45700 | K15: Ernesto | L15: Diesel | M15: 4722 | N15: 0 | O15: =SUM(M15:N15) -> 4722 | P15: 0 | Q15: 0 | R15: 0 | S15: Tarjata de credito | T15: =IFERROR(VLOOKUP($A15,Tabla3[#All],2,0),"no esta registrado") -> Strata, S.R.L.
A16: 101025794 | B16: 1 | C16: 4 | D16: =IF(C16=1,Leyenda!$C$3,IF(C16=2,Leyenda!$C$4,IF(C16=3,Leyenda!$C$5,IF(C16=4,Leyenda!$C$6,IF(C16=5,Leyenda!$C$7,IF(C16=6,Leyenda!$C$8,IF(C16=7,Leyenda!$C$9,IF(C16=8,Leyenda!$C$10," "))))))))&IF(C16=9,Leyenda!$C$11,IF(C16=10,Leyenda!$C$12,IF(C16=11,Leyenda!$C$13,IF(C16=12,Leyenda!D74," ")))) -> GASTOS DE ACTIVOS FIJO | E16: B0100145993 | F16: 45728 | G16: =TEXT(F16,"MMMM") -> marzo | H16: 12 | I16: =TEXT(gastos[[#This Row],[Fecha]],"DDDD") -> miércoles | J16: =DATE(YEAR(F16),MONTH(F16),H16) -> 45728 | K16: Casa | L16: Gas Domestico | M16: 1578 | N16: 0 | O16: =SUM(M16:N16) -> 1578 | P16: 0 | Q16: 0 | R16: 0 | S16: Tarjata de credito | T16: =IFERROR(VLOOKUP($A16,Tabla3[#All],2,0),"no esta registrado") -> Envasadora Gas Caribe Principal
A17: 130794987 | B17: 1 | C17: 4 | D17: =IF(C17=1,Leyenda!$C$3,IF(C17=2,Leyenda!$C$4,IF(C17=3,Leyenda!$C$5,IF(C17=4,Leyenda!$C$6,IF(C17=5,Leyenda!$C$7,IF(C17=6,Leyenda!$C$8,IF(C17=7,Leyenda!$C$9,IF(C17=8,Leyenda!$C$10," "))))))))&IF(C17=9,Leyenda!$C$11,IF(C17=10,Leyenda!$C$12,IF(C17=11,Leyenda!$C$13,IF(C17=12,Leyenda!D74," ")))) -> GASTOS DE ACTIVOS FIJO | E17: B0101193605 | F17: 45316 | G17: =TEXT(F17,"MMMM") -> enero | H17: 25 | I17: =TEXT(gastos[[#This Row],[Fecha]],"DDDD") -> jueves | J17: =DATE(YEAR(F17),MONTH(F17),H17) -> 45316 | M17: 0 | N17: 3560 | O17: =SUM(M17:N17) -> 3560 | P17: 0 | Q17: 0 | R17: 0 | S17: 0 | T17: =VLOOKUP($A17,Tabla3[#All],2,0) -> Strata, S.R.L.
A18: 130794987 | B18: 1 | C18: 4 | D18: =IF(C18=1,Leyenda!$C$3,IF(C18=2,Leyenda!$C$4,IF(C18=3,Leyenda!$C$5,IF(C18=4,Leyenda!$C$6,IF(C18=5,Leyenda!$C$7,IF(C18=6,Leyenda!$C$8,IF(C18=7,Leyenda!$C$9,IF(C18=8,Leyenda!$C$10," "))))))))&IF(C18=9,Leyenda!$C$11,IF(C18=10,Leyenda!$C$12,IF(C18=11,Leyenda!$C$13,IF(C18=12,Leyenda!D75," ")))) -> GASTOS DE ACTIVOS FIJO | E18: B0101186499 | F18: 45301 | G18: =TEXT(F18,"MMMM") -> enero | H18: 10 | I18: =TEXT(gastos[[#This Row],[Fecha]],"DDDD") -> miércoles | J18: =DATE(YEAR(F18),MONTH(F18),H18) -> 45301 | M18: 0 | N18: 3500 | O18: =SUM(M18:N18) -> 3500 | P18: 0 | Q18: 0 | R18: 0 | S18: 0 | T18: =VLOOKUP($A18,Tabla3[#All],2,0) -> Strata, S.R.L.
A19: 130794987 | B19: 1 | C19: 4 | D19: =IF(C19=1,Leyenda!$C$3,IF(C19=2,Leyenda!$C$4,IF(C19=3,Leyenda!$C$5,IF(C19=4,Leyenda!$C$6,IF(C19=5,Leyenda!$C$7,IF(C19=6,Leyenda!$C$8,IF(C19=7,Leyenda!$C$9,IF(C19=8,Leyenda!$C$10," "))))))))&IF(C19=9,Leyenda!$C$11,IF(C19=10,Leyenda!$C$12,IF(C19=11,Leyenda!$C$13,IF(C19=12,Leyenda!D76," ")))) -> GASTOS DE ACTIVOS FIJO | E19: B0101205083 | F19: 45292 | G19: =TEXT(F19,"MMMM") -> enero | H19: 1 | I19: =TEXT(gastos[[#This Row],[Fecha]],"DDDD") -> lunes | J19: =DATE(YEAR(F19),MONTH(F19),H19) -> 45292 | M19: 0 | N19: 3384 | O19: =SUM(M19:N19) -> 3384 | P19: 0 | Q19: 0 | R19: 0 | S19: 0 | T19: =VLOOKUP($A19,Tabla3[#All],2,0) -> Strata, S.R.L.
A20: 00101352929 | B20: 2 | C20: 2 | D20: =IF(C20=1,Leyenda!$C$3,IF(C20=2,Leyenda!$C$4,IF(C20=3,Leyenda!$C$5,IF(C20=4,Leyenda!$C$6,IF(C20=5,Leyenda!$C$7,IF(C20=6,Leyenda!$C$8,IF(C20=7,Leyenda!$C$9,IF(C20=8,Leyenda!$C$10," "))))))))&IF(C20=9,Leyenda!$C$11,IF(C20=10,Leyenda!$C$12,IF(C20=11,Leyenda!$C$13,IF(C20=12,Leyenda!D77," ")))) -> GASTOS POR TRABAJOS, SUMINISTROS Y SERVICIOS | E20: B0100038002 | F20: 45307 | G20: =TEXT(F20,"MMMM") -> enero | H20: 16 | I20: =TEXT(gastos[[#This Row],[Fecha]],"DDDD") -> martes | J20: =DATE(YEAR(F20),MONTH(F20),H20) -> 45307 | M20: 0 | N20: =1500-228.81 -> 1271.19 | O20: =SUM(M20:N20) -> 1271.19 | P20: 228.81 | Q20: 0 | R20: 0 | S20: 0 | T20: =IFERROR(VLOOKUP($A20,Tabla3[#All],2,0),"no esta registrado") -> no esta registrado
A21: 131153666 | B21: 1 | C21: 2 | D21: =IF(C21=1,Leyenda!$C$3,IF(C21=2,Leyenda!$C$4,IF(C21=3,Leyenda!$C$5,IF(C21=4,Leyenda!$C$6,IF(C21=5,Leyenda!$C$7,IF(C21=6,Leyenda!$C$8,IF(C21=7,Leyenda!$C$9,IF(C21=8,Leyenda!$C$10," "))))))))&IF(C21=9,Leyenda!$C$11,IF(C21=10,Leyenda!$C$12,IF(C21=11,Leyenda!$C$13,IF(C21=12,Leyenda!D78," ")))) -> GASTOS POR TRABAJOS, SUMINISTROS Y SERVICIOS | E21: B0100004392 | F21: 45295 | G21: =TEXT(F21,"MMMM") -> enero | H21: 4 | I21: =TEXT(gastos[[#This Row],[Fecha]],"DDDD") -> jueves | J21: =DATE(YEAR(F21),MONTH(F21),H21) -> 45295 | M21: 0 | N21: 622.89 | O21: =SUM(M21:N21) -> 622.89 | P21: 112.13 | Q21: 0 | R21: 0 | S21: 0 | T21: =IFERROR(VLOOKUP($A21,Tabla3[#All],2,0),"no esta registrado") -> Grupo VARNET
A22: 101863528 | B22: 1 | C22: 2 | D22: =IF(C22=1,Leyenda!$C$3,IF(C22=2,Leyenda!$C$4,IF(C22=3,Leyenda!$C$5,IF(C22=4,Leyenda!$C$6,IF(C22=5,Leyenda!$C$7,IF(C22=6,Leyenda!$C$8,IF(C22=7,Leyenda!$C$9,IF(C22=8,Leyenda!$C$10," "))))))))&IF(C22=9,Leyenda!$C$11,IF(C22=10,Leyenda!$C$12,IF(C22=11,Leyenda!$C$13,IF(C22=12,Leyenda!D79," ")))) -> GASTOS POR TRABAJOS, SUMINISTROS Y SERVICIOS | E22: E310000002110 | F22: 45305 | G22: =TEXT(F22,"MMMM") -> enero | H22: 14 | I22: =TEXT(gastos[[#This Row],[Fecha]],"DDDD") -> domingo | J22: =DATE(YEAR(F22),MONTH(F22),H22) -> 45305 | M22: 0 | N22: 794.49 | O22: =SUM(M22:N22) -> 794.49 | P22: 143.01 | Q22: 0 | R22: 0 | S22: 0 | T22: =IFERROR(VLOOKUP($A22,Tabla3[#All],2,0),"no esta registrado") -> Payless Shoesource
A23: 101602465 | B23: 1 | C23: 2 | D23: =IF(C23=1,Leyenda!$C$3,IF(C23=2,Leyenda!$C$4,IF(C23=3,Leyenda!$C$5,IF(C23=4,Leyenda!$C$6,IF(C23=5,Leyenda!$C$7,IF(C23=6,Leyenda!$C$8,IF(C23=7,Leyenda!$C$9,IF(C23=8,Leyenda!$C$10," "))))))))&IF(C23=9,Leyenda!$C$11,IF(C23=10,Leyenda!$C$12,IF(C23=11,Leyenda!$C$13,IF(C23=12,Leyenda!D80," ")))) -> GASTOS POR TRABAJOS, SUMINISTROS Y SERVICIOS | E23: E310003929628 | F23: 45297 | G23: =TEXT(F23,"MMMM") -> enero | H23: 6 | I23: =TEXT(gastos[[#This Row],[Fecha]],"DDDD") -> sábado | J23: =DATE(YEAR(F23),MONTH(F23),H23) -> 45297 | M23: 0 | N23: =1712-149.35 -> 1562.65 | O23: =SUM(M23:N23) -> 1562.65 | P23: 149.35 | Q23: 0 | R23: 0 | S23: 0 | T23: =IFERROR(VLOOKUP($A23,Tabla3[#All],2,0),"no esta registrado") -> Bravo, S.A.//Supermercados Bravo
A24: 101602465 | B24: 1 | C24: 2 | D24: =IF(C24=1,Leyenda!$C$3,IF(C24=2,Leyenda!$C$4,IF(C24=3,Leyenda!$C$5,IF(C24=4,Leyenda!$C$6,IF(C24=5,Leyenda!$C$7,IF(C24=6,Leyenda!$C$8,IF(C24=7,Leyenda!$C$9,IF(C24=8,Leyenda!$C$10," "))))))))&IF(C24=9,Leyenda!$C$11,IF(C24=10,Leyenda!$C$12,IF(C24=11,Leyenda!$C$13,IF(C24=12,Leyenda!D81," ")))) -> GASTOS POR TRABAJOS, SUMINISTROS Y SERVICIOS | E24: E310003931395 | F24: 45304 | G24: =TEXT(F24,"MMMM") -> enero | H24: 13 | I24: =TEXT(gastos[[#This Row],[Fecha]],"DDDD") -> sábado | J24: =DATE(YEAR(F24),MONTH(F24),H24) -> 45304 | M24: 0 | N24: =14132-1135.17 -> 12996.83 | O24: =SUM(M24:N24) -> 12996.83 | P24: 1135.17 | Q24: 0 | R24: 0 | S24: 0 | T24: =IFERROR(VLOOKUP($A24,Tabla3[#All],2,0),"no esta registrado") -> Bravo, S.A.//Supermercados Bravo
A25: 101602465 | B25: 1 | C25: 2 | D25: =IF(C25=1,Leyenda!$C$3,IF(C25=2,Leyenda!$C$4,IF(C25=3,Leyenda!$C$5,IF(C25=4,Leyenda!$C$6,IF(C25=5,Leyenda!$C$7,IF(C25=6,Leyenda!$C$8,IF(C25=7,Leyenda!$C$9,IF(C25=8,Leyenda!$C$10," "))))))))&IF(C25=9,Leyenda!$C$11,IF(C25=10,Leyenda!$C$12,IF(C25=11,Leyenda!$C$13,IF(C25=12,Leyenda!D82," ")))) -> GASTOS POR TRABAJOS, SUMINISTROS Y SERVICIOS | E25: E310003932338 | F25: 45308 | G25: =TEXT(F25,"MMMM") -> enero | H25: 17 | I25: =TEXT(gastos[[#This Row],[Fecha]],"DDDD") -> miércoles | J25: =DATE(YEAR(F25),MONTH(F25),H25) -> 45308 | M25: 0 | N25: =1725-201.67 -> 1523.33 | O25: =SUM(M25:N25) -> 1523.33 | P25: 201.67 | Q25: 0 | R25: 0 | S25: 0 | T25: =IFERROR(VLOOKUP($A25,Tabla3[#All],2,0),"no esta registrado") -> Bravo, S.A.//Supermercados Bravo
A26: 101019921 | B26: 1 | C26: 2 | D26: =IF(C26=1,Leyenda!$C$3,IF(C26=2,Leyenda!$C$4,IF(C26=3,Leyenda!$C$5,IF(C26=4,Leyenda!$C$6,IF(C26=5,Leyenda!$C$7,IF(C26=6,Leyenda!$C$8,IF(C26=7,Leyenda!$C$9,IF(C26=8,Leyenda!$C$10," "))))))))&IF(C26=9,Leyenda!$C$11,IF(C26=10,Leyenda!$C$12,IF(C26=11,Leyenda!$C$13,IF(C26=12,Leyenda!D83," ")))) -> GASTOS POR TRABAJOS, SUMINISTROS Y SERVICIOS | E26: B0114461355 | F26: 45311 | G26: =TEXT(F26,"MMMM") -> enero | H26: 20 | I26: =TEXT(gastos[[#This Row],[Fecha]],"DDDD") -> sábado | J26: =DATE(YEAR(F26),MONTH(F26),H26) -> 45311 | M26: 0 | N26: =2059.95-314.23 -> 1745.72 | O26: =SUM(M26:N26) -> 1745.72 | P26: 314.23 | Q26: 0 | R26: 0 | S26: 0 | T26: =IFERROR(VLOOKUP($A26,Tabla3[#All],2,0),"no esta registrado") -> Centro Cuesta Nacional S.A.S.//Supermercados Nacional//Casa Cuesta//Ferretería Cuesta//JUMBO//Bebemundo
A27: 101602465 | B27: 1 | C27: 2 | D27: =IF(C27=1,Leyenda!$C$3,IF(C27=2,Leyenda!$C$4,IF(C27=3,Leyenda!$C$5,IF(C27=4,Leyenda!$C$6,IF(C27=5,Leyenda!$C$7,IF(C27=6,Leyenda!$C$8,IF(C27=7,Leyenda!$C$9,IF(C27=8,Leyenda!$C$10," "))))))))&IF(C27=9,Leyenda!$C$11,IF(C27=10,Leyenda!$C$12,IF(C27=11,Leyenda!$C$13,IF(C27=12,Leyenda!D84," ")))) -> GASTOS POR TRABAJOS, SUMINISTROS Y SERVICIOS | E27: E310003528970 | F27: 45293 | G27: =TEXT(F27,"MMMM") -> enero | H27: 2 | I27: =TEXT(gastos[[#This Row],[Fecha]],"DDDD") -> martes | J27: =DATE(YEAR(F27),MONTH(F27),H27) -> 45293 | M27: 0 | N27: =12866-1080.27 -> 11785.73 | O27: =SUM(M27:N27) -> 11785.73 | P27: 1080.27 | Q27: 0 | R27: 0 | S27: 0 | T27: =IFERROR(VLOOKUP($A27,Tabla3[#All],2,0),"no esta registrado") -> Bravo, S.A.//Supermercados Bravo
A28: 130196796 | B28: 1 | C28: 2 | D28: =IF(C28=1,Leyenda!$C$3,IF(C28=2,Leyenda!$C$4,IF(C28=3,Leyenda!$C$5,IF(C28=4,Leyenda!$C$6,IF(C28=5,Leyenda!$C$7,IF(C28=6,Leyenda!$C$8,IF(C28=7,Leyenda!$C$9,IF(C28=8,Leyenda!$C$10," "))))))))&IF(C28=9,Leyenda!$C$11,IF(C28=10,Leyenda!$C$12,IF(C28=11,Leyenda!$C$13,IF(C28=12,Leyenda!D85," ")))) -> GASTOS POR TRABAJOS, SUMINISTROS Y SERVICIOS | E28: B0100053568 | F28: 45311 | G28: =TEXT(F28,"MMMM") -> enero | H28: 20 | I28: =TEXT(gastos[[#This Row],[Fecha]],"DDDD") -> sábado | J28: =DATE(YEAR(F28),MONTH(F28),H28) -> 45311 | M28: 2876 | N28: 0 | O28: =SUM(M28:N28) -> 2876 | P28: 0 | Q28: 0 | R28: 0 | S28: 0 | T28: =IFERROR(VLOOKUP($A28,Tabla3[#All],2,0),"no esta registrado") -> ACADEMIA EUROPEA
A29: 130196796 | B29: 1 | C29: 2 | D29: =IF(C29=1,Leyenda!$C$3,IF(C29=2,Leyenda!$C$4,IF(C29=3,Leyenda!$C$5,IF(C29=4,Leyenda!$C$6,IF(C29=5,Leyenda!$C$7,IF(C29=6,Leyenda!$C$8,IF(C29=7,Leyenda!$C$9,IF(C29=8,Leyenda!$C$10," "))))))))&IF(C29=9,Leyenda!$C$11,IF(C29=10,Leyenda!$C$12,IF(C29=11,Leyenda!$C$13,IF(C29=12,Leyenda!D86," ")))) -> GASTOS POR TRABAJOS, SUMINISTROS Y SERVICIOS | E29: B0100053388 | F29: 45303 | G29: =TEXT(F29,"MMMM") -> enero | H29: 12 | I29: =TEXT(gastos[[#This Row],[Fecha]],"DDDD") -> viernes | J29: =DATE(YEAR(F29),MONTH(F29),H29) -> 45303 | M29: 3190 | N29: 0 | O29: =SUM(M29:N29) -> 3190 | P29: 0 | Q29: 0 | R29: 0 | S29: 0 | T29: =IFERROR(VLOOKUP($A29,Tabla3[#All],2,0),"no esta registrado") -> ACADEMIA EUROPEA
A30: 130857865 | B30: 1 | C30: 7 | D30: =IF(C30=1,Leyenda!$C$3,IF(C30=2,Leyenda!$C$4,IF(C30=3,Leyenda!$C$5,IF(C30=4,Leyenda!$C$6,IF(C30=5,Leyenda!$C$7,IF(C30=6,Leyenda!$C$8,IF(C30=7,Leyenda!$C$9,IF(C30=8,Leyenda!$C$10," "))))))))&IF(C30=9,Leyenda!$C$11,IF(C30=10,Leyenda!$C$12,IF(C30=11,Leyenda!$C$13,IF(C30=12,Leyenda!D87," ")))) -> GASTOS FINANCIEROS | E30: B0100056091 | F30: 45292 | G30: =TEXT(F30,"MMMM") -> enero | H30: 1 | I30: =TEXT(gastos[[#This Row],[Fecha]],"DDDD") -> lunes | J30: =DATE(YEAR(F30),MONTH(F30),H30) -> 45292 | M30: 0 | N30: 1309.32 | O30: =SUM(M30:N30) -> 1309.32 | P30: 235.68 | Q30: 0 | R30: 0 | S30: 0 | T30: =IFERROR(VLOOKUP($A30,Tabla3[#All],2,0),"no esta registrado") -> no esta registrado
A31: 101602465 | B31: 1 | C31: 2 | D31: =IF(C31=1,Leyenda!$C$3,IF(C31=2,Leyenda!$C$4,IF(C31=3,Leyenda!$C$5,IF(C31=4,Leyenda!$C$6,IF(C31=5,Leyenda!$C$7,IF(C31=6,Leyenda!$C$8,IF(C31=7,Leyenda!$C$9,IF(C31=8,Leyenda!$C$10," "))))))))&IF(C31=9,Leyenda!$C$11,IF(C31=10,Leyenda!$C$12,IF(C31=11,Leyenda!$C$13,IF(C31=12,Leyenda!D88," ")))) -> GASTOS POR TRABAJOS, SUMINISTROS Y SERVICIOS | E31: E310003956081 | F31: 45315 | G31: =TEXT(F31,"MMMM") -> enero | H31: 24 | I31: =TEXT(gastos[[#This Row],[Fecha]],"DDDD") -> miércoles | J31: =DATE(YEAR(F31),MONTH(F31),H31) -> 45315 | M31: 1490 | N31: 0 | O31: =SUM(M31:N31) -> 1490 | P31: 0 | Q31: 0 | R31: 0 | S31: 0 | T31: =IFERROR(VLOOKUP($A31,Tabla3[#All],2,0),"no esta registrado") -> Bravo, S.A.//Supermercados Bravo
A32: 131619046 | B32: 1 | C32: 2 | D32: =IF(C32=1,Leyenda!$C$3,IF(C32=2,Leyenda!$C$4,IF(C32=3,Leyenda!$C$5,IF(C32=4,Leyenda!$C$6,IF(C32=5,Leyenda!$C$7,IF(C32=6,Leyenda!$C$8,IF(C32=7,Leyenda!$C$9,IF(C32=8,Leyenda!$C$10," "))))))))&IF(C32=9,Leyenda!$C$11,IF(C32=10,Leyenda!$C$12,IF(C32=11,Leyenda!$C$13,IF(C32=12,Leyenda!D89," ")))) -> GASTOS POR TRABAJOS, SUMINISTROS Y SERVICIOS | E32: B0100001472 | F32: 45308 | G32: =TEXT(F32,"MMMM") -> enero | H32: 17 | I32: =TEXT(gastos[[#This Row],[Fecha]],"DDDD") -> miércoles | J32: =DATE(YEAR(F32),MONTH(F32),H32) -> 45308 | M32: 0 | N32: 1072.03 | O32: =SUM(M32:N32) -> 1072.03 | P32: 192.97 | Q32: 0 | R32: 0 | S32: 0 | T32: =IFERROR(VLOOKUP($A32,Tabla3[#All],2,0),"no esta registrado") -> no esta registrado
A33: 101876077 | B33: 1 | C33: 2 | D33: =IF(C33=1,Leyenda!$C$3,IF(C33=2,Leyenda!$C$4,IF(C33=3,Leyenda!$C$5,IF(C33=4,Leyenda!$C$6,IF(C33=5,Leyenda!$C$7,IF(C33=6,Leyenda!$C$8,IF(C33=7,Leyenda!$C$9,IF(C33=8,Leyenda!$C$10," "))))))))&IF(C33=9,Leyenda!$C$11,IF(C33=10,Leyenda!$C$12,IF(C33=11,Leyenda!$C$13,IF(C33=12,Leyenda!D90," ")))) -> GASTOS POR TRABAJOS, SUMINISTROS Y SERVICIOS | E33: B0100003560 | F33: 45314 | G33: =TEXT(F33,"MMMM") -> enero | H33: 23 | I33: =TEXT(gastos[[#This Row],[Fecha]],"DDDD") -> martes | J33: =DATE(YEAR(F33),MONTH(F33),H33) -> 45314 | M33: 0 | N33: 8474.58 | O33: =SUM(M33:N33) -> 8474.58 | P33: 1525.42 | Q33: 0 | R33: 0 | S33: 0 | T33: =IFERROR(VLOOKUP($A33,Tabla3[#All],2,0),"no esta registrado") -> no esta registrado
A34: 131156398 | B34: 1 | C34: 2 | D34: =IF(C34=1,Leyenda!$C$3,IF(C34=2,Leyenda!$C$4,IF(C34=3,Leyenda!$C$5,IF(C34=4,Leyenda!$C$6,IF(C34=5,Leyenda!$C$7,IF(C34=6,Leyenda!$C$8,IF(C34=7,Leyenda!$C$9,IF(C34=8,Leyenda!$C$10," "))))))))&IF(C34=9,Leyenda!$C$11,IF(C34=10,Leyenda!$C$12,IF(C34=11,Leyenda!$C$13,IF(C34=12,Leyenda!D91," ")))) -> GASTOS POR TRABAJOS, SUMINISTROS Y SERVICIOS | E34: B0100033027 | F34: 45299 | G34: =TEXT(F34,"MMMM") -> enero | H34: 8 | I34: =TEXT(gastos[[#This Row],[Fecha]],"DDDD") -> lunes | J34: =DATE(YEAR(F34),MONTH(F34),H34) -> 45299 | M34: 0 | N34: 250.16 | O34: =SUM(M34:N34) -> 250.16 | P34: 25.28 | Q34: 0 | R34: 0 | S34: 0 | T34: =IFERROR(VLOOKUP($A34,Tabla3[#All],2,0),"no esta registrado") -> no esta registrado
A35: 430030341 | B35: 1 | C35: 2 | D35: =IF(C35=1,Leyenda!$C$3,IF(C35=2,Leyenda!$C$4,IF(C35=3,Leyenda!$C$5,IF(C35=4,Leyenda!$C$6,IF(C35=5,Leyenda!$C$7,IF(C35=6,Leyenda!$C$8,IF(C35=7,Leyenda!$C$9,IF(C35=8,Leyenda!$C$10," "))))))))&IF(C35=9,Leyenda!$C$11,IF(C35=10,Leyenda!$C$12,IF(C35=11,Leyenda!$C$13,IF(C35=12,Leyenda!D92," ")))) -> GASTOS POR TRABAJOS, SUMINISTROS Y SERVICIOS | E35: B0100012571 | F35: 45300 | G35: =TEXT(F35,"MMMM") -> enero | H35: 9 | I35: =TEXT(gastos[[#This Row],[Fecha]],"DDDD") -> martes | J35: =DATE(YEAR(F35),MONTH(F35),H35) -> 45300 | M35: 7100 | N35: 0 | O35: =SUM(M35:N35) -> 7100 | P35: 0 | Q35: 0 | R35: 0 | S35: 0 | T35: =IFERROR(VLOOKUP($A35,Tabla3[#All],2,0),"no esta registrado") -> COLEGIO SANTA ROSA DE LIMA
A36: 430030341 | B36: 1 | C36: 2 | D36: =IF(C36=1,Leyenda!$C$3,IF(C36=2,Leyenda!$C$4,IF(C36=3,Leyenda!$C$5,IF(C36=4,Leyenda!$C$6,IF(C36=5,Leyenda!$C$7,IF(C36=6,Leyenda!$C$8,IF(C36=7,Leyenda!$C$9,IF(C36=8,Leyenda!$C$10," "))))))))&IF(C36=9,Leyenda!$C$11,IF(C36=10,Leyenda!$C$12,IF(C36=11,Leyenda!$C$13,IF(C36=12,Leyenda!D93," ")))) -> GASTOS POR TRABAJOS, SUMINISTROS Y SERVICIOS | E36: B0100012572 | F36: 45300 | G36: =TEXT(F36,"MMMM") -> enero | H36: 9 | I36: =TEXT(gastos[[#This Row],[Fecha]],"DDDD") -> martes | J36: =DATE(YEAR(F36),MONTH(F36),H36) -> 45300 | M36: 6800 | N36: 0 | O36: =SUM(M36:N36) -> 6800 | P36: 0 | Q36: 0 | R36: 0 | S36: 0 | T36: =IFERROR(VLOOKUP($A36,Tabla3[#All],2,0),"no esta registrado") -> COLEGIO SANTA ROSA DE LIMA
A37: 430030341 | B37: 1 | C37: 2 | D37: =IF(C37=1,Leyenda!$C$3,IF(C37=2,Leyenda!$C$4,IF(C37=3,Leyenda!$C$5,IF(C37=4,Leyenda!$C$6,IF(C37=5,Leyenda!$C$7,IF(C37=6,Leyenda!$C$8,IF(C37=7,Leyenda!$C$9,IF(C37=8,Leyenda!$C$10," "))))))))&IF(C37=9,Leyenda!$C$11,IF(C37=10,Leyenda!$C$12,IF(C37=11,Leyenda!$C$13,IF(C37=12,Leyenda!D94," ")))) -> GASTOS POR TRABAJOS, SUMINISTROS Y SERVICIOS | E37: B0100012573 | F37: =IF($C37=0," ",$F$17) -> 45316 | G37: =TEXT(F37,"MMMM") -> enero | H37: 9 | I37: =TEXT(gastos[[#This Row],[Fecha]],"DDDD") -> martes | J37: =DATE(YEAR(F37),MONTH(F37),H37) -> 45300 | M37: 6800 | N37: 0 | O37: =SUM(M37:N37) -> 6800 | P37: 0 | Q37: 0 | R37: 0 | S37: 0 | T37: =IFERROR(VLOOKUP($A37,Tabla3[#All],2,0),"no esta registrado") -> COLEGIO SANTA ROSA DE LIMA
A38: 430030341 | B38: 1 | C38: 2 | D38: =IF(C38=1,Leyenda!$C$3,IF(C38=2,Leyenda!$C$4,IF(C38=3,Leyenda!$C$5,IF(C38=4,Leyenda!$C$6,IF(C38=5,Leyenda!$C$7,IF(C38=6,Leyenda!$C$8,IF(C38=7,Leyenda!$C$9,IF(C38=8,Leyenda!$C$10," "))))))))&IF(C38=9,Leyenda!$C$11,IF(C38=10,Leyenda!$C$12,IF(C38=11,Leyenda!$C$13,IF(C38=12,Leyenda!D95," ")))) -> GASTOS POR TRABAJOS, SUMINISTROS Y SERVICIOS | E38: B0100012768 | F38: =IF($C38=0," ",$F$17) -> 45316 | G38: =TEXT(F38,"MMMM") -> enero | H38: 31 | I38: =TEXT(gastos[[#This Row],[Fecha]],"DDDD") -> miércoles | J38: =DATE(YEAR(F38),MONTH(F38),H38) -> 45322 | M38: 7100 | N38: 0 | O38: =SUM(M38:N38) -> 7100 | P38: 0 | Q38: 0 | R38: 0 | S38: 0 | T38: =IFERROR(VLOOKUP($A38,Tabla3[#All],2,0),"no esta registrado") -> COLEGIO SANTA ROSA DE LIMA
A39: 430030341 | B39: 1 | C39: 2 | D39: =IF(C39=1,Leyenda!$C$3,IF(C39=2,Leyenda!$C$4,IF(C39=3,Leyenda!$C$5,IF(C39=4,Leyenda!$C$6,IF(C39=5,Leyenda!$C$7,IF(C39=6,Leyenda!$C$8,IF(C39=7,Leyenda!$C$9,IF(C39=8,Leyenda!$C$10," "))))))))&IF(C39=9,Leyenda!$C$11,IF(C39=10,Leyenda!$C$12,IF(C39=11,Leyenda!$C$13,IF(C39=12,Leyenda!D96," ")))) -> GASTOS POR TRABAJOS, SUMINISTROS Y SERVICIOS | E39: B0100012769 | F39: =IF($C39=0," ",$F$17) -> 45316 | G39: =TEXT(F39,"MMMM") -> enero | H39: 31 | I39: =TEXT(gastos[[#This Row],[Fecha]],"DDDD") -> miércoles | J39: =DATE(YEAR(F39),MONTH(F39),H39) -> 45322 | M39: 6800 | N39: 0 | O39: =SUM(M39:N39) -> 6800 | P39: 0 | Q39: 0 | R39: 0 | S39: 0 | T39: =IFERROR(VLOOKUP($A39,Tabla3[#All],2,0),"no esta registrado") -> COLEGIO SANTA ROSA DE LIMA
A40: 430030341 | B40: 1 | C40: 2 | D40: =IF(C40=1,Leyenda!$C$3,IF(C40=2,Leyenda!$C$4,IF(C40=3,Leyenda!$C$5,IF(C40=4,Leyenda!$C$6,IF(C40=5,Leyenda!$C$7,IF(C40=6,Leyenda!$C$8,IF(C40=7,Leyenda!$C$9,IF(C40=8,Leyenda!$C$10," "))))))))&IF(C40=9,Leyenda!$C$11,IF(C40=10,Leyenda!$C$12,IF(C40=11,Leyenda!$C$13,IF(C40=12,Leyenda!D97," ")))) -> GASTOS POR TRABAJOS, SUMINISTROS Y SERVICIOS | E40: B0100012770 | F40: =IF($C40=0," ",$F$17) -> 45316 | G40: =TEXT(F40,"MMMM") -> enero | H40: 31 | I40: =TEXT(gastos[[#This Row],[Fecha]],"DDDD") -> miércoles | J40: =DATE(YEAR(F40),MONTH(F40),H40) -> 45322 | M40: 6800 | N40: 0 | O40: =SUM(M40:N40) -> 6800 | P40: 0 | Q40: 0 | R40: 0 | S40: 0 | T40: =IFERROR(VLOOKUP($A40,Tabla3[#All],2,0),"no esta registrado") -> COLEGIO SANTA ROSA DE LIMA
A41: 101820217 | B41: 1 | C41: 2 | D41: =IF(C41=1,Leyenda!$C$3,IF(C41=2,Leyenda!$C$4,IF(C41=3,Leyenda!$C$5,IF(C41=4,Leyenda!$C$6,IF(C41=5,Leyenda!$C$7,IF(C41=6,Leyenda!$C$8,IF(C41=7,Leyenda!$C$9,IF(C41=8,Leyenda!$C$10," "))))))))&IF(C41=9,Leyenda!$C$11,IF(C41=10,Leyenda!$C$12,IF(C41=11,Leyenda!$C$13,IF(C41=12,Leyenda!D98," ")))) -> GASTOS POR TRABAJOS, SUMINISTROS Y SERVICIOS | E41: B0101805031 | F41: =IF($C41=0," ",$F$17) -> 45316 | G41: =TEXT(F41,"MMMM") -> enero | H41: 20 | I41: =TEXT(gastos[[#This Row],[Fecha]],"DDDD") -> sábado | J41: =DATE(YEAR(F41),MONTH(F41),H41) -> 45311 | M41: 5023.39 | N41: 0 | O41: =SUM(M41:N41) -> 5023.39 | P41: 0 | Q41: 0 | R41: 0 | S41: 0 | T41: =IFERROR(VLOOKUP($A41,Tabla3[#All],2,0),"no esta registrado") -> EDEESTE
A42: 101001577 | B42: 1 | C42: 2 | D42: =IF(C42=1,Leyenda!$C$3,IF(C42=2,Leyenda!$C$4,IF(C42=3,Leyenda!$C$5,IF(C42=4,Leyenda!$C$6,IF(C42=5,Leyenda!$C$7,IF(C42=6,Leyenda!$C$8,IF(C42=7,Leyenda!$C$9,IF(C42=8,Leyenda!$C$10," "))))))))&IF(C42=9,Leyenda!$C$11,IF(C42=10,Leyenda!$C$12,IF(C42=11,Leyenda!$C$13,IF(C42=12,Leyenda!D99," ")))) -> GASTOS POR TRABAJOS, SUMINISTROS Y SERVICIOS | E42: E310008741475 | F42: =IF($C42=0," ",$F$17) -> 45316 | G42: =TEXT(F42,"MMMM") -> enero | H42: 7 | I42: =TEXT(gastos[[#This Row],[Fecha]],"DDDD") -> domingo | J42: =DATE(YEAR(F42),MONTH(F42),H42) -> 45298 | M42: 2407.69 | N42: 0 | O42: =SUM(M42:N42) -> 2407.69 | P42: 433.39 | Q42: 0 | R42: 0 | S42: 0 | T42: =IFERROR(VLOOKUP($A42,Tabla3[#All],2,0),"no esta registrado") -> CLARO//CODETEL
A43: 101001577 | B43: 2 | C43: 2 | D43: =IF(C43=1,Leyenda!$C$3,IF(C43=2,Leyenda!$C$4,IF(C43=3,Leyenda!$C$5,IF(C43=4,Leyenda!$C$6,IF(C43=5,Leyenda!$C$7,IF(C43=6,Leyenda!$C$8,IF(C43=7,Leyenda!$C$9,IF(C43=8,Leyenda!$C$10," "))))))))&IF(C43=9,Leyenda!$C$11,IF(C43=10,Leyenda!$C$12,IF(C43=11,Leyenda!$C$13,IF(C43=12,Leyenda!D100," ")))) -> GASTOS POR TRABAJOS, SUMINISTROS Y SERVICIOS | E43: E310008744559 | F43: =IF($C43=0," ",$F$17) -> 45316 | G43: =TEXT(F43,"MMMM") -> enero | H43: 7 | I43: =TEXT(gastos[[#This Row],[Fecha]],"DDDD") -> domingo | J43: =DATE(YEAR(F43),MONTH(F43),H43) -> 45298 | M43: 830 | N43: 0 | O43: =SUM(M43:N43) -> 830 | P43: 149.4 | Q43: 0 | R43: 0 | S43: 0 | T43: =IFERROR(VLOOKUP($A43,Tabla3[#All],2,0),"no esta registrado") -> CLARO//CODETEL
A44: 101136792 | B44: 1 | C44: 7 | D44: =IF(C44=1,Leyenda!$C$3,IF(C44=2,Leyenda!$C$4,IF(C44=3,Leyenda!$C$5,IF(C44=4,Leyenda!$C$6,IF(C44=5,Leyenda!$C$7,IF(C44=6,Leyenda!$C$8,IF(C44=7,Leyenda!$C$9,IF(C44=8,Leyenda!$C$10," "))))))))&IF(C44=9,Leyenda!$C$11,IF(C44=10,Leyenda!$C$12,IF(C44=11,Leyenda!$C$13,IF(C44=12,Leyenda!D101," ")))) -> GASTOS FINANCIEROS | E44: B0185964421 | F44: =IF($C44=0," ",$F$17) -> 45316 | G44: =TEXT(F44,"MMMM") -> enero | H44: 22 | I44: =TEXT(gastos[[#This Row],[Fecha]],"DDDD") -> lunes | J44: =DATE(YEAR(F44),MONTH(F44),H44) -> 45313 | M44: 22604.17 | N44: 0 | O44: =SUM(M44:N44) -> 22604.17 | P44: 0 | Q44: 0 | R44: 0 | S44: 0 | T44: =IFERROR(VLOOKUP($A44,Tabla3[#All],2,0),"no esta registrado") -> Banco Multiple BHD León, S. A.
A45: 101136792 | B45: 1 | C45: 7 | D45: =IF(C45=1,Leyenda!$C$3,IF(C45=2,Leyenda!$C$4,IF(C45=3,Leyenda!$C$5,IF(C45=4,Leyenda!$C$6,IF(C45=5,Leyenda!$C$7,IF(C45=6,Leyenda!$C$8,IF(C45=7,Leyenda!$C$9,IF(C45=8,Leyenda!$C$10," "))))))))&IF(C45=9,Leyenda!$C$11,IF(C45=10,Leyenda!$C$12,IF(C45=11,Leyenda!$C$13,IF(C45=12,Leyenda!D102," ")))) -> GASTOS FINANCIEROS | E45: B0185895065 | F45: =IF($C45=0," ",$F$17) -> 45316 | G45: =TEXT(F45,"MMMM") -> enero | H45: 1 | I45: =TEXT(gastos[[#This Row],[Fecha]],"DDDD") -> lunes | J45: =DATE(YEAR(F45),MONTH(F45),H45) -> 45292 | M45: 7500 | N45: 0 | O45: =SUM(M45:N45) -> 7500 | P45: 0 | Q45: 0 | R45: 0 | S45: 0 | T45: =IFERROR(VLOOKUP($A45,Tabla3[#All],2,0),"no esta registrado") -> Banco Multiple BHD León, S. A.
A46: 101010632 | B46: 1 | C46: 7 | D46: =IF(C46=1,Leyenda!$C$3,IF(C46=2,Leyenda!$C$4,IF(C46=3,Leyenda!$C$5,IF(C46=4,Leyenda!$C$6,IF(C46=5,Leyenda!$C$7,IF(C46=6,Leyenda!$C$8,IF(C46=7,Leyenda!$C$9,IF(C46=8,Leyenda!$C$10," "))))))))&IF(C46=9,Leyenda!$C$11,IF(C46=10,Leyenda!$C$12,IF(C46=11,Leyenda!$C$13,IF(C46=12,Leyenda!D103," ")))) -> GASTOS FINANCIEROS | E46: E310118055012 | F46: =IF($C46=0," ",$F$17) -> 45316 | G46: =TEXT(F46,"MMMM") -> enero | H46: 31 | I46: =TEXT(gastos[[#This Row],[Fecha]],"DDDD") -> miércoles | J46: =DATE(YEAR(F46),MONTH(F46),H46) -> 45322 | M46: 11927.34 | N46: 0 | O46: =SUM(M46:N46) -> 11927.34 | P46: 0 | Q46: 0 | R46: 0 | S46: 0 | T46: =IFERROR(VLOOKUP($A46,Tabla3[#All],2,0),"no esta registrado") -> Banco Popular Dominicano, S. A. Banco Multiple
A47: 130794987 | B47: 1 | C47: 4 | D47: =IF(C47=1,Leyenda!$C$3,IF(C47=2,Leyenda!$C$4,IF(C47=3,Leyenda!$C$5,IF(C47=4,Leyenda!$C$6,IF(C47=5,Leyenda!$C$7,IF(C47=6,Leyenda!$C$8,IF(C47=7,Leyenda!$C$9,IF(C47=8,Leyenda!$C$10," "))))))))&IF(C47=9,Leyenda!$C$11,IF(C47=10,Leyenda!$C$12,IF(C47=11,Leyenda!$C$13,IF(C47=12,Leyenda!D104," ")))) -> GASTOS DE ACTIVOS FIJO | E47: B0101199417 | F47: 45328 | G47: =TEXT(F47,"MMMM") -> febrero | H47: 6 | I47: =TEXT(gastos[[#This Row],[Fecha]],"DDDD") -> martes | J47: =DATE(YEAR(F47),MONTH(F47),H47) -> 45328 | M47: 0 | N47: 3400 | O47: =SUM(M47:N47) -> 3400 | P47: 0 | Q47: 0 | R47: 0 | S47: 0 | T47: =IFERROR(VLOOKUP($A47,Tabla3[#All],2,0),"no esta registrado") -> Strata, S.R.L.
A48: 101025794 | B48: 1 | C48: 4 | D48: =IF(C48=1,Leyenda!$C$3,IF(C48=2,Leyenda!$C$4,IF(C48=3,Leyenda!$C$5,IF(C48=4,Leyenda!$C$6,IF(C48=5,Leyenda!$C$7,IF(C48=6,Leyenda!$C$8,IF(C48=7,Leyenda!$C$9,IF(C48=8,Leyenda!$C$10," "))))))))&IF(C48=9,Leyenda!$C$11,IF(C48=10,Leyenda!$C$12,IF(C48=11,Leyenda!$C$13,IF(C48=12,Leyenda!D105," ")))) -> GASTOS DE ACTIVOS FIJO | E48: B0100126326 | F48: 45329 | G48: =TEXT(F48,"MMMM") -> febrero | H48: 15 | I48: =TEXT(gastos[[#This Row],[Fecha]],"DDDD") -> jueves | J48: =DATE(YEAR(F48),MONTH(F48),H48) -> 45337 | M48: 0 | N48: 1591 | O48: =SUM(M48:N48) -> 1591 | P48: 0 | Q48: 0 | R48: 0 | S48: 0 | T48: =IFERROR(VLOOKUP($A48,Tabla3[#All],2,0),"no esta registrado") -> Envasadora Gas Caribe Principal
A49: 130794987 | B49: 1 | C49: 4 | D49: =IF(C49=1,Leyenda!$C$3,IF(C49=2,Leyenda!$C$4,IF(C49=3,Leyenda!$C$5,IF(C49=4,Leyenda!$C$6,IF(C49=5,Leyenda!$C$7,IF(C49=6,Leyenda!$C$8,IF(C49=7,Leyenda!$C$9,IF(C49=8,Leyenda!$C$10," "))))))))&IF(C49=9,Leyenda!$C$11,IF(C49=10,Leyenda!$C$12,IF(C49=11,Leyenda!$C$13,IF(C49=12,Leyenda!D106," ")))) -> GASTOS DE ACTIVOS FIJO | E49: B0101207136 | F49: 45330 | G49: =TEXT(F49,"MMMM") -> febrero | H49: 22 | I49: =TEXT(gastos[[#This Row],[Fecha]],"DDDD") -> jueves | J49: =DATE(YEAR(F49),MONTH(F49),H49) -> 45344 | M49: 0 | N49: 4630 | O49: =SUM(M49:N49) -> 4630 | P49: 0 | Q49: 0 | R49: 0 | S49: 0 | T49: =IFERROR(VLOOKUP($A49,Tabla3[#All],2,0),"no esta registrado") -> Strata, S.R.L.
A50: 130794987 | B50: 1 | C50: 4 | D50: =IF(C50=1,Leyenda!$C$3,IF(C50=2,Leyenda!$C$4,IF(C50=3,Leyenda!$C$5,IF(C50=4,Leyenda!$C$6,IF(C50=5,Leyenda!$C$7,IF(C50=6,Leyenda!$C$8,IF(C50=7,Leyenda!$C$9,IF(C50=8,Leyenda!$C$10," "))))))))&IF(C50=9,Leyenda!$C$11,IF(C50=10,Leyenda!$C$12,IF(C50=11,Leyenda!$C$13,IF(C50=12,Leyenda!D107," ")))) -> GASTOS DE ACTIVOS FIJO | E50: B0101197334 | F50: 45331 | G50: =TEXT(F50,"MMMM") -> febrero | H50: 2 | I50: =TEXT(gastos[[#This Row],[Fecha]],"DDDD") -> viernes | J50: =DATE(YEAR(F50),MONTH(F50),H50) -> 45324 | M50: 0 | N50: 4549 | O50: =SUM(M50:N50) -> 4549 | P50: 0 | Q50: 0 | R50: 0 | S50: 0 | T50: =IFERROR(VLOOKUP($A50,Tabla3[#All],2,0),"no esta registrado") -> Strata, S.R.L.
A51: 101801875 | B51: 1 | C51: 2 | D51: =IF(C51=1,Leyenda!$C$3,IF(C51=2,Leyenda!$C$4,IF(C51=3,Leyenda!$C$5,IF(C51=4,Leyenda!$C$6,IF(C51=5,Leyenda!$C$7,IF(C51=6,Leyenda!$C$8,IF(C51=7,Leyenda!$C$9,IF(C51=8,Leyenda!$C$10," "))))))))&IF(C51=9,Leyenda!$C$11,IF(C51=10,Leyenda!$C$12,IF(C51=11,Leyenda!$C$13,IF(C51=12,Leyenda!D108," ")))) -> GASTOS POR TRABAJOS, SUMINISTROS Y SERVICIOS | E51: B0105915412 | F51: 45332 | G51: =TEXT(F51,"MMMM") -> febrero | H51: 10 | I51: =TEXT(gastos[[#This Row],[Fecha]],"DDDD") -> sábado | J51: =DATE(YEAR(F51),MONTH(F51),H51) -> 45332 | M51: 0 | N51: =390-59.43 -> 330.57 | O51: =SUM(M51:N51) -> 330.57 | P51: 59.43 | Q51: 0 | R51: 0 | S51: 0 | T51: =IFERROR(VLOOKUP($A51,Tabla3[#All],2,0),"no esta registrado") -> Pricesmart Dominicana S. A.
A52: 119017191 | B52: 1 | C52: 2 | D52: =IF(C52=1,Leyenda!$C$3,IF(C52=2,Leyenda!$C$4,IF(C52=3,Leyenda!$C$5,IF(C52=4,Leyenda!$C$6,IF(C52=5,Leyenda!$C$7,IF(C52=6,Leyenda!$C$8,IF(C52=7,Leyenda!$C$9,IF(C52=8,Leyenda!$C$10," "))))))))&IF(C52=9,Leyenda!$C$11,IF(C52=10,Leyenda!$C$12,IF(C52=11,Leyenda!$C$13,IF(C52=12,Leyenda!D109," ")))) -> GASTOS POR TRABAJOS, SUMINISTROS Y SERVICIOS | E52: B0101221570 | F52: 45333 | G52: =TEXT(F52,"MMMM") -> febrero | H52: 26 | I52: =TEXT(gastos[[#This Row],[Fecha]],"DDDD") -> lunes | J52: =DATE(YEAR(F52),MONTH(F52),H52) -> 45348 | M52: 0 | N52: 1478.84 | O52: =SUM(M52:N52) -> 1478.84 | P52: 266.19 | Q52: 0 | R52: 0 | S52: 0 | T52: =IFERROR(VLOOKUP($A52,Tabla3[#All],2,0),"no esta registrado") -> no esta registrado
A53: 101023163 | B53: 1 | C53: 2 | D53: =IF(C53=1,Leyenda!$C$3,IF(C53=2,Leyenda!$C$4,IF(C53=3,Leyenda!$C$5,IF(C53=4,Leyenda!$C$6,IF(C53=5,Leyenda!$C$7,IF(C53=6,Leyenda!$C$8,IF(C53=7,Leyenda!$C$9,IF(C53=8,Leyenda!$C$10," "))))))))&IF(C53=9,Leyenda!$C$11,IF(C53=10,Leyenda!$C$12,IF(C53=11,Leyenda!$C$13,IF(C53=12,Leyenda!D110," ")))) -> GASTOS POR TRABAJOS, SUMINISTROS Y SERVICIOS | E53: B0100263953 | F53: 45334 | G53: =TEXT(F53,"MMMM") -> febrero | H53: 15 | I53: =TEXT(gastos[[#This Row],[Fecha]],"DDDD") -> jueves | J53: =DATE(YEAR(F53),MONTH(F53),H53) -> 45337 | M53: 0 | N53: =650-99.15 -> 550.85 | O53: =SUM(M53:N53) -> 550.85 | P53: 99.15 | Q53: 0 | R53: 0 | S53: 0 | T53: =IFERROR(VLOOKUP($A53,Tabla3[#All],2,0),"no esta registrado") -> Almacenes Garrido
A54: 101023163 | B54: 1 | C54: 2 | D54: =IF(C54=1,Leyenda!$C$3,IF(C54=2,Leyenda!$C$4,IF(C54=3,Leyenda!$C$5,IF(C54=4,Leyenda!$C$6,IF(C54=5,Leyenda!$C$7,IF(C54=6,Leyenda!$C$8,IF(C54=7,Leyenda!$C$9,IF(C54=8,Leyenda!$C$10," "))))))))&IF(C54=9,Leyenda!$C$11,IF(C54=10,Leyenda!$C$12,IF(C54=11,Leyenda!$C$13,IF(C54=12,Leyenda!D111," ")))) -> GASTOS POR TRABAJOS, SUMINISTROS Y SERVICIOS | E54: B0100266519 | F54: 45335 | G54: =TEXT(F54,"MMMM") -> febrero | H54: 16 | I54: =TEXT(gastos[[#This Row],[Fecha]],"DDDD") -> viernes | J54: =DATE(YEAR(F54),MONTH(F54),H54) -> 45338 | M54: 0 | N54: =2795-425.36 -> 2369.64 | O54: =SUM(M54:N54) -> 2369.64 | P54: 425.36 | Q54: 0 | R54: 0 | S54: 0 | T54: =IFERROR(VLOOKUP($A54,Tabla3[#All],2,0),"no esta registrado") -> Almacenes Garrido
A55: 131341136 | B55: 1 | C55: 2 | D55: =IF(C55=1,Leyenda!$C$3,IF(C55=2,Leyenda!$C$4,IF(C55=3,Leyenda!$C$5,IF(C55=4,Leyenda!$C$6,IF(C55=5,Leyenda!$C$7,IF(C55=6,Leyenda!$C$8,IF(C55=7,Leyenda!$C$9,IF(C55=8,Leyenda!$C$10," "))))))))&IF(C55=9,Leyenda!$C$11,IF(C55=10,Leyenda!$C$12,IF(C55=11,Leyenda!$C$13,IF(C55=12,Leyenda!D112," ")))) -> GASTOS POR TRABAJOS, SUMINISTROS Y SERVICIOS | E55: B0100584345 | F55: 45336 | G55: =TEXT(F55,"MMMM") -> febrero | H55: 22 | I55: =TEXT(gastos[[#This Row],[Fecha]],"DDDD") -> jueves | J55: =DATE(YEAR(F55),MONTH(F55),H55) -> 45344 | M55: 0 | N55: 614.41 | O55: =SUM(M55:N55) -> 614.41 | P55: 110.59 | Q55: 0 | R55: 0 | S55: 0 | T55: =IFERROR(VLOOKUP($A55,Tabla3[#All],2,0),"no esta registrado") -> Little Ceasars Pizza Alma Rosa
A56: 101088222 | B56: 1 | C56: 2 | D56: =IF(C56=1,Leyenda!$C$3,IF(C56=2,Leyenda!$C$4,IF(C56=3,Leyenda!$C$5,IF(C56=4,Leyenda!$C$6,IF(C56=5,Leyenda!$C$7,IF(C56=6,Leyenda!$C$8,IF(C56=7,Leyenda!$C$9,IF(C56=8,Leyenda!$C$10," "))))))))&IF(C56=9,Leyenda!$C$11,IF(C56=10,Leyenda!$C$12,IF(C56=11,Leyenda!$C$13,IF(C56=12,Leyenda!D113," ")))) -> GASTOS POR TRABAJOS, SUMINISTROS Y SERVICIOS | E56: B0100375847 | F56: 45337 | G56: =TEXT(F56,"MMMM") -> febrero | H56: 20 | I56: =TEXT(gastos[[#This Row],[Fecha]],"DDDD") -> martes | J56: =DATE(YEAR(F56),MONTH(F56),H56) -> 45342 | M56: 0 | N56: =3295-502.63 -> 2792.37 | O56: =SUM(M56:N56) -> 2792.37 | P56: 502.63 | Q56: 0 | R56: 0 | S56: 0 | T56: =IFERROR(VLOOKUP($A56,Tabla3[#All],2,0),"no esta registrado") -> Antonio Chahin M., S.A.//Anthony s
A57: 101019921 | B57: 1 | C57: 2 | D57: =IF(C57=1,Leyenda!$C$3,IF(C57=2,Leyenda!$C$4,IF(C57=3,Leyenda!$C$5,IF(C57=4,Leyenda!$C$6,IF(C57=5,Leyenda!$C$7,IF(C57=6,Leyenda!$C$8,IF(C57=7,Leyenda!$C$9,IF(C57=8,Leyenda!$C$10," "))))))))&IF(C57=9,Leyenda!$C$11,IF(C57=10,Leyenda!$C$12,IF(C57=11,Leyenda!$C$13,IF(C57=12,Leyenda!D114," ")))) -> GASTOS POR TRABAJOS, SUMINISTROS Y SERVICIOS | E57: B0113793606 | F57: 45338 | G57: =TEXT(F57,"MMMM") -> febrero | H57: 23 | I57: =TEXT(gastos[[#This Row],[Fecha]],"DDDD") -> viernes | J57: =DATE(YEAR(F57),MONTH(F57),H57) -> 45345 | M57: 0 | N57: 1850 | O57: =SUM(M57:N57) -> 1850 | P57: 0 | Q57: 0 | R57: 0 | S57: 0 | T57: =IFERROR(VLOOKUP($A57,Tabla3[#All],2,0),"no esta registrado") -> Centro Cuesta Nacional S.A.S.//Supermercados Nacional//Casa Cuesta//Ferretería Cuesta//JUMBO//Bebemundo
A58: 101602465 | B58: 1 | C58: 2 | D58: =IF(C58=1,Leyenda!$C$3,IF(C58=2,Leyenda!$C$4,IF(C58=3,Leyenda!$C$5,IF(C58=4,Leyenda!$C$6,IF(C58=5,Leyenda!$C$7,IF(C58=6,Leyenda!$C$8,IF(C58=7,Leyenda!$C$9,IF(C58=8,Leyenda!$C$10," "))))))))&IF(C58=9,Leyenda!$C$11,IF(C58=10,Leyenda!$C$12,IF(C58=11,Leyenda!$C$13,IF(C58=12,Leyenda!D115," ")))) -> GASTOS POR TRABAJOS, SUMINISTROS Y SERVICIOS | E58: E310004336398 | F58: 45339 | G58: =TEXT(F58,"MMMM") -> febrero | H58: 26 | I58: =TEXT(gastos[[#This Row],[Fecha]],"DDDD") -> lunes | J58: =DATE(YEAR(F58),MONTH(F58),H58) -> 45348 | M58: 0 | N58: =14383-1063.11 -> 13319.89 | O58: =SUM(M58:N58) -> 13319.89 | P58: 1063.11 | Q58: 0 | R58: 0 | S58: 0 | T58: =IFERROR(VLOOKUP($A58,Tabla3[#All],2,0),"no esta registrado") -> Bravo, S.A.//Supermercados Bravo
A59: 101796822 | B59: 1 | C59: 2 | D59: =IF(C59=1,Leyenda!$C$3,IF(C59=2,Leyenda!$C$4,IF(C59=3,Leyenda!$C$5,IF(C59=4,Leyenda!$C$6,IF(C59=5,Leyenda!$C$7,IF(C59=6,Leyenda!$C$8,IF(C59=7,Leyenda!$C$9,IF(C59=8,Leyenda!$C$10," "))))))))&IF(C59=9,Leyenda!$C$11,IF(C59=10,Leyenda!$C$12,IF(C59=11,Leyenda!$C$13,IF(C59=12,Leyenda!D116," ")))) -> GASTOS POR TRABAJOS, SUMINISTROS Y SERVICIOS | E59: E310002301031 | F59: 45340 | G59: =TEXT(F59,"MMMM") -> febrero | H59: 14 | I59: =TEXT(gastos[[#This Row],[Fecha]],"DDDD") -> miércoles | J59: =DATE(YEAR(F59),MONTH(F59),H59) -> 45336 | M59: 0 | N59: =4440-677.31 -> 3762.69 | O59: =SUM(M59:N59) -> 3762.69 | P59: 677.31 | Q59: 0 | R59: 0 | S59: 0 | T59: =IFERROR(VLOOKUP($A59,Tabla3[#All],2,0),"no esta registrado") -> Grupo Ramos, S. A.//Super Pola//La Sirena
A60: 101602465 | B60: 1 | C60: 2 | D60: =IF(C60=1,Leyenda!$C$3,IF(C60=2,Leyenda!$C$4,IF(C60=3,Leyenda!$C$5,IF(C60=4,Leyenda!$C$6,IF(C60=5,Leyenda!$C$7,IF(C60=6,Leyenda!$C$8,IF(C60=7,Leyenda!$C$9,IF(C60=8,Leyenda!$C$10," "))))))))&IF(C60=9,Leyenda!$C$11,IF(C60=10,Leyenda!$C$12,IF(C60=11,Leyenda!$C$13,IF(C60=12,Leyenda!D117," ")))) -> GASTOS POR TRABAJOS, SUMINISTROS Y SERVICIOS | E60: E310004176176 | F60: 45341 | G60: =TEXT(F60,"MMMM") -> febrero | H60: 8 | I60: =TEXT(gastos[[#This Row],[Fecha]],"DDDD") -> jueves | J60: =DATE(YEAR(F60),MONTH(F60),H60) -> 45330 | M60: 0 | N60: =13937-1158.35 -> 12778.65 | O60: =SUM(M60:N60) -> 12778.65 | P60: 1158.35 | Q60: 0 | R60: 0 | S60: 0 | T60: =IFERROR(VLOOKUP($A60,Tabla3[#All],2,0),"no esta registrado") -> Bravo, S.A.//Supermercados Bravo
A61: 101796822 | B61: 1 | C61: 2 | D61: =IF(C61=1,Leyenda!$C$3,IF(C61=2,Leyenda!$C$4,IF(C61=3,Leyenda!$C$5,IF(C61=4,Leyenda!$C$6,IF(C61=5,Leyenda!$C$7,IF(C61=6,Leyenda!$C$8,IF(C61=7,Leyenda!$C$9,IF(C61=8,Leyenda!$C$10," "))))))))&IF(C61=9,Leyenda!$C$11,IF(C61=10,Leyenda!$C$12,IF(C61=11,Leyenda!$C$13,IF(C61=12,Leyenda!D118," ")))) -> GASTOS POR TRABAJOS, SUMINISTROS Y SERVICIOS | E61: E310001348750 | F61: 45342 | G61: =TEXT(F61,"MMMM") -> febrero | H61: 2 | I61: =TEXT(gastos[[#This Row],[Fecha]],"DDDD") -> viernes | J61: =DATE(YEAR(F61),MONTH(F61),H61) -> 45324 | M61: 0 | N61: =2975-453.83 -> 2521.17 | O61: =SUM(M61:N61) -> 2521.17 | P61: 453.83 | Q61: 0 | R61: 0 | S61: 0 | T61: =IFERROR(VLOOKUP($A61,Tabla3[#All],2,0),"no esta registrado") -> Grupo Ramos, S. A.//Super Pola//La Sirena
A62: 101602465 | B62: 1 | C62: 2 | D62: =IF(C62=1,Leyenda!$C$3,IF(C62=2,Leyenda!$C$4,IF(C62=3,Leyenda!$C$5,IF(C62=4,Leyenda!$C$6,IF(C62=5,Leyenda!$C$7,IF(C62=6,Leyenda!$C$8,IF(C62=7,Leyenda!$C$9,IF(C62=8,Leyenda!$C$10," "))))))))&IF(C62=9,Leyenda!$C$11,IF(C62=10,Leyenda!$C$12,IF(C62=11,Leyenda!$C$13,IF(C62=12,Leyenda!D119," ")))) -> GASTOS POR TRABAJOS, SUMINISTROS Y SERVICIOS | E62: E310004176965 | F62: 45343 | G62: =TEXT(F62,"MMMM") -> febrero | H62: 12 | I62: =TEXT(gastos[[#This Row],[Fecha]],"DDDD") -> lunes | J62: =DATE(YEAR(F62),MONTH(F62),H62) -> 45334 | M62: 0 | N62: =2847-150.71 -> 2696.29 | O62: =SUM(M62:N62) -> 2696.29 | P62: 150.71 | Q62: 0 | R62: 0 | S62: 0 | T62: =IFERROR(VLOOKUP($A62,Tabla3[#All],2,0),"no esta registrado") -> Bravo, S.A.//Supermercados Bravo
A63: 101602465 | B63: 1 | C63: 2 | D63: =IF(C63=1,Leyenda!$C$3,IF(C63=2,Leyenda!$C$4,IF(C63=3,Leyenda!$C$5,IF(C63=4,Leyenda!$C$6,IF(C63=5,Leyenda!$C$7,IF(C63=6,Leyenda!$C$8,IF(C63=7,Leyenda!$C$9,IF(C63=8,Leyenda!$C$10," "))))))))&IF(C63=9,Leyenda!$C$11,IF(C63=10,Leyenda!$C$12,IF(C63=11,Leyenda!$C$13,IF(C63=12,Leyenda!D120," ")))) -> GASTOS POR TRABAJOS, SUMINISTROS Y SERVICIOS | E63: E310004178560 | F63: 45344 | G63: =TEXT(F63,"MMMM") -> febrero | H63: 17 | I63: =TEXT(gastos[[#This Row],[Fecha]],"DDDD") -> sábado | J63: =DATE(YEAR(F63),MONTH(F63),H63) -> 45339 | M63: 0 | N63: =12291-1090.15 -> 11200.85 | O63: =SUM(M63:N63) -> 11200.85 | P63: 1090.15 | Q63: 0 | R63: 0 | S63: 0 | T63: =IFERROR(VLOOKUP($A63,Tabla3[#All],2,0),"no esta registrado") -> Bravo, S.A.//Supermercados Bravo
A64: 101019921 | B64: 1 | C64: 2 | D64: =IF(C64=1,Leyenda!$C$3,IF(C64=2,Leyenda!$C$4,IF(C64=3,Leyenda!$C$5,IF(C64=4,Leyenda!$C$6,IF(C64=5,Leyenda!$C$7,IF(C64=6,Leyenda!$C$8,IF(C64=7,Leyenda!$C$9,IF(C64=8,Leyenda!$C$10," "))))))))&IF(C64=9,Leyenda!$C$11,IF(C64=10,Leyenda!$C$12,IF(C64=11,Leyenda!$C$13,IF(C64=12,Leyenda!D121," ")))) -> GASTOS POR TRABAJOS, SUMINISTROS Y SERVICIOS | E64: B0114154295 | F64: 45345 | G64: =TEXT(F64,"MMMM") -> febrero | H64: 16 | I64: =TEXT(gastos[[#This Row],[Fecha]],"DDDD") -> viernes | J64: =DATE(YEAR(F64),MONTH(F64),H64) -> 45338 | M64: 0 | N64: =1655.11-112.31 -> 1542.8 | O64: =SUM(M64:N64) -> 1542.8 | P64: 112.31 | Q64: 0 | R64: 0 | S64: 0 | T64: =IFERROR(VLOOKUP($A64,Tabla3[#All],2,0),"no esta registrado") -> Centro Cuesta Nacional S.A.S.//Supermercados Nacional//Casa Cuesta//Ferretería Cuesta//JUMBO//Bebemundo
A65: 101602465 | B65: 1 | C65: 2 | D65: =IF(C65=1,Leyenda!$C$3,IF(C65=2,Leyenda!$C$4,IF(C65=3,Leyenda!$C$5,IF(C65=4,Leyenda!$C$6,IF(C65=5,Leyenda!$C$7,IF(C65=6,Leyenda!$C$8,IF(C65=7,Leyenda!$C$9,IF(C65=8,Leyenda!$C$10," "))))))))&IF(C65=9,Leyenda!$C$11,IF(C65=10,Leyenda!$C$12,IF(C65=11,Leyenda!$C$13,IF(C65=12,Leyenda!D122," ")))) -> GASTOS POR TRABAJOS, SUMINISTROS Y SERVICIOS | E65: E310004054564 | F65: 45346 | G65: =TEXT(F65,"MMMM") -> febrero | H65: 29 | I65: =TEXT(gastos[[#This Row],[Fecha]],"DDDD") -> jueves | J65: =DATE(YEAR(F65),MONTH(F65),H65) -> 45351 | M65: 0 | N65: =13042-1075.67 -> 11966.33 | O65: =SUM(M65:N65) -> 11966.33 | P65: 1075.67 | Q65: 0 | R65: 0 | S65: 0 | T65: =IFERROR(VLOOKUP($A65,Tabla3[#All],2,0),"no esta registrado") -> Bravo, S.A.//Supermercados Bravo
A66: 130196796 | B66: 1 | C66: 2 | D66: =IF(C66=1,Leyenda!$C$3,IF(C66=2,Leyenda!$C$4,IF(C66=3,Leyenda!$C$5,IF(C66=4,Leyenda!$C$6,IF(C66=5,Leyenda!$C$7,IF(C66=6,Leyenda!$C$8,IF(C66=7,Leyenda!$C$9,IF(C66=8,Leyenda!$C$10," "))))))))&IF(C66=9,Leyenda!$C$11,IF(C66=10,Leyenda!$C$12,IF(C66=11,Leyenda!$C$13,IF(C66=12,Leyenda!D123," ")))) -> GASTOS POR TRABAJOS, SUMINISTROS Y SERVICIOS | E66: B0100054417 | F66: 45347 | G66: =TEXT(F66,"MMMM") -> febrero | H66: 9 | I66: =TEXT(gastos[[#This Row],[Fecha]],"DDDD") -> viernes | J66: =DATE(YEAR(F66),MONTH(F66),H66) -> 45331 | M66: 2606 | N66: 0 | O66: =SUM(M66:N66) -> 2606 | P66: 0 | Q66: 0 | R66: 0 | S66: 0 | T66: =IFERROR(VLOOKUP($A66,Tabla3[#All],2,0),"no esta registrado") -> ACADEMIA EUROPEA
A67: 130196796 | B67: 1 | C67: 2 | D67: =IF(C67=1,Leyenda!$C$3,IF(C67=2,Leyenda!$C$4,IF(C67=3,Leyenda!$C$5,IF(C67=4,Leyenda!$C$6,IF(C67=5,Leyenda!$C$7,IF(C67=6,Leyenda!$C$8,IF(C67=7,Leyenda!$C$9,IF(C67=8,Leyenda!$C$10," "))))))))&IF(C67=9,Leyenda!$C$11,IF(C67=10,Leyenda!$C$12,IF(C67=11,Leyenda!$C$13,IF(C67=12,Leyenda!D124," ")))) -> GASTOS POR TRABAJOS, SUMINISTROS Y SERVICIOS | E67: B0100054418 | F67: 45348 | G67: =TEXT(F67,"MMMM") -> febrero | H67: 9 | I67: =TEXT(gastos[[#This Row],[Fecha]],"DDDD") -> viernes | J67: =DATE(YEAR(F67),MONTH(F67),H67) -> 45331 | M67: 2606 | N67: 0 | O67: =SUM(M67:N67) -> 2606 | P67: 0 | Q67: 0 | R67: 0 | S67: 0 | T67: =IFERROR(VLOOKUP($A67,Tabla3[#All],2,0),"no esta registrado") -> ACADEMIA EUROPEA
A68: 130196796 | B68: 1 | C68: 2 | D68: =IF(C68=1,Leyenda!$C$3,IF(C68=2,Leyenda!$C$4,IF(C68=3,Leyenda!$C$5,IF(C68=4,Leyenda!$C$6,IF(C68=5,Leyenda!$C$7,IF(C68=6,Leyenda!$C$8,IF(C68=7,Leyenda!$C$9,IF(C68=8,Leyenda!$C$10," "))))))))&IF(C68=9,Leyenda!$C$11,IF(C68=10,Leyenda!$C$12,IF(C68=11,Leyenda!$C$13,IF(C68=12,Leyenda!D125," ")))) -> GASTOS POR TRABAJOS, SUMINISTROS Y SERVICIOS | E68: B0100054419 | F68: 45349 | G68: =TEXT(F68,"MMMM") -> febrero | H68: 9 | I68: =TEXT(gastos[[#This Row],[Fecha]],"DDDD") -> viernes | J68: =DATE(YEAR(F68),MONTH(F68),H68) -> 45331 | M68: 2876 | N68: 0 | O68: =SUM(M68:N68) -> 2876 | P68: 0 | Q68: 0 | R68: 0 | S68: 0 | T68: =IFERROR(VLOOKUP($A68,Tabla3[#All],2,0),"no esta registrado") -> ACADEMIA EUROPEA
A69: 130196796 | B69: 1 | C69: 2 | D69: =IF(C69=1,Leyenda!$C$3,IF(C69=2,Leyenda!$C$4,IF(C69=3,Leyenda!$C$5,IF(C69=4,Leyenda!$C$6,IF(C69=5,Leyenda!$C$7,IF(C69=6,Leyenda!$C$8,IF(C69=7,Leyenda!$C$9,IF(C69=8,Leyenda!$C$10," "))))))))&IF(C69=9,Leyenda!$C$11,IF(C69=10,Leyenda!$C$12,IF(C69=11,Leyenda!$C$13,IF(C69=12,Leyenda!D126," ")))) -> GASTOS POR TRABAJOS, SUMINISTROS Y SERVICIOS | E69: B0100055443 | F69: 45350 | G69: =TEXT(F69,"MMMM") -> febrero | H69: 23 | I69: =TEXT(gastos[[#This Row],[Fecha]],"DDDD") -> viernes | J69: =DATE(YEAR(F69),MONTH(F69),H69) -> 45345 | M69: 2876 | N69: 0 | O69: =SUM(M69:N69) -> 2876 | P69: 0 | Q69: 0 | R69: 0 | S69: 0 | T69: =IFERROR(VLOOKUP($A69,Tabla3[#All],2,0),"no esta registrado") -> ACADEMIA EUROPEA
A70: 130196796 | B70: 1 | C70: 2 | D70: =IF(C70=1,Leyenda!$C$3,IF(C70=2,Leyenda!$C$4,IF(C70=3,Leyenda!$C$5,IF(C70=4,Leyenda!$C$6,IF(C70=5,Leyenda!$C$7,IF(C70=6,Leyenda!$C$8,IF(C70=7,Leyenda!$C$9,IF(C70=8,Leyenda!$C$10," "))))))))&IF(C70=9,Leyenda!$C$11,IF(C70=10,Leyenda!$C$12,IF(C70=11,Leyenda!$C$13,IF(C70=12,Leyenda!D127," ")))) -> GASTOS POR TRABAJOS, SUMINISTROS Y SERVICIOS | E70: B0100054491 | F70: 45351 | G70: =TEXT(F70,"MMMM") -> febrero | H70: 16 | I70: =TEXT(gastos[[#This Row],[Fecha]],"DDDD") -> viernes | J70: =DATE(YEAR(F70),MONTH(F70),H70) -> 45338 | M70: 3190 | N70: 0 | O70: =SUM(M70:N70) -> 3190 | P70: 0 | Q70: 0 | R70: 0 | S70: 0 | T70: =IFERROR(VLOOKUP($A70,Tabla3[#All],2,0),"no esta registrado") -> ACADEMIA EUROPEA
A71: 430030341 | B71: 1 | C71: 2 | D71: =IF(C71=1,Leyenda!$C$3,IF(C71=2,Leyenda!$C$4,IF(C71=3,Leyenda!$C$5,IF(C71=4,Leyenda!$C$6,IF(C71=5,Leyenda!$C$7,IF(C71=6,Leyenda!$C$8,IF(C71=7,Leyenda!$C$9,IF(C71=8,Leyenda!$C$10," "))))))))&IF(C71=9,Leyenda!$C$11,IF(C71=10,Leyenda!$C$12,IF(C71=11,Leyenda!$C$13,IF(C71=12,Leyenda!D128," ")))) -> GASTOS POR TRABAJOS, SUMINISTROS Y SERVICIOS | E71: B0100013050 | F71: 45338 | G71: =TEXT(F71,"MMMM") -> febrero | H71: 29 | I71: =TEXT(gastos[[#This Row],[Fecha]],"DDDD") -> jueves | J71: =DATE(YEAR(F71),MONTH(F71),H71) -> 45351 | M71: 7100 | N71: 0 | O71: =SUM(M71:N71) -> 7100 | P71: 0 | Q71: 0 | R71: 0 | S71: 0 | T71: =IFERROR(VLOOKUP($A71,Tabla3[#All],2,0),"no esta registrado") -> COLEGIO SANTA ROSA DE LIMA
A72: 430030341 | B72: 1 | C72: 2 | D72: =IF(C72=1,Leyenda!$C$3,IF(C72=2,Leyenda!$C$4,IF(C72=3,Leyenda!$C$5,IF(C72=4,Leyenda!$C$6,IF(C72=5,Leyenda!$C$7,IF(C72=6,Leyenda!$C$8,IF(C72=7,Leyenda!$C$9,IF(C72=8,Leyenda!$C$10," "))))))))&IF(C72=9,Leyenda!$C$11,IF(C72=10,Leyenda!$C$12,IF(C72=11,Leyenda!$C$13,IF(C72=12,Leyenda!D129," ")))) -> GASTOS POR TRABAJOS, SUMINISTROS Y SERVICIOS | E72: B0100013051 | F72: 45339 | G72: =TEXT(F72,"MMMM") -> febrero | H72: 29 | I72: =TEXT(gastos[[#This Row],[Fecha]],"DDDD") -> jueves | J72: =DATE(YEAR(F72),MONTH(F72),H72) -> 45351 | M72: 6800 | N72: 0 | O72: =SUM(M72:N72) -> 6800 | P72: 0 | Q72: 0 | R72: 0 | S72: 0 | T72: =IFERROR(VLOOKUP($A72,Tabla3[#All],2,0),"no esta registrado") -> COLEGIO SANTA ROSA DE LIMA
A73: 430030341 | B73: 1 | C73: 2 | D73: =IF(C73=1,Leyenda!$C$3,IF(C73=2,Leyenda!$C$4,IF(C73=3,Leyenda!$C$5,IF(C73=4,Leyenda!$C$6,IF(C73=5,Leyenda!$C$7,IF(C73=6,Leyenda!$C$8,IF(C73=7,Leyenda!$C$9,IF(C73=8,Leyenda!$C$10," "))))))))&IF(C73=9,Leyenda!$C$11,IF(C73=10,Leyenda!$C$12,IF(C73=11,Leyenda!$C$13,IF(C73=12,Leyenda!D130," ")))) -> GASTOS POR TRABAJOS, SUMINISTROS Y SERVICIOS | E73: B0100013052 | F73: 45340 | G73: =TEXT(F73,"MMMM") -> febrero | H73: 29 | I73: =TEXT(gastos[[#This Row],[Fecha]],"DDDD") -> jueves | J73: =DATE(YEAR(F73),MONTH(F73),H73) -> 45351 | M73: 6800 | N73: 0 | O73: =SUM(M73:N73) -> 6800 | P73: 0 | Q73: 0 | R73: 0 | S73: 0 | T73: =IFERROR(VLOOKUP($A73,Tabla3[#All],2,0),"no esta registrado") -> COLEGIO SANTA ROSA DE LIMA
A74: 101001577 | B74: 1 | C74: 2 | D74: =IF(C74=1,Leyenda!$C$3,IF(C74=2,Leyenda!$C$4,IF(C74=3,Leyenda!$C$5,IF(C74=4,Leyenda!$C$6,IF(C74=5,Leyenda!$C$7,IF(C74=6,Leyenda!$C$8,IF(C74=7,Leyenda!$C$9,IF(C74=8,Leyenda!$C$10," "))))))))&IF(C74=9,Leyenda!$C$11,IF(C74=10,Leyenda!$C$12,IF(C74=11,Leyenda!$C$13,IF(C74=12,Leyenda!D131," ")))) -> GASTOS POR TRABAJOS, SUMINISTROS Y SERVICIOS | E74: E310008901348 | F74: 45341 | G74: =TEXT(F74,"MMMM") -> febrero | H74: 7 | I74: =TEXT(gastos[[#This Row],[Fecha]],"DDDD") -> miércoles | J74: =DATE(YEAR(F74),MONTH(F74),H74) -> 45329 | M74: 830 | N74: 0 | O74: =SUM(M74:N74) -> 830 | P74: 149.4 | Q74: 0 | R74: 0 | S74: 0 | T74: =IFERROR(VLOOKUP($A74,Tabla3[#All],2,0),"no esta registrado") -> CLARO//CODETEL
A75: 101001577 | B75: 1 | C75: 2 | D75: =IF(C75=1,Leyenda!$C$3,IF(C75=2,Leyenda!$C$4,IF(C75=3,Leyenda!$C$5,IF(C75=4,Leyenda!$C$6,IF(C75=5,Leyenda!$C$7,IF(C75=6,Leyenda!$C$8,IF(C75=7,Leyenda!$C$9,IF(C75=8,Leyenda!$C$10," "))))))))&IF(C75=9,Leyenda!$C$11,IF(C75=10,Leyenda!$C$12,IF(C75=11,Leyenda!$C$13,IF(C75=12,Leyenda!D132," ")))) -> GASTOS POR TRABAJOS, SUMINISTROS Y SERVICIOS | E75: E310008898278 | F75: 45342 | G75: =TEXT(F75,"MMMM") -> febrero | H75: 7 | I75: =TEXT(gastos[[#This Row],[Fecha]],"DDDD") -> miércoles | J75: =DATE(YEAR(F75),MONTH(F75),H75) -> 45329 | M75: 2407.69 | N75: 0 | O75: =SUM(M75:N75) -> 2407.69 | P75: 433.39 | Q75: 0 | R75: 0 | S75: 0 | T75: =IFERROR(VLOOKUP($A75,Tabla3[#All],2,0),"no esta registrado") -> CLARO//CODETEL
A76: 101820217 | B76: 1 | C76: 2 | D76: =IF(C76=1,Leyenda!$C$3,IF(C76=2,Leyenda!$C$4,IF(C76=3,Leyenda!$C$5,IF(C76=4,Leyenda!$C$6,IF(C76=5,Leyenda!$C$7,IF(C76=6,Leyenda!$C$8,IF(C76=7,Leyenda!$C$9,IF(C76=8,Leyenda!$C$10," "))))))))&IF(C76=9,Leyenda!$C$11,IF(C76=10,Leyenda!$C$12,IF(C76=11,Leyenda!$C$13,IF(C76=12,Leyenda!D133," ")))) -> GASTOS POR TRABAJOS, SUMINISTROS Y SERVICIOS | E76: B0110183279 | F76: 45343 | G76: =TEXT(F76,"MMMM") -> febrero | H76: 19 | I76: =TEXT(gastos[[#This Row],[Fecha]],"DDDD") -> lunes | J76: =DATE(YEAR(F76),MONTH(F76),H76) -> 45341 | M76: 6340.43 | N76: 0 | O76: =SUM(M76:N76) -> 6340.43 | P76: 0 | Q76: 0 | R76: 0 | S76: 0 | T76: =IFERROR(VLOOKUP($A76,Tabla3[#All],2,0),"no esta registrado") -> EDEESTE
A77: 101136792 | B77: 1 | C77: 7 | D77: =IF(C77=1,Leyenda!$C$3,IF(C77=2,Leyenda!$C$4,IF(C77=3,Leyenda!$C$5,IF(C77=4,Leyenda!$C$6,IF(C77=5,Leyenda!$C$7,IF(C77=6,Leyenda!$C$8,IF(C77=7,Leyenda!$C$9,IF(C77=8,Leyenda!$C$10," "))))))))&IF(C77=9,Leyenda!$C$11,IF(C77=10,Leyenda!$C$12,IF(C77=11,Leyenda!$C$13,IF(C77=12,Leyenda!D134," ")))) -> GASTOS FINANCIEROS | E77: B0188189014 | F77: 45344 | G77: =TEXT(F77,"MMMM") -> febrero | H77: 20 | I77: =TEXT(gastos[[#This Row],[Fecha]],"DDDD") -> martes | J77: =DATE(YEAR(F77),MONTH(F77),H77) -> 45342 | M77: 22604.17 | N77: 0 | O77: =SUM(M77:N77) -> 22604.17 | P77: 0 | Q77: 0 | R77: 0 | S77: 0 | T77: =IFERROR(VLOOKUP($A77,Tabla3[#All],2,0),"no esta registrado") -> Banco Multiple BHD León, S. A.
... A90: 130064423 | B90: 1 | C90: 2 | D90: =IF(C90=1,Leyenda!$C$3,IF(C90=2,Leyenda!$C$4,IF(C90=3,Leyenda!$C$5,IF(C90=4,Leyenda!$C$6,IF(C90=5,Leyenda!$C$7,IF(C90=6,Leyenda!$C$8,IF(C90=7,Leyenda!$C$9,IF(C90=8,Leyenda!$C$10," "))))))))&IF(C90=9,Leyenda!$C$11,IF(C90=10,Leyenda!$C$12,IF(C90=11,Leyenda!$C$13,IF(C90=12,Leyenda!D147," ")))) -> GASTOS POR TRABAJOS, SUMINISTROS Y SERVICIOS | E90: B0101702945 | F90: 45356 | G90: =TEXT(F90,"MMMM") -> marzo | H90: 25 | I90: =TEXT(gastos[[#This Row],[Fecha]],"DDDD") -> lunes | J90: =DATE(YEAR(F90),MONTH(F90),H90) -> 45376 | M90: 0 | N90: 1386.42 | O90: =SUM(M90:N90) -> 1386.42 | P90: 0 | Q90: 0 | R90: 0 | S90: 0 | T90: =IFERROR(VLOOKUP($A90,Tabla3[#All],2,0),"no esta registrado") -> Farmacía Medicar GBC, A. H.
A91: 130897026 | B91: 1 | C91: 2 | D91: =IF(C91=1,Leyenda!$C$3,IF(C91=2,Leyenda!$C$4,IF(C91=3,Leyenda!$C$5,IF(C91=4,Leyenda!$C$6,IF(C91=5,Leyenda!$C$7,IF(C91=6,Leyenda!$C$8,IF(C91=7,Leyenda!$C$9,IF(C91=8,Leyenda!$C$10," "))))))))&IF(C91=9,Leyenda!$C$11,IF(C91=10,Leyenda!$C$12,IF(C91=11,Leyenda!$C$13,IF(C91=12,Leyenda!D148," ")))) -> GASTOS POR TRABAJOS, SUMINISTROS Y SERVICIOS | E91: B0100034524 | F91: 45356 | G91: =TEXT(F91,"MMMM") -> marzo | H91: 15 | I91: =TEXT(gastos[[#This Row],[Fecha]],"DDDD") -> viernes | J91: =DATE(YEAR(F91),MONTH(F91),H91) -> 45366 | M91: 0 | N91: =1595-243.31 -> 1351.69 | O91: =SUM(M91:N91) -> 1351.69 | P91: 243,31 | Q91: 0 | R91: 0 | S91: 0 | T91: =IFERROR(VLOOKUP($A91,Tabla3[#All],2,0),"no esta registrado") -> BAKERS DR LLC
A92: 130832447 | B92: 1 | C92: 2 | D92: =IF(C92=1,Leyenda!$C$3,IF(C92=2,Leyenda!$C$4,IF(C92=3,Leyenda!$C$5,IF(C92=4,Leyenda!$C$6,IF(C92=5,Leyenda!$C$7,IF(C92=6,Leyenda!$C$8,IF(C92=7,Leyenda!$C$9,IF(C92=8,Leyenda!$C$10," "))))))))&IF(C92=9,Leyenda!$C$11,IF(C92=10,Leyenda!$C$12,IF(C92=11,Leyenda!$C$13,IF(C92=12,Leyenda!D149," ")))) -> GASTOS POR TRABAJOS, SUMINISTROS Y SERVICIOS | E92: B0100007670 | F92: 45356 | G92: =TEXT(F92,"MMMM") -> marzo | H92: 5 | I92: =TEXT(gastos[[#This Row],[Fecha]],"DDDD") -> martes | J92: =DATE(YEAR(F92),MONTH(F92),H92) -> 45356 | M92: 0 | N92: 16271 | O92: =SUM(M92:N92) -> 16271 | P92: 2928.78 | Q92: 0 | R92: 0 | S92: 0 | T92: =IFERROR(VLOOKUP($A92,Tabla3[#All],2,0),"no esta registrado") -> no esta registrado
A93: 101871865 | B93: 1 | C93: 2 | D93: =IF(C93=1,Leyenda!$C$3,IF(C93=2,Leyenda!$C$4,IF(C93=3,Leyenda!$C$5,IF(C93=4,Leyenda!$C$6,IF(C93=5,Leyenda!$C$7,IF(C93=6,Leyenda!$C$8,IF(C93=7,Leyenda!$C$9,IF(C93=8,Leyenda!$C$10," "))))))))&IF(C93=9,Leyenda!$C$11,IF(C93=10,Leyenda!$C$12,IF(C93=11,Leyenda!$C$13,IF(C93=12,Leyenda!D150," ")))) -> GASTOS POR TRABAJOS, SUMINISTROS Y SERVICIOS | E93: B0102844307 | F93: 45356 | G93: =TEXT(F93,"MMMM") -> marzo | H93: 15 | I93: =TEXT(gastos[[#This Row],[Fecha]],"DDDD") -> viernes | J93: =DATE(YEAR(F93),MONTH(F93),H93) -> 45366 | M93: 0 | N93: =1320-201.36 -> 1118.64 | O93: =SUM(M93:N93) -> 1118.64 | P93: 201.36 | Q93: 0 | R93: 0 | S93: 0 | T93: =IFERROR(VLOOKUP($A93,Tabla3[#All],2,0),"no esta registrado") -> Grupo Carol, S. A.//Farmacia Carol
A94: 101801875 | B94: 1 | C94: 2 | D94: =IF(C94=1,Leyenda!$C$3,IF(C94=2,Leyenda!$C$4,IF(C94=3,Leyenda!$C$5,IF(C94=4,Leyenda!$C$6,IF(C94=5,Leyenda!$C$7,IF(C94=6,Leyenda!$C$8,IF(C94=7,Leyenda!$C$9,IF(C94=8,Leyenda!$C$10," "))))))))&IF(C94=9,Leyenda!$C$11,IF(C94=10,Leyenda!$C$12,IF(C94=11,Leyenda!$C$13,IF(C94=12,Leyenda!D151," ")))) -> GASTOS POR TRABAJOS, SUMINISTROS Y SERVICIOS | E94: B0106222313 | F94: 45356 | G94: =TEXT(F94,"MMMM") -> marzo | H94: 24 | I94: =TEXT(gastos[[#This Row],[Fecha]],"DDDD") -> domingo | J94: =DATE(YEAR(F94),MONTH(F94),H94) -> 45375 | M94: 0 | N94: 2350 | O94: =SUM(M94:N94) -> 2350 | P94: 0 | Q94: 0 | R94: 0 | S94: 0 | T94: =IFERROR(VLOOKUP($A94,Tabla3[#All],2,0),"no esta registrado") -> Pricesmart Dominicana S. A.
A95: 101019921 | B95: 1 | C95: 2 | D95: =IF(C95=1,Leyenda!$C$3,IF(C95=2,Leyenda!$C$4,IF(C95=3,Leyenda!$C$5,IF(C95=4,Leyenda!$C$6,IF(C95=5,Leyenda!$C$7,IF(C95=6,Leyenda!$C$8,IF(C95=7,Leyenda!$C$9,IF(C95=8,Leyenda!$C$10," "))))))))&IF(C95=9,Leyenda!$C$11,IF(C95=10,Leyenda!$C$12,IF(C95=11,Leyenda!$C$13,IF(C95=12,Leyenda!D152," ")))) -> GASTOS POR TRABAJOS, SUMINISTROS Y SERVICIOS | E95: B0114156957 | F95: 45356 | G95: =TEXT(F95,"MMMM") -> marzo | H95: 2 | I95: =TEXT(gastos[[#This Row],[Fecha]],"DDDD") -> sábado | J95: =DATE(YEAR(F95),MONTH(F95),H95) -> 45353 | M95: 0 | N95: =1044.4-72.28 -> 972.12 | O95: =SUM(M95:N95) -> 972.12 | P95: 72,28 | Q95: 0 | R95: 0 | S95: 0 | T95: =IFERROR(VLOOKUP($A95,Tabla3[#All],2,0),"no esta registrado") -> Centro Cuesta Nacional S.A.S.//Supermercados Nacional//Casa Cuesta//Ferretería Cuesta//JUMBO//Bebemundo
A96: 101568224 | B96: 1 | C96: 2 | D96: =IF(C96=1,Leyenda!$C$3,IF(C96=2,Leyenda!$C$4,IF(C96=3,Leyenda!$C$5,IF(C96=4,Leyenda!$C$6,IF(C96=5,Leyenda!$C$7,IF(C96=6,Leyenda!$C$8,IF(C96=7,Leyenda!$C$9,IF(C96=8,Leyenda!$C$10," "))))))))&IF(C96=9,Leyenda!$C$11,IF(C96=10,Leyenda!$C$12,IF(C96=11,Leyenda!$C$13,IF(C96=12,Leyenda!D153," ")))) -> GASTOS POR TRABAJOS, SUMINISTROS Y SERVICIOS | E96: B0100491067 | F96: 45356 | G96: =TEXT(F96,"MMMM") -> marzo | H96: 16 | I96: =TEXT(gastos[[#This Row],[Fecha]],"DDDD") -> sábado | J96: =DATE(YEAR(F96),MONTH(F96),H96) -> 45367 | M96: 0 | N96: 2822.57 | O96: =SUM(M96:N96) -> 2822.57 | P96: 508.06 | Q96: 0 | R96: 282.26 | S96: 0 | T96: =IFERROR(VLOOKUP($A96,Tabla3[#All],2,0),"no esta registrado") -> Concesiones y Servicios, S. A. / Burger King
A97: 101801875 | B97: 1 | C97: 2 | D97: =IF(C97=1,Leyenda!$C$3,IF(C97=2,Leyenda!$C$4,IF(C97=3,Leyenda!$C$5,IF(C97=4,Leyenda!$C$6,IF(C97=5,Leyenda!$C$7,IF(C97=6,Leyenda!$C$8,IF(C97=7,Leyenda!$C$9,IF(C97=8,Leyenda!$C$10," "))))))))&IF(C97=9,Leyenda!$C$11,IF(C97=10,Leyenda!$C$12,IF(C97=11,Leyenda!$C$13,IF(C97=12,Leyenda!D154," ")))) -> GASTOS POR TRABAJOS, SUMINISTROS Y SERVICIOS | E97: B0105983516 | F97: 45356 | G97: =TEXT(F97,"MMMM") -> marzo | H97: 24 | I97: =TEXT(gastos[[#This Row],[Fecha]],"DDDD") -> domingo | J97: =DATE(YEAR(F97),MONTH(F97),H97) -> 45375 | M97: 0 | N97: =7270-1108.97 -> 6161.03 | O97: =SUM(M97:N97) -> 6161.03 | P97: 1108.97 | Q97: 0 | R97: 0 | S97: 0 | T97: =IFERROR(VLOOKUP($A97,Tabla3[#All],2,0),"no esta registrado") -> Pricesmart Dominicana S. A.
A98: 101019921 | B98: 1 | C98: 2 | D98: =IF(C98=1,Leyenda!$C$3,IF(C98=2,Leyenda!$C$4,IF(C98=3,Leyenda!$C$5,IF(C98=4,Leyenda!$C$6,IF(C98=5,Leyenda!$C$7,IF(C98=6,Leyenda!$C$8,IF(C98=7,Leyenda!$C$9,IF(C98=8,Leyenda!$C$10," "))))))))&IF(C98=9,Leyenda!$C$11,IF(C98=10,Leyenda!$C$12,IF(C98=11,Leyenda!$C$13,IF(C98=12,Leyenda!D155," ")))) -> GASTOS POR TRABAJOS, SUMINISTROS Y SERVICIOS | E98: B0114459203 | F98: 45356 | G98: =TEXT(F98,"MMMM") -> marzo | H98: 8 | I98: =TEXT(gastos[[#This Row],[Fecha]],"DDDD") -> viernes | J98: =DATE(YEAR(F98),MONTH(F98),H98) -> 45359 | M98: 0 | N98: =2851-434.97 -> 2416.03 | O98: =SUM(M98:N98) -> 2416.03 | P98: 434.98 | Q98: 0 | R98: 0 | S98: 0 | T98: =IFERROR(VLOOKUP($A98,Tabla3[#All],2,0),"no esta registrado") -> Centro Cuesta Nacional S.A.S.//Supermercados Nacional//Casa Cuesta//Ferretería Cuesta//JUMBO//Bebemundo
A99: 101602465 | B99: 1 | C99: 2 | D99: =IF(C99=1,Leyenda!$C$3,IF(C99=2,Leyenda!$C$4,IF(C99=3,Leyenda!$C$5,IF(C99=4,Leyenda!$C$6,IF(C99=5,Leyenda!$C$7,IF(C99=6,Leyenda!$C$8,IF(C99=7,Leyenda!$C$9,IF(C99=8,Leyenda!$C$10," "))))))))&IF(C99=9,Leyenda!$C$11,IF(C99=10,Leyenda!$C$12,IF(C99=11,Leyenda!$C$13,IF(C99=12,Leyenda!D156," ")))) -> GASTOS POR TRABAJOS, SUMINISTROS Y SERVICIOS | E99: E310004339465 | F99: 45356 | G99: =TEXT(F99,"MMMM") -> marzo | H99: 9 | I99: =TEXT(gastos[[#This Row],[Fecha]],"DDDD") -> sábado | J99: =DATE(YEAR(F99),MONTH(F99),H99) -> 45360 | M99: 0 | N99: =14265-1028.49 -> 13236.51 | O99: =SUM(M99:N99) -> 13236.51 | P99: 1028.49 | Q99: 0 | R99: 0 | S99: 0 | T99: =IFERROR(VLOOKUP($A99,Tabla3[#All],2,0),"no esta registrado") -> Bravo, S.A.//Supermercados Bravo
A100: 101602465 | B100: 1 | C100: 2 | D100: =IF(C100=1,Leyenda!$C$3,IF(C100=2,Leyenda!$C$4,IF(C100=3,Leyenda!$C$5,IF(C100=4,Leyenda!$C$6,IF(C100=5,Leyenda!$C$7,IF(C100=6,Leyenda!$C$8,IF(C100=7,Leyenda!$C$9,IF(C100=8,Leyenda!$C$10," "))))))))&IF(C100=9,Leyenda!$C$11,IF(C100=10,Leyenda!$C$12,IF(C100=11,Leyenda!$C$13,IF(C100=12,Leyenda!D157," ")))) -> GASTOS POR TRABAJOS, SUMINISTROS Y SERVICIOS | E100: E310004463612 | F100: 45356 | G100: =TEXT(F100,"MMMM") -> marzo | H100: 15 | I100: =TEXT(gastos[[#This Row],[Fecha]],"DDDD") -> viernes | J100: =DATE(YEAR(F100),MONTH(F100),H100) -> 45366 | M100: 0 | N100: =6913-467.7 -> 6445.3 | O100: =SUM(M100:N100) -> 6445.3 | P100: 467.7 | Q100: 0 | R100: 0 | S100: 0 | T100: =IFERROR(VLOOKUP($A100,Tabla3[#All],2,0),"no esta registrado") -> Bravo, S.A.//Supermercados Bravo
A101: 101602465 | B101: 1 | C101: 2 | D101: =IF(C101=1,Leyenda!$C$3,IF(C101=2,Leyenda!$C$4,IF(C101=3,Leyenda!$C$5,IF(C101=4,Leyenda!$C$6,IF(C101=5,Leyenda!$C$7,IF(C101=6,Leyenda!$C$8,IF(C101=7,Leyenda!$C$9,IF(C101=8,Leyenda!$C$10," "))))))))&IF(C101=9,Leyenda!$C$11,IF(C101=10,Leyenda!$C$12,IF(C101=11,Leyenda!$C$13,IF(C101=12,Leyenda!D158," ")))) -> GASTOS POR TRABAJOS, SUMINISTROS Y SERVICIOS | E101: E310004464811 | F101: 45356 | G101: =TEXT(F101,"MMMM") -> marzo | H101: 21 | I101: =TEXT(gastos[[#This Row],[Fecha]],"DDDD") -> jueves | J101: =DATE(YEAR(F101),MONTH(F101),H101) -> 45372 | M101: 0 | N101: =12790-1037.62 -> 11752.38 | O101: =SUM(M101:N101) -> 11752.38 | P101: 1037.42 | Q101: 0 | R101: 0 | S101: 0 | T101: =IFERROR(VLOOKUP($A101,Tabla3[#All],2,0),"no esta registrado") -> Bravo, S.A.//Supermercados Bravo
A102: 101602465 | B102: 1 | C102: 2 | D102: =IF(C102=1,Leyenda!$C$3,IF(C102=2,Leyenda!$C$4,IF(C102=3,Leyenda!$C$5,IF(C102=4,Leyenda!$C$6,IF(C102=5,Leyenda!$C$7,IF(C102=6,Leyenda!$C$8,IF(C102=7,Leyenda!$C$9,IF(C102=8,Leyenda!$C$10," "))))))))&IF(C102=9,Leyenda!$C$11,IF(C102=10,Leyenda!$C$12,IF(C102=11,Leyenda!$C$13,IF(C102=12,Leyenda!D159," ")))) -> GASTOS POR TRABAJOS, SUMINISTROS Y SERVICIOS | E102: E310004587935 | F102: 45356 | G102: =TEXT(F102,"MMMM") -> marzo | H102: 28 | I102: =TEXT(gastos[[#This Row],[Fecha]],"DDDD") -> jueves | J102: =DATE(YEAR(F102),MONTH(F102),H102) -> 45379 | M102: 0 | N102: =8445-724.34 -> 7720.66 | O102: =SUM(M102:N102) -> 7720.66 | P102: 724.34 | Q102: 0 | R102: 0 | S102: 0 | T102: =IFERROR(VLOOKUP($A102,Tabla3[#All],2,0),"no esta registrado") -> Bravo, S.A.//Supermercados Bravo
A103: 130196796 | B103: 1 | C103: 2 | D103: =IF(C103=1,Leyenda!$C$3,IF(C103=2,Leyenda!$C$4,IF(C103=3,Leyenda!$C$5,IF(C103=4,Leyenda!$C$6,IF(C103=5,Leyenda!$C$7,IF(C103=6,Leyenda!$C$8,IF(C103=7,Leyenda!$C$9,IF(C103=8,Leyenda!$C$10," "))))))))&IF(C103=9,Leyenda!$C$11,IF(C103=10,Leyenda!$C$12,IF(C103=11,Leyenda!$C$13,IF(C103=12,Leyenda!D160," ")))) -> GASTOS POR TRABAJOS, SUMINISTROS Y SERVICIOS | E103: B0100056456 | F103: 45356 | G103: =TEXT(F103,"MMMM") -> marzo | H103: 8 | I103: =TEXT(gastos[[#This Row],[Fecha]],"DDDD") -> viernes | J103: =DATE(YEAR(F103),MONTH(F103),H103) -> 45359 | M103: 2606 | N103: 0 | O103: =SUM(M103:N103) -> 2606 | P103: 0 | Q103: 0 | R103: 0 | S103: 0 | T103: =IFERROR(VLOOKUP($A103,Tabla3[#All],2,0),"no esta registrado") -> ACADEMIA EUROPEA
A104: 130196796 | B104: 1 | C104: 2 | D104: =IF(C104=1,Leyenda!$C$3,IF(C104=2,Leyenda!$C$4,IF(C104=3,Leyenda!$C$5,IF(C104=4,Leyenda!$C$6,IF(C104=5,Leyenda!$C$7,IF(C104=6,Leyenda!$C$8,IF(C104=7,Leyenda!$C$9,IF(C104=8,Leyenda!$C$10," "))))))))&IF(C104=9,Leyenda!$C$11,IF(C104=10,Leyenda!$C$12,IF(C104=11,Leyenda!$C$13,IF(C104=12,Leyenda!D161," ")))) -> GASTOS POR TRABAJOS, SUMINISTROS Y SERVICIOS | E104: B0100056454 | F104: 45356 | G104: =TEXT(F104,"MMMM") -> marzo | H104: 8 | I104: =TEXT(gastos[[#This Row],[Fecha]],"DDDD") -> viernes | J104: =DATE(YEAR(F104),MONTH(F104),H104) -> 45359 | M104: 2876 | N104: 0 | O104: =SUM(M104:N104) -> 2876 | P104: 0 | Q104: 0 | R104: 0 | S104: 0 | T104: =IFERROR(VLOOKUP($A104,Tabla3[#All],2,0),"no esta registrado") -> ACADEMIA EUROPEA
A105: 130196796 | B105: 1 | C105: 2 | D105: =IF(C105=1,Leyenda!$C$3,IF(C105=2,Leyenda!$C$4,IF(C105=3,Leyenda!$C$5,IF(C105=4,Leyenda!$C$6,IF(C105=5,Leyenda!$C$7,IF(C105=6,Leyenda!$C$8,IF(C105=7,Leyenda!$C$9,IF(C105=8,Leyenda!$C$10," "))))))))&IF(C105=9,Leyenda!$C$11,IF(C105=10,Leyenda!$C$12,IF(C105=11,Leyenda!$C$13,IF(C105=12,Leyenda!D162," ")))) -> GASTOS POR TRABAJOS, SUMINISTROS Y SERVICIOS | E105: B0100056455 | F105: 45356 | G105: =TEXT(F105,"MMMM") -> marzo | H105: 8 | I105: =TEXT(gastos[[#This Row],[Fecha]],"DDDD") -> viernes | J105: =DATE(YEAR(F105),MONTH(F105),H105) -> 45359 | M105: 2606 | N105: 0 | O105: =SUM(M105:N105) -> 2606 | P105: 0 | Q105: 0 | R105: 0 | S105: 0 | T105: =IFERROR(VLOOKUP($A105,Tabla3[#All],2,0),"no esta registrado") -> ACADEMIA EUROPEA
A106: 130196796 | B106: 1 | C106: 2 | D106: =IF(C106=1,Leyenda!$C$3,IF(C106=2,Leyenda!$C$4,IF(C106=3,Leyenda!$C$5,IF(C106=4,Leyenda!$C$6,IF(C106=5,Leyenda!$C$7,IF(C106=6,Leyenda!$C$8,IF(C106=7,Leyenda!$C$9,IF(C106=8,Leyenda!$C$10," "))))))))&IF(C106=9,Leyenda!$C$11,IF(C106=10,Leyenda!$C$12,IF(C106=11,Leyenda!$C$13,IF(C106=12,Leyenda!D163," ")))) -> GASTOS POR TRABAJOS, SUMINISTROS Y SERVICIOS | E106: B0100056714 | F106: 45356 | G106: =TEXT(F106,"MMMM") -> marzo | H106: 22 | I106: =TEXT(gastos[[#This Row],[Fecha]],"DDDD") -> viernes | J106: =DATE(YEAR(F106),MONTH(F106),H106) -> 45373 | M106: 2876 | N106: 0 | O106: =SUM(M106:N106) -> 2876 | P106: 0 | Q106: 0 | R106: 0 | S106: 0 | T106: =IFERROR(VLOOKUP($A106,Tabla3[#All],2,0),"no esta registrado") -> ACADEMIA EUROPEA
A107: 131092659 | B107: 1 | C107: 2 | D107: =IF(C107=1,Leyenda!$C$3,IF(C107=2,Leyenda!$C$4,IF(C107=3,Leyenda!$C$5,IF(C107=4,Leyenda!$C$6,IF(C107=5,Leyenda!$C$7,IF(C107=6,Leyenda!$C$8,IF(C107=7,Leyenda!$C$9,IF(C107=8,Leyenda!$C$10," "))))))))&IF(C107=9,Leyenda!$C$11,IF(C107=10,Leyenda!$C$12,IF(C107=11,Leyenda!$C$13,IF(C107=12,Leyenda!D164," ")))) -> GASTOS POR TRABAJOS, SUMINISTROS Y SERVICIOS | E107: B0100457526 | F107: 45356 | G107: =TEXT(F107,"MMMM") -> marzo | H107: 21 | I107: =TEXT(gastos[[#This Row],[Fecha]],"DDDD") -> jueves | J107: =DATE(YEAR(F107),MONTH(F107),H107) -> 45372 | M107: 0 | N107: 500 | O107: =SUM(M107:N107) -> 500 | P107: 0 | Q107: 0 | R107: 0 | S107: 0 | T107: =IFERROR(VLOOKUP($A107,Tabla3[#All],2,0),"no esta registrado") -> no esta registrado
A108: 101001577 | B108: 1 | C108: 2 | D108: =IF(C108=1,Leyenda!$C$3,IF(C108=2,Leyenda!$C$4,IF(C108=3,Leyenda!$C$5,IF(C108=4,Leyenda!$C$6,IF(C108=5,Leyenda!$C$7,IF(C108=6,Leyenda!$C$8,IF(C108=7,Leyenda!$C$9,IF(C108=8,Leyenda!$C$10," "))))))))&IF(C108=9,Leyenda!$C$11,IF(C108=10,Leyenda!$C$12,IF(C108=11,Leyenda!$C$13,IF(C108=12,Leyenda!D165," ")))) -> GASTOS POR TRABAJOS, SUMINISTROS Y SERVICIOS | E108: E310009058506 | F108: 45356 | G108: =TEXT(F108,"MMMM") -> marzo | H108: 7 | I108: =TEXT(gastos[[#This Row],[Fecha]],"DDDD") -> jueves | J108: =DATE(YEAR(F108),MONTH(F108),H108) -> 45358 | M108: 830 | N108: 0 | O108: =SUM(M108:N108) -> 830 | P108: 149.4 | Q108: 0 | R108: 0 | S108: 0 | T108: =IFERROR(VLOOKUP($A108,Tabla3[#All],2,0),"no esta registrado") -> CLARO//CODETEL
A109: 101001577 | B109: 1 | C109: 2 | D109: =IF(C109=1,Leyenda!$C$3,IF(C109=2,Leyenda!$C$4,IF(C109=3,Leyenda!$C$5,IF(C109=4,Leyenda!$C$6,IF(C109=5,Leyenda!$C$7,IF(C109=6,Leyenda!$C$8,IF(C109=7,Leyenda!$C$9,IF(C109=8,Leyenda!$C$10," "))))))))&IF(C109=9,Leyenda!$C$11,IF(C109=10,Leyenda!$C$12,IF(C109=11,Leyenda!$C$13,IF(C109=12,Leyenda!D166," ")))) -> GASTOS POR TRABAJOS, SUMINISTROS Y SERVICIOS | E109: E310009055453 | F109: 45356 | G109: =TEXT(F109,"MMMM") -> marzo | H109: 7 | I109: =TEXT(gastos[[#This Row],[Fecha]],"DDDD") -> jueves | J109: =DATE(YEAR(F109),MONTH(F109),H109) -> 45358 | M109: 2407.69 | N109: 0 | O109: =SUM(M109:N109) -> 2407.69 | P109: 433.39 | Q109: 0 | R109: 0 | S109: 0 | T109: =IFERROR(VLOOKUP($A109,Tabla3[#All],2,0),"no esta registrado") -> CLARO//CODETEL
A110: 101820217 | B110: 1 | C110: 2 | D110: =IF(C110=1,Leyenda!$C$3,IF(C110=2,Leyenda!$C$4,IF(C110=3,Leyenda!$C$5,IF(C110=4,Leyenda!$C$6,IF(C110=5,Leyenda!$C$7,IF(C110=6,Leyenda!$C$8,IF(C110=7,Leyenda!$C$9,IF(C110=8,Leyenda!$C$10," "))))))))&IF(C110=9,Leyenda!$C$11,IF(C110=10,Leyenda!$C$12,IF(C110=11,Leyenda!$C$13,IF(C110=12,Leyenda!D167," ")))) -> GASTOS POR TRABAJOS, SUMINISTROS Y SERVICIOS | E110: B0101862499 | F110: 45356 | G110: =TEXT(F110,"MMMM") -> marzo | H110: 21 | I110: =TEXT(gastos[[#This Row],[Fecha]],"DDDD") -> jueves | J110: =DATE(YEAR(F110),MONTH(F110),H110) -> 45372 | M110: 6549.07 | N110: 0 | O110: =SUM(M110:N110) -> 6549.07 | P110: 0 | Q110: 0 | R110: 0 | S110: 0 | T110: =IFERROR(VLOOKUP($A110,Tabla3[#All],2,0),"no esta registrado") -> EDEESTE
A111: 101010632 | B111: 2 | C111: 7 | D111: =IF(C111=1,Leyenda!$C$3,IF(C111=2,Leyenda!$C$4,IF(C111=3,Leyenda!$C$5,IF(C111=4,Leyenda!$C$6,IF(C111=5,Leyenda!$C$7,IF(C111=6,Leyenda!$C$8,IF(C111=7,Leyenda!$C$9,IF(C111=8,Leyenda!$C$10," "))))))))&IF(C111=9,Leyenda!$C$11,IF(C111=10,Leyenda!$C$12,IF(C111=11,Leyenda!$C$13,IF(C111=12,Leyenda!D168," ")))) -> GASTOS FINANCIEROS | E111: E310119268921 | F111: 45356 | G111: =TEXT(F111,"MMMM") -> marzo | H111: 31 | I111: =TEXT(gastos[[#This Row],[Fecha]],"DDDD") -> domingo | J111: =DATE(YEAR(F111),MONTH(F111),H111) -> 45382 | M111: 11622.36 | N111: 0 | O111: =SUM(M111:N111) -> 11622.36 | P111: 0 | Q111: 0 | R111: 0 | S111: 0 | T111: =IFERROR(VLOOKUP($A111,Tabla3[#All],2,0),"no esta registrado") -> Banco Popular Dominicano, S. A. Banco Multiple
A112: 101043598 | B112: 1 | C112: 7 | D112: =IF(C112=1,Leyenda!$C$3,IF(C112=2,Leyenda!$C$4,IF(C112=3,Leyenda!$C$5,IF(C112=4,Leyenda!$C$6,IF(C112=5,Leyenda!$C$7,IF(C112=6,Leyenda!$C$8,IF(C112=7,Leyenda!$C$9,IF(C112=8,Leyenda!$C$10," "))))))))&IF(C112=9,Leyenda!$C$11,IF(C112=10,Leyenda!$C$12,IF(C112=11,Leyenda!$C$13,IF(C112=12,Leyenda!D169," ")))) -> GASTOS FINANCIEROS | E112: B0105692805 | F112: 45356 | G112: =TEXT(F112,"MMMM") -> marzo | H112: 4 | I112: =TEXT(gastos[[#This Row],[Fecha]],"DDDD") -> lunes | J112: =DATE(YEAR(F112),MONTH(F112),H112) -> 45355 | M112: 137.53 | N112: 0 | O112: =SUM(M112:N112) -> 137.53 | P112: 0 | Q112: 0 | R112: 0 | S112: 0 | T112: =IFERROR(VLOOKUP($A112,Tabla3[#All],2,0),"no esta registrado") -> Banco Dominicano del Progreso, S. A.//Banco Multiple
...

Sheet Detalles2025
A1: Fecha | B1: Año | C1: Mes | D1: Dia de la semana | E1: RNC o Cédula | F1: Tipo Id | G1: Tipo Bienes y Servicios Comprados | H1: Descripción | I1: NCF | J1: NCF ó Documento Modificado | K1: Fecha Comprobante | L1: Dia | M1: Fecha Pago | N1: Columna2 | O1: Monto Facturado en Servicios | P1: Monto Facturado en Bienes | Q1: Monto Facturado | R1: ITBIS Facturado | S1: ITBIS Retenido | T1: ITBIS sujeto a Proporcionalidad (Art. 349) | U1: ITBIS llevado al Costo | V1: ITBIS por Adelantar | W1: ITBIS percibido en compras | X1: Tipo de Retención en ISR | Y1: Monto Retención Renta | Z1: ISR Percibido en compras | AA1: Impuesto Selectivo al Consumo | AB1: Otros Impuesto/Tasas | AC1: Monto Propina Legal | AD1: Total Facturado | AE1: Forma de Pago | AF1: Suplidor | AG1: Producto | AH1: Objeto del gasto
A2: 45677 | B2: =TEXT(Detalles2025[[#This Row],[Fecha]],"AAAA") -> 2025 | C2: =TEXT(Detalles2025[[#This Row],[Fecha]],"MMMM") -> enero | D2: =TEXT(Detalles2025[[#This Row],[Fecha]],"DDDD") -> lunes | E2: 130794987 | F2: 1 | G2: 4 | H2: =IF(G2=1,Leyenda!$C$3,IF(G2=2,Leyenda!$C$4,IF(G2=3,Leyenda!$C$5,IF(G2=4,Leyenda!$C$6,IF(G2=5,Leyenda!$C$7,IF(G2=6,Leyenda!$C$8,IF(G2=7,Leyenda!$C$9,IF(G2=8,Leyenda!$C$10," "))))))))&IF(G2=9,Leyenda!$C$11,IF(G2=10,Leyenda!$C$12,IF(G2=11,Leyenda!$C$13,IF(G2=12,Leyenda!$C$14," ")))) -> GASTOS DE ACTIVOS FIJO | I2: B0101358927 | K2: 202501 | L2: 20 | O2: 0 | P2: 3400 | Q2: =SUM(O2:P2) -> 3400 | R2: 0 | U2: 0 | AA2: 0 | AB2: 0 | AC2: 0 | AD2: =SUM(Detalles2025[[#This Row],[Monto Facturado]:[Monto Propina Legal]]) -> 3400 | AE2: Tarjeta de Credito | AF2: =IFERROR(VLOOKUP(E2,Tabla3[],2,0),"No Registrado") -> Strata, S.R.L. | AG2: Gasolina | AH2: CRV
A3: 45675 | B3: =TEXT(Detalles2025[[#This Row],[Fecha]],"AAAA") -> 2025 | C3: =TEXT(Detalles2025[[#This Row],[Fecha]],"MMMM") -> enero | D3: =TEXT(Detalles2025[[#This Row],[Fecha]],"DDDD") -> sábado | E3: 130794987 | F3: 1 | G3: 4 | H3: =IF(G3=1,Leyenda!$C$3,IF(G3=2,Leyenda!$C$4,IF(G3=3,Leyenda!$C$5,IF(G3=4,Leyenda!$C$6,IF(G3=5,Leyenda!$C$7,IF(G3=6,Leyenda!$C$8,IF(G3=7,Leyenda!$C$9,IF(G3=8,Leyenda!$C$10," "))))))))&IF(G3=9,Leyenda!$C$11,IF(G3=10,Leyenda!$C$12,IF(G3=11,Leyenda!$C$13,IF(G3=12,Leyenda!$C$14," ")))) -> GASTOS DE ACTIVOS FIJO | I3: B0101358304 | K3: =IF($G3=0," ",$K$2) -> 202501 | L3: 18 | O3: 0 | P3: 4702 | Q3: =SUM(O3:P3) -> 4702 | R3: 0 | U3: 0 | AA3: 0 | AB3: 0 | AC3: 0 | AD3: =SUM(Detalles2025[[#This Row],[Monto Facturado]:[Monto Propina Legal]]) -> 4702 | AE3: Tarjeta de Credito | AF3: =IFERROR(VLOOKUP(E3,Tabla3[],2,0),"No Registrado") -> Strata, S.R.L. | AG3: Diesel | AH3: HILUX
A4: 45688 | B4: =TEXT(Detalles2025[[#This Row],[Fecha]],"AAAA") -> 2025 | C4: =TEXT(Detalles2025[[#This Row],[Fecha]],"MMMM") -> enero | D4: =TEXT(Detalles2025[[#This Row],[Fecha]],"DDDD") -> viernes | E4: 131208371 | F4: 1 | G4: 2 | H4: =IF(G4=1,Leyenda!$C$3,IF(G4=2,Leyenda!$C$4,IF(G4=3,Leyenda!$C$5,IF(G4=4,Leyenda!$C$6,IF(G4=5,Leyenda!$C$7,IF(G4=6,Leyenda!$C$8,IF(G4=7,Leyenda!$C$9,IF(G4=8,Leyenda!$C$10," "))))))))&IF(G4=9,Leyenda!$C$11,IF(G4=10,Leyenda!$C$12,IF(G4=11,Leyenda!$C$13,IF(G4=12,Leyenda!$C$14," ")))) -> GASTOS POR TRABAJOS, SUMINISTROS Y SERVICIOS | I4: B0100026718 | K4: =IF($G4=0," ",$K$2) -> 202501 | L4: 31 | O4: 0 | P4: 800 | Q4: =SUM(O4:P4) -> 800 | R4: 0 | U4: 0 | V4: 0 | W4: 0 | X4: 0 | Y4: 0 | Z4: 0 | AA4: 0 | AB4: 0 | AC4: 0 | AD4: =SUM(Detalles2025[[#This Row],[Monto Facturado]:[Monto Propina Legal]]) -> 800 | AE4: Tarjeta de Credito | AF4: =IFERROR(VLOOKUP(E4,Tabla3[],2,0),"No Registrado") -> U.S. POLO ASSN | AG4: tienda | AH4: casa
A5: 45664 | B5: =TEXT(Detalles2025[[#This Row],[Fecha]],"AAAA") -> 2025 | C5: =TEXT(Detalles2025[[#This Row],[Fecha]],"MMMM") -> enero | D5: =TEXT(Detalles2025[[#This Row],[Fecha]],"DDDD") -> martes | E5: 131341136 | F5: 1 | G5: 2 | H5: =IF(G5=1,Leyenda!$C$3,IF(G5=2,Leyenda!$C$4,IF(G5=3,Leyenda!$C$5,IF(G5=4,Leyenda!$C$6,IF(G5=5,Leyenda!$C$7,IF(G5=6,Leyenda!$C$8,IF(G5=7,Leyenda!$C$9,IF(G5=8,Leyenda!$C$10," "))))))))&IF(G5=9,Leyenda!$C$11,IF(G5=10,Leyenda!$C$12,IF(G5=11,Leyenda!$C$13,IF(G5=12,Leyenda!$C$14," ")))) -> GASTOS POR TRABAJOS, SUMINISTROS Y SERVICIOS | I5: B0100703682 | K5: =IF($G5=0," ",$K$2) -> 202501 | L5: 7 | O5: 0 | P5: 634.75 | Q5: =SUM(O5:P5) -> 634.75 | R5: 114.26 | U5: 0 | V5: 0 | W5: 0 | X5: 0 | Y5: 0 | Z5: 0 | AA5: 0 | AB5: 0 | AC5: 0 | AD5: =SUM(Detalles2025[[#This Row],[Monto Facturado]:[Monto Propina Legal]]) -> 749.01 | AE5: Tarjeta de Credito | AF5: =IFERROR(VLOOKUP(E5,Tabla3[],2,0),"No Registrado") -> Little Ceasars Pizza Alma Rosa | AG5: Cena Familiar | AH5: Restorant
A6: =DATE(LEFT(K6,4),RIGHT(K6,2),L6) -> 45683 | B6: =TEXT(Detalles2025[[#This Row],[Fecha]],"AAAA") -> 2025 | C6: =TEXT(Detalles2025[[#This Row],[Fecha]],"MMMM") -> enero | D6: =TEXT(Detalles2025[[#This Row],[Fecha]],"DDDD") -> domingo | E6: 000000001 | F6: 1 | G6: 12 | H6: =IF(G6=1,Leyenda!$C$3,IF(G6=2,Leyenda!$C$4,IF(G6=3,Leyenda!$C$5,IF(G6=4,Leyenda!$C$6,IF(G6=5,Leyenda!$C$7,IF(G6=6,Leyenda!$C$8,IF(G6=7,Leyenda!$C$9,IF(G6=8,Leyenda!$C$10," "))))))))&IF(G6=9,Leyenda!$C$11,IF(G6=10,Leyenda!$C$12,IF(G6=11,Leyenda!$C$13,IF(G6=12,Leyenda!$C$14," ")))) -> GASTOS MENORES | I6: 0 | K6: =IF($G6=0," ",$K$3) -> 202501 | L6: 26 | O6: 0 | P6: 6000 | Q6: =SUM(O6:P6) -> 6000 | R6: 0 | S6: 0 | T6: 0 | U6: 0 | V6: 0 | W6: 0 | X6: 0 | Y6: 0 | Z6: 0 | AA6: 0 | AB6: 0 | AC6: 0 | AD6: =SUM(Detalles2025[[#This Row],[Monto Facturado]:[Monto Propina Legal]]) -> 6000 | AE6: Transferencia Bancaria | AF6: =IFERROR(VLOOKUP(E6,Tabla3[],2,0),"No Registrado") -> No Registrado | AG6: Mesada | AH6: Yajaira
A7: =DATE(LEFT(K7,4),RIGHT(K7,2),L7) -> 45683 | B7: =TEXT(Detalles2025[[#This Row],[Fecha]],"AAAA") -> 2025 | C7: =TEXT(Detalles2025[[#This Row],[Fecha]],"MMMM") -> enero | D7: =TEXT(Detalles2025[[#This Row],[Fecha]],"DDDD") -> domingo | E7: 000000002 | F7: 1 | G7: 12 | H7: =IF(G7=1,Leyenda!$C$3,IF(G7=2,Leyenda!$C$4,IF(G7=3,Leyenda!$C$5,IF(G7=4,Leyenda!$C$6,IF(G7=5,Leyenda!$C$7,IF(G7=6,Leyenda!$C$8,IF(G7=7,Leyenda!$C$9,IF(G7=8,Leyenda!$C$10," "))))))))&IF(G7=9,Leyenda!$C$11,IF(G7=10,Leyenda!$C$12,IF(G7=11,Leyenda!$C$13,IF(G7=12,Leyenda!$C$14," ")))) -> GASTOS MENORES | I7: 0 | K7: =IF($G7=0," ",$K$3) -> 202501 | L7: 26 | O7: 0 | P7: 3000 | Q7: =SUM(O7:P7) -> 3000 | R7: 0 | S7: 0 | T7: 0 | U7: 0 | V7: 0 | W7: 0 | X7: 0 | Y7: 0 | Z7: 0 | AA7: 0 | AB7: 0 | AC7: 0 | AD7: =SUM(Detalles2025[[#This Row],[Monto Facturado]:[Monto Propina Legal]]) -> 3000 | AE7: Transferencia Bancaria | AF7: =IFERROR(VLOOKUP(E7,Tabla3[],2,0),"No Registrado") -> No Registrado | AG7: Mesada | AH7: Yahelis
A8: =DATE(LEFT(K8,4),RIGHT(K8,2),L8) -> 45683 | B8: =TEXT(Detalles2025[[#This Row],[Fecha]],"AAAA") -> 2025 | C8: =TEXT(Detalles2025[[#This Row],[Fecha]],"MMMM") -> enero | D8: =TEXT(Detalles2025[[#This Row],[Fecha]],"DDDD") -> domingo | E8: 000000003 | F8: 1 | G8: 12 | H8: =IF(G8=1,Leyenda!$C$3,IF(G8=2,Leyenda!$C$4,IF(G8=3,Leyenda!$C$5,IF(G8=4,Leyenda!$C$6,IF(G8=5,Leyenda!$C$7,IF(G8=6,Leyenda!$C$8,IF(G8=7,Leyenda!$C$9,IF(G8=8,Leyenda!$C$10," "))))))))&IF(G8=9,Leyenda!$C$11,IF(G8=10,Leyenda!$C$12,IF(G8=11,Leyenda!$C$13,IF(G8=12,Leyenda!$C$14," ")))) -> GASTOS MENORES | I8: 0 | K8: =IF($G8=0," ",$K$3) -> 202501 | L8: 26 | O8: 0 | P8: 1500 | Q8: =SUM(O8:P8) -> 1500 | R8: 0 | S8: 0 | T8: 0 | U8: 0 | V8: 0 | W8: 0 | X8: 0 | Y8: 0 | Z8: 0 | AA8: 0 | AB8: 0 | AC8: 0 | AD8: =SUM(Detalles2025[[#This Row],[Monto Facturado]:[Monto Propina Legal]]) -> 1500 | AE8: Efectivo | AF8: =IFERROR(VLOOKUP(E8,Tabla3[],2,0),"No Registrado") -> No Registrado | AG8: Mesada | AH8: Javier
A9: =DATE(LEFT(K9,4),RIGHT(K9,2),L9) -> 45683 | B9: =TEXT(Detalles2025[[#This Row],[Fecha]],"AAAA") -> 2025 | C9: =TEXT(Detalles2025[[#This Row],[Fecha]],"MMMM") -> enero | D9: =TEXT(Detalles2025[[#This Row],[Fecha]],"DDDD") -> domingo | E9: 000000004 | F9: 1 | G9: 12 | H9: =IF(G9=1,Leyenda!$C$3,IF(G9=2,Leyenda!$C$4,IF(G9=3,Leyenda!$C$5,IF(G9=4,Leyenda!$C$6,IF(G9=5,Leyenda!$C$7,IF(G9=6,Leyenda!$C$8,IF(G9=7,Leyenda!$C$9,IF(G9=8,Leyenda!$C$10," "))))))))&IF(G9=9,Leyenda!$C$11,IF(G9=10,Leyenda!$C$12,IF(G9=11,Leyenda!$C$13,IF(G9=12,Leyenda!$C$14," ")))) -> GASTOS MENORES | I9: 0 | K9: =IF($G9=0," ",$K$3) -> 202501 | L9: 26 | O9: 0 | P9: 500 | Q9: =SUM(O9:P9) -> 500 | R9: 0 | S9: 0 | T9: 0 | U9: 0 | V9: 0 | W9: 0 | X9: 0 | Y9: 0 | Z9: 0 | AA9: 0 | AB9: 0 | AC9: 0 | AD9: =SUM(Detalles2025[[#This Row],[Monto Facturado]:[Monto Propina Legal]]) -> 500 | AE9: Efectivo | AF9: =IFERROR(VLOOKUP(E9,Tabla3[],2,0),"No Registrado") -> No Registrado | AG9: Mesada | AH9: Lorena
A10: =DATE(LEFT(K10,4),RIGHT(K10,2),L10) -> 45683 | B10: =TEXT(Detalles2025[[#This Row],[Fecha]],"AAAA") -> 2025 | C10: =TEXT(Detalles2025[[#This Row],[Fecha]],"MMMM") -> enero | D10: =TEXT(Detalles2025[[#This Row],[Fecha]],"DDDD") -> domingo | E10: 000000005 | F10: 1 | G10: 12 | H10: =IF(G10=1,Leyenda!$C$3,IF(G10=2,Leyenda!$C$4,IF(G10=3,Leyenda!$C$5,IF(G10=4,Leyenda!$C$6,IF(G10=5,Leyenda!$C$7,IF(G10=6,Leyenda!$C$8,IF(G10=7,Leyenda!$C$9,IF(G10=8,Leyenda!$C$10," "))))))))&IF(G10=9,Leyenda!$C$11,IF(G10=10,Leyenda!$C$12,IF(G10=11,Leyenda!$C$13,IF(G10=12,Leyenda!$C$14," ")))) -> GASTOS MENORES | I10: 0 | K10: =IF($G10=0," ",$K$3) -> 202501 | L10: 26 | O10: 0 | P10: 500 | Q10: =SUM(O10:P10) -> 500 | R10: 0 | S10: 0 | T10: 0 | U10: 0 | V10: 0 | W10: 0 | X10: 0 | Y10: 0 | Z10: 0 | AA10: 0 | AB10: 0 | AC10: 0 | AD10: =SUM(Detalles2025[[#This Row],[Monto Facturado]:[Monto Propina Legal]]) -> 500 | AE10: Efectivo | AF10: =IFERROR(VLOOKUP(E10,Tabla3[],2,0),"No Registrado") -> No Registrado | AG10: Mesada | AH10: Andres
A11: =DATE(LEFT(K11,4),RIGHT(K11,2),L11) -> 45673 | B11: =TEXT(Detalles2025[[#This Row],[Fecha]],"AAAA") -> 2025 | C11: =TEXT(Detalles2025[[#This Row],[Fecha]],"MMMM") -> enero | D11: =TEXT(Detalles2025[[#This Row],[Fecha]],"DDDD") -> jueves | E11: 101043598 | F11: 1 | G11: 7 | H11: =IF(G11=1,Leyenda!$C$3,IF(G11=2,Leyenda!$C$4,IF(G11=3,Leyenda!$C$5,IF(G11=4,Leyenda!$C$6,IF(G11=5,Leyenda!$C$7,IF(G11=6,Leyenda!$C$8,IF(G11=7,Leyenda!$C$9,IF(G11=8,Leyenda!$C$10," "))))))))&IF(G11=9,Leyenda!$C$11,IF(G11=10,Leyenda!$C$12,IF(G11=11,Leyenda!$C$13,IF(G11=12,Leyenda!$C$14," ")))) -> GASTOS FINANCIEROS | I11: E310000175557 | K11: =IF($G11=0," ",$K$3) -> 202501 | L11: 16 | O11: 0 | P11: 48000 | Q11: =SUM(O11:P11) -> 48000 | R11: 0 | U11: 0 | AA11: 0 | AB11: 0 | AC11: 0 | AD11: =SUM(Detalles2025[[#This Row],[Monto Facturado]:[Monto Propina Legal]]) -> 48000 | AE11: Transferencia Bancaria | AF11: =IFERROR(VLOOKUP(E11,Tabla3[],2,0),"No Registrado") -> Banco Dominicano del Progreso, S. A.//Banco Multiple | AG11: Hipoteca | AH11: Prestamo
A12: =DATE(LEFT(K12,4),RIGHT(K12,2),L12) -> 45681 | B12: =TEXT(Detalles2025[[#This Row],[Fecha]],"AAAA") -> 2025 | C12: =TEXT(Detalles2025[[#This Row],[Fecha]],"MMMM") -> enero | D12: =TEXT(Detalles2025[[#This Row],[Fecha]],"DDDD") -> viernes | E12: 4453939 | F12: 1 | G12: 7 | H12: =IF(G12=1,Leyenda!$C$3,IF(G12=2,Leyenda!$C$4,IF(G12=3,Leyenda!$C$5,IF(G12=4,Leyenda!$C$6,IF(G12=5,Leyenda!$C$7,IF(G12=6,Leyenda!$C$8,IF(G12=7,Leyenda!$C$9,IF(G12=8,Leyenda!$C$10," "))))))))&IF(G12=9,Leyenda!$C$11,IF(G12=10,Leyenda!$C$12,IF(G12=11,Leyenda!$C$13,IF(G12=12,Leyenda!$C$14," ")))) -> GASTOS FINANCIEROS | I12: 0 | K12: =IF($G12=0," ",$K$3) -> 202501 | L12: 24 | O12: 0 | P12: 23443.75 | Q12: =SUM(O12:P12) -> 23443.75 | R12: 0 | U12: 0 | AA12: 0 | AB12: 0 | AC12: 0 | AD12: =SUM(Detalles2025[[#This Row],[Monto Facturado]:[Monto Propina Legal]]) -> 23443.75 | AE12: Transferencia Bancaria | AF12: =IFERROR(VLOOKUP(E12,Tabla3[],2,0),"No Registrado") -> No Registrado | AG12: BHD | AH12: Prestamo
A13: =DATE(LEFT(K13,4),RIGHT(K13,2),L13) -> 45658 | B13: =TEXT(Detalles2025[[#This Row],[Fecha]],"AAAA") -> 2025 | C13: =TEXT(Detalles2025[[#This Row],[Fecha]],"MMMM") -> enero | D13: =TEXT(Detalles2025[[#This Row],[Fecha]],"DDDD") -> miércoles | E13: 835651126 | F13: 1 | G13: 7 | H13: =IF(G13=1,Leyenda!$C$3,IF(G13=2,Leyenda!$C$4,IF(G13=3,Leyenda!$C$5,IF(G13=4,Leyenda!$C$6,IF(G13=5,Leyenda!$C$7,IF(G13=6,Leyenda!$C$8,IF(G13=7,Leyenda!$C$9,IF(G13=8,Leyenda!$C$10," "))))))))&IF(G13=9,Leyenda!$C$11,IF(G13=10,Leyenda!$C$12,IF(G13=11,Leyenda!$C$13,IF(G13=12,Leyenda!$C$14," ")))) -> GASTOS FINANCIEROS | I13: 0 | K13: =IF($G13=0," ",$K$3) -> 202501 | L13: 1 | O13: 0 | P13: 25404.27 | Q13: =SUM(O13:P13) -> 25404.27 | R13: 0 | U13: 0 | AA13: 0 | AB13: 0 | AC13: 0 | AD13: =SUM(Detalles2025[[#This Row],[Monto Facturado]:[Monto Propina Legal]]) -> 25404.27 | AE13: Transferencia Bancaria | AF13: =IFERROR(VLOOKUP(E13,Tabla3[],2,0),"No Registrado") -> No Registrado | AG13: Popular | AH13: Prestamo
A14: =DATE(LEFT(K14,4),RIGHT(K14,2),L14) -> 45661 | B14: =TEXT(Detalles2025[[#This Row],[Fecha]],"AAAA") -> 2025 | C14: =TEXT(Detalles2025[[#This Row],[Fecha]],"MMMM") -> enero | D14: =TEXT(Detalles2025[[#This Row],[Fecha]],"DDDD") -> sábado | E14: 4458538 | F14: 1 | G14: 7 | H14: =IF(G14=1,Leyenda!$C$3,IF(G14=2,Leyenda!$C$4,IF(G14=3,Leyenda!$C$5,IF(G14=4,Leyenda!$C$6,IF(G14=5,Leyenda!$C$7,IF(G14=6,Leyenda!$C$8,IF(G14=7,Leyenda!$C$9,IF(G14=8,Leyenda!$C$10," "))))))))&IF(G14=9,Leyenda!$C$11,IF(G14=10,Leyenda!$C$12,IF(G14=11,Leyenda!$C$13,IF(G14=12,Leyenda!$C$14," ")))) -> GASTOS FINANCIEROS | I14: 0 | K14: =IF($G14=0," ",$K$3) -> 202501 | L14: 4 | O14: 0 | P14: 15208.33 | Q14: =SUM(O14:P14) -> 15208.33 | R14: 0 | U14: 0 | AA14: 0 | AB14: 0 | AC14: 0 | AD14: =SUM(Detalles2025[[#This Row],[Monto Facturado]:[Monto Propina Legal]]) -> 15208.33 | AE14: Transferencia Bancaria | AF14: =IFERROR(VLOOKUP(E14,Tabla3[],2,0),"No Registrado") -> No Registrado | AG14: BHD | AH14: Prestamo
A15: 45665 | B15: =TEXT(Detalles2025[[#This Row],[Fecha]],"AAAA") -> 2025 | C15: =TEXT(Detalles2025[[#This Row],[Fecha]],"MMMM") -> enero | D15: =TEXT(Detalles2025[[#This Row],[Fecha]],"DDDD") -> miércoles | E15: 131436781 | F15: 2 | G15: 2 | H15: =IF(G15=1,Leyenda!$C$3,IF(G15=2,Leyenda!$C$4,IF(G15=3,Leyenda!$C$5,IF(G15=4,Leyenda!$C$6,IF(G15=5,Leyenda!$C$7,IF(G15=6,Leyenda!$C$8,IF(G15=7,Leyenda!$C$9,IF(G15=8,Leyenda!$C$10," "))))))))&IF(G15=9,Leyenda!$C$11,IF(G15=10,Leyenda!$C$12,IF(G15=11,Leyenda!$C$13,IF(G15=12,Leyenda!$C$14," ")))) -> GASTOS POR TRABAJOS, SUMINISTROS Y SERVICIOS | I15: B0100019983 | K15: 202501 | L15: 8 | O15: 0 | P15: 885.59 | Q15: =SUM(O15:P15) -> 885.59 | R15: 159.41 | U15: 0 | V15: 0 | W15: 0 | X15: 0 | Y15: 0 | Z15: 0 | AA15: 0 | AB15: 0 | AC15: 0 | AD15: =SUM(Detalles2025[[#This Row],[Monto Facturado]:[Monto Propina Legal]]) -> 1045 | AE15: Tarjeta de Credito | AF15: =IFERROR(VLOOKUP(E15,Tabla3[],2,0),"No Registrado") -> Floremch Importaciones SRL | AG15: tienda | AH15: casa
A16: 45663 | B16: =TEXT(Detalles2025[[#This Row],[Fecha]],"AAAA") -> 2025 | C16: =TEXT(Detalles2025[[#This Row],[Fecha]],"MMMM") -> enero | D16: =TEXT(Detalles2025[[#This Row],[Fecha]],"DDDD") -> lunes | E16: 130064423 | F16: 1 | G16: 2 | H16: =IF(G16=1,Leyenda!$C$3,IF(G16=2,Leyenda!$C$4,IF(G16=3,Leyenda!$C$5,IF(G16=4,Leyenda!$C$6,IF(G16=5,Leyenda!$C$7,IF(G16=6,Leyenda!$C$8,IF(G16=7,Leyenda!$C$9,IF(G16=8,Leyenda!$C$10," "))))))))&IF(G16=9,Leyenda!$C$11,IF(G16=10,Leyenda!$C$12,IF(G16=11,Leyenda!$C$13,IF(G16=12,Leyenda!$C$14," ")))) -> GASTOS POR TRABAJOS, SUMINISTROS Y SERVICIOS | I16: B0102042097 | K16: =IF($G16=0," ",$K$2) -> 202501 | L16: 6 | O16: 0 | P16: 1216 | Q16: =SUM(O16:P16) -> 1216 | R16: 0 | U16: 0 | V16: 0 | W16: 0 | X16: 0 | Y16: 0 | Z16: 0 | AA16: 0 | AB16: 0 | AC16: 0 | AD16: =SUM(Detalles2025[[#This Row],[Monto Facturado]:[Monto Propina Legal]]) -> 1216 | AE16: Tarjeta de Credito | AF16: =IFERROR(VLOOKUP(E16,Tabla3[],2,0),"No Registrado") -> Farmacía Medicar GBC, A. H. | AG16: salud | AH16: Salud
A17: 45663 | B17: =TEXT(Detalles2025[[#This Row],[Fecha]],"AAAA") -> 2025 | C17: =TEXT(Detalles2025[[#This Row],[Fecha]],"MMMM") -> enero | D17: =TEXT(Detalles2025[[#This Row],[Fecha]],"DDDD") -> lunes | E17: 131649122 | F17: 1 | G17: 2 | H17: =IF(G17=1,Leyenda!$C$3,IF(G17=2,Leyenda!$C$4,IF(G17=3,Leyenda!$C$5,IF(G17=4,Leyenda!$C$6,IF(G17=5,Leyenda!$C$7,IF(G17=6,Leyenda!$C$8,IF(G17=7,Leyenda!$C$9,IF(G17=8,Leyenda!$C$10," "))))))))&IF(G17=9,Leyenda!$C$11,IF(G17=10,Leyenda!$C$12,IF(G17=11,Leyenda!$C$13,IF(G17=12,Leyenda!$C$14," ")))) -> GASTOS POR TRABAJOS, SUMINISTROS Y SERVICIOS | I17: B0100144365 | K17: =IF($G17=0," ",$K$2) -> 202501 | L17: 6 | O17: 0 | P17: =699.98-106.78 -> 593.2 | Q17: =SUM(O17:P17) -> 593.2 | R17: 106.78 | U17: 0 | V17: 0 | W17: 0 | X17: 0 | Y17: 0 | Z17: 0 | AA17: 0 | AB17: 0 | AC17: 0 | AD17: =SUM(Detalles2025[[#This Row],[Monto Facturado]:[Monto Propina Legal]]) -> 699.98 | AE17: Tarjeta de Credito | AF17: =IFERROR(VLOOKUP(E17,Tabla3[],2,0),"No Registrado") -> Abastek Marketing SRL | AG17: tienda | AH17: casa
A18: 45679 | B18: =TEXT(Detalles2025[[#This Row],[Fecha]],"AAAA") -> 2025 | C18: =TEXT(Detalles2025[[#This Row],[Fecha]],"MMMM") -> enero | D18: =TEXT(Detalles2025[[#This Row],[Fecha]],"DDDD") -> miércoles | E18: 131039499 | F18: 1 | G18: 2 | H18: =IF(G18=1,Leyenda!$C$3,IF(G18=2,Leyenda!$C$4,IF(G18=3,Leyenda!$C$5,IF(G18=4,Leyenda!$C$6,IF(G18=5,Leyenda!$C$7,IF(G18=6,Leyenda!$C$8,IF(G18=7,Leyenda!$C$9,IF(G18=8,Leyenda!$C$10," "))))))))&IF(G18=9,Leyenda!$C$11,IF(G18=10,Leyenda!$C$12,IF(G18=11,Leyenda!$C$13,IF(G18=12,Leyenda!$C$14," ")))) -> GASTOS POR TRABAJOS, SUMINISTROS Y SERVICIOS | I18: B0100096375 | K18: =IF($G18=0," ",$K$2) -> 202501 | L18: 22 | O18: 0 | P18: 751.52 | Q18: =SUM(O18:P18) -> 751.52 | R18: 0 | U18: 0 | V18: 0 | W18: 0 | X18: 0 | Y18: 0 | Z18: 0 | AA18: 0 | AB18: 0 | AC18: 0 | AD18: =SUM(Detalles2025[[#This Row],[Monto Facturado]:[Monto Propina Legal]]) -> 751.52 | AE18: Tarjeta de Credito | AF18: =IFERROR(VLOOKUP(E18,Tabla3[],2,0),"No Registrado") -> Farmacia VIP Mendo SRL | AG18: salud | AH18: Salud
A19: 45687 | B19: =TEXT(Detalles2025[[#This Row],[Fecha]],"AAAA") -> 2025 | C19: =TEXT(Detalles2025[[#This Row],[Fecha]],"MMMM") -> enero | D19: =TEXT(Detalles2025[[#This Row],[Fecha]],"DDDD") -> jueves | E19: 131153666 | F19: 1 | G19: 2 | H19: =IF(G19=1,Leyenda!$C$3,IF(G19=2,Leyenda!$C$4,IF(G19=3,Leyenda!$C$5,IF(G19=4,Leyenda!$C$6,IF(G19=5,Leyenda!$C$7,IF(G19=6,Leyenda!$C$8,IF(G19=7,Leyenda!$C$9,IF(G19=8,Leyenda!$C$10," "))))))))&IF(G19=9,Leyenda!$C$11,IF(G19=10,Leyenda!$C$12,IF(G19=11,Leyenda!$C$13,IF(G19=12,Leyenda!$C$14," ")))) -> GASTOS POR TRABAJOS, SUMINISTROS Y SERVICIOS | I19: B0100006053 | K19: =IF($G19=0," ",$K$2) -> 202501 | L19: 30 | O19: 0 | P19: 933.47 | Q19: =SUM(O19:P19) -> 933.47 | R19: 136.52 | U19: 0 | V19: 0 | W19: 0 | X19: 0 | Y19: 0 | Z19: 0 | AA19: 0 | AB19: 0 | AC19: 0 | AD19: =SUM(Detalles2025[[#This Row],[Monto Facturado]:[Monto Propina Legal]]) -> 1069.99 | AE19: Tarjeta de Credito | AF19: =IFERROR(VLOOKUP(E19,Tabla3[],2,0),"No Registrado") -> Grupo VARNET | AG19: tienda | AH19: casa
A20: 45666 | B20: =TEXT(Detalles2025[[#This Row],[Fecha]],"AAAA") -> 2025 | C20: =TEXT(Detalles2025[[#This Row],[Fecha]],"MMMM") -> enero | D20: =TEXT(Detalles2025[[#This Row],[Fecha]],"DDDD") -> jueves | E20: 101651555 | F20: 1 | G20: 4 | H20: =IF(G20=1,Leyenda!$C$3,IF(G20=2,Leyenda!$C$4,IF(G20=3,Leyenda!$C$5,IF(G20=4,Leyenda!$C$6,IF(G20=5,Leyenda!$C$7,IF(G20=6,Leyenda!$C$8,IF(G20=7,Leyenda!$C$9,IF(G20=8,Leyenda!$C$10," "))))))))&IF(G20=9,Leyenda!$C$11,IF(G20=10,Leyenda!$C$12,IF(G20=11,Leyenda!$C$13,IF(G20=12,Leyenda!$C$14," ")))) -> GASTOS DE ACTIVOS FIJO | I20: B0100048701 | K20: =IF($G20=0," ",$K$2) -> 202501 | L20: 9 | O20: 0 | P20: =3870-590.34 -> 3279.66 | Q20: =SUM(O20:P20) -> 3279.66 | R20: 590.34 | U20: 0 | V20: 0 | W20: 0 | X20: 0 | Y20: 0 | Z20: 0 | AA20: 0 | AB20: 0 | AC20: 0 | AD20: =SUM(Detalles2025[[#This Row],[Monto Facturado]:[Monto Propina Legal]]) -> 3870 | AE20: Tarjeta de Credito | AF20: =IFERROR(VLOOKUP(E20,Tabla3[],2,0),"No Registrado") -> INDY PLAZA | AG20: Mantenimiento de CRV | AH20: CRV
A21: 45684 | B21: =TEXT(Detalles2025[[#This Row],[Fecha]],"AAAA") -> 2025 | C21: =TEXT(Detalles2025[[#This Row],[Fecha]],"MMMM") -> enero | D21: =TEXT(Detalles2025[[#This Row],[Fecha]],"DDDD") -> lunes | E21: 101602465 | F21: 1 | G21: 2 | H21: =IF(G21=1,Leyenda!$C$3,IF(G21=2,Leyenda!$C$4,IF(G21=3,Leyenda!$C$5,IF(G21=4,Leyenda!$C$6,IF(G21=5,Leyenda!$C$7,IF(G21=6,Leyenda!$C$8,IF(G21=7,Leyenda!$C$9,IF(G21=8,Leyenda!$C$10," "))))))))&IF(G21=9,Leyenda!$C$11,IF(G21=10,Leyenda!$C$12,IF(G21=11,Leyenda!$C$13,IF(G21=12,Leyenda!$C$14," ")))) -> GASTOS POR TRABAJOS, SUMINISTROS Y SERVICIOS | I21: E310006681341 | K21: =IF($G21=0," ",$K$2) -> 202501 | L21: 27 | O21: 0 | P21: =1950-195.94 -> 1754.06 | Q21: =SUM(O21:P21) -> 1754.06 | R21: 195.94 | U21: 0 | V21: 0 | W21: 0 | X21: 0 | Y21: 0 | Z21: 0 | AA21: 0 | AB21: 0 | AC21: 0 | AD21: =SUM(Detalles2025[[#This Row],[Monto Facturado]:[Monto Propina Legal]]) -> 1950 | AE21: Tarjeta de Credito | AF21: =IFERROR(VLOOKUP(E21,Tabla3[],2,0),"No Registrado") -> Bravo, S.A.//Supermercados Bravo | AG21: Compra supermercado | AH21: casa
A22: 45681 | B22: =TEXT(Detalles2025[[#This Row],[Fecha]],"AAAA") -> 2025 | C22: =TEXT(Detalles2025[[#This Row],[Fecha]],"MMMM") -> enero | D22: =TEXT(Detalles2025[[#This Row],[Fecha]],"DDDD") -> viernes | E22: 130389586 | F22: 1 | G22: 2 | H22: =IF(G22=1,Leyenda!$C$3,IF(G22=2,Leyenda!$C$4,IF(G22=3,Leyenda!$C$5,IF(G22=4,Leyenda!$C$6,IF(G22=5,Leyenda!$C$7,IF(G22=6,Leyenda!$C$8,IF(G22=7,Leyenda!$C$9,IF(G22=8,Leyenda!$C$10," "))))))))&IF(G22=9,Leyenda!$C$11,IF(G22=10,Leyenda!$C$12,IF(G22=11,Leyenda!$C$13,IF(G22=12,Leyenda!$C$14," ")))) -> GASTOS POR TRABAJOS, SUMINISTROS Y SERVICIOS | I22: E310000121980 | K22: =IF($G22=0," ",$K$2) -> 202501 | L22: 24 | O22: 0 | P22: 2109.41 | Q22: =SUM(O22:P22) -> 2109.41 | R22: 379.69 | U22: 0 | V22: 0 | W22: 0 | X22: 0 | Y22: 0 | Z22: 0 | AA22: 0 | AB22: 0 | AC22: 210.94 | AD22: =SUM(Detalles2025[[#This Row],[Monto Facturado]:[Monto Propina Legal]]) -> 2700.04 | AE22: Tarjeta de Credito | AF22: =IFERROR(VLOOKUP(E22,Tabla3[],2,0),"No Registrado") -> Jade Teriyaki, S.A. | AG22: Cena Familiar | AH22: Restorant
A23: 45684 | B23: =TEXT(Detalles2025[[#This Row],[Fecha]],"AAAA") -> 2025 | C23: =TEXT(Detalles2025[[#This Row],[Fecha]],"MMMM") -> enero | D23: =TEXT(Detalles2025[[#This Row],[Fecha]],"DDDD") -> lunes | E23: 101801875 | F23: 1 | G23: 2 | H23: =IF(G23=1,Leyenda!$C$3,IF(G23=2,Leyenda!$C$4,IF(G23=3,Leyenda!$C$5,IF(G23=4,Leyenda!$C$6,IF(G23=5,Leyenda!$C$7,IF(G23=6,Leyenda!$C$8,IF(G23=7,Leyenda!$C$9,IF(G23=8,Leyenda!$C$10," "))))))))&IF(G23=9,Leyenda!$C$11,IF(G23=10,Leyenda!$C$12,IF(G23=11,Leyenda!$C$13,IF(G23=12,Leyenda!$C$14," ")))) -> GASTOS POR TRABAJOS, SUMINISTROS Y SERVICIOS | I23: E310001078218 | K23: =IF($G23=0," ",$K$2) -> 202501 | L23: 27 | O23: 0 | P23: =6415.26+1470 -> 7885.26 | Q23: =SUM(O23:P23) -> 7885.26 | R23: 1154.74 | U23: 0 | V23: 0 | W23: 0 | X23: 0 | Y23: 0 | Z23: 0 | AA23: 0 | AB23: 0 | AC23: 0 | AD23: =SUM(Detalles2025[[#This Row],[Monto Facturado]:[Monto Propina Legal]]) -> 9040 | AE23: Tarjeta de Credito | AF23: =IFERROR(VLOOKUP(E23,Tabla3[],2,0),"No Registrado") -> Pricesmart Dominicana S. A. | AG23: Compra supermercado | AH23: casa
A24: 45686 | B24: =TEXT(Detalles2025[[#This Row],[Fecha]],"AAAA") -> 2025 | C24: =TEXT(Detalles2025[[#This Row],[Fecha]],"MMMM") -> enero | D24: =TEXT(Detalles2025[[#This Row],[Fecha]],"DDDD") -> miércoles | E24: 101019921 | F24: 1 | G24: 2 | H24: =IF(G24=1,Leyenda!$C$3,IF(G24=2,Leyenda!$C$4,IF(G24=3,Leyenda!$C$5,IF(G24=4,Leyenda!$C$6,IF(G24=5,Leyenda!$C$7,IF(G24=6,Leyenda!$C$8,IF(G24=7,Leyenda!$C$9,IF(G24=8,Leyenda!$C$10," "))))))))&IF(G24=9,Leyenda!$C$11,IF(G24=10,Leyenda!$C$12,IF(G24=11,Leyenda!$C$13,IF(G24=12,Leyenda!$C$14," ")))) -> GASTOS POR TRABAJOS, SUMINISTROS Y SERVICIOS | I24: B012052147 | K24: =IF($G24=0," ",$K$2) -> 202501 | L24: 29 | O24: 0 | P24: =2415.61-50.21 -> 2365.4 | Q24: =SUM(O24:P24) -> 2365.4 | R24: 50.21 | U24: 0 | V24: 0 | W24: 0 | X24: 0 | Y24: 0 | Z24: 0 | AA24: 0 | AB24: 0 | AC24: 0 | AD24: =SUM(Detalles2025[[#This Row],[Monto Facturado]:[Monto Propina Legal]]) -> 2415.61 | AE24: Tarjeta de Credito | AF24: =IFERROR(VLOOKUP(E24,Tabla3[],2,0),"No Registrado") -> Centro Cuesta Nacional S.A.S.//Supermercados Nacional//Casa Cuesta//Ferretería Cuesta//JUMBO//Bebemundo | AG24: Compra de libros | AH24: Yahelis
A25: 45666 | B25: =TEXT(Detalles2025[[#This Row],[Fecha]],"AAAA") -> 2025 | C25: =TEXT(Detalles2025[[#This Row],[Fecha]],"MMMM") -> enero | D25: =TEXT(Detalles2025[[#This Row],[Fecha]],"DDDD") -> jueves | E25: 101602465 | F25: 1 | G25: 2 | H25: =IF(G25=1,Leyenda!$C$3,IF(G25=2,Leyenda!$C$4,IF(G25=3,Leyenda!$C$5,IF(G25=4,Leyenda!$C$6,IF(G25=5,Leyenda!$C$7,IF(G25=6,Leyenda!$C$8,IF(G25=7,Leyenda!$C$9,IF(G25=8,Leyenda!$C$10," "))))))))&IF(G25=9,Leyenda!$C$11,IF(G25=10,Leyenda!$C$12,IF(G25=11,Leyenda!$C$13,IF(G25=12,Leyenda!$C$14," ")))) -> GASTOS POR TRABAJOS, SUMINISTROS Y SERVICIOS | I25: E310006676912 | K25: =IF($G25=0," ",$K$2) -> 202501 | L25: 9 | O25: 0 | P25: =13556-1177.06 -> 12378.94 | Q25: =SUM(O25:P25) -> 12378.94 | R25: 1177.06 | U25: 0 | V25: 0 | W25: 0 | X25: 0 | Y25: 0 | Z25: 0 | AA25: 0 | AB25: 0 | AC25: 0 | AD25: =SUM(Detalles2025[[#This Row],[Monto Facturado]:[Monto Propina Legal]]) -> 13556 | AE25: Tarjeta de Credito | AF25: =IFERROR(VLOOKUP(E25,Tabla3[],2,0),"No Registrado") -> Bravo, S.A.//Supermercados Bravo | AG25: Compra supermercado | AH25: casa
A26: 45671 | B26: =TEXT(Detalles2025[[#This Row],[Fecha]],"AAAA") -> 2025 | C26: =TEXT(Detalles2025[[#This Row],[Fecha]],"MMMM") -> enero | D26: =TEXT(Detalles2025[[#This Row],[Fecha]],"DDDD") -> martes | E26: 101602465 | F26: 1 | G26: 2 | H26: =IF(G26=1,Leyenda!$C$3,IF(G26=2,Leyenda!$C$4,IF(G26=3,Leyenda!$C$5,IF(G26=4,Leyenda!$C$6,IF(G26=5,Leyenda!$C$7,IF(G26=6,Leyenda!$C$8,IF(G26=7,Leyenda!$C$9,IF(G26=8,Leyenda!$C$10," "))))))))&IF(G26=9,Leyenda!$C$11,IF(G26=10,Leyenda!$C$12,IF(G26=11,Leyenda!$C$13,IF(G26=12,Leyenda!$C$14," ")))) -> GASTOS POR TRABAJOS, SUMINISTROS Y SERVICIOS | I26: E310006677922 | K26: =IF($G26=0," ",$K$2) -> 202501 | L26: 14 | O26: 0 | P26: =2104-144.46 -> 1959.54 | Q26: =SUM(O26:P26) -> 1959.54 | R26: 144.46 | U26: 0 | V26: 0 | W26: 0 | X26: 0 | Y26: 0 | Z26: 0 | AA26: 0 | AB26: 0 | AC26: 0 | AD26: =SUM(Detalles2025[[#This Row],[Monto Facturado]:[Monto Propina Legal]]) -> 2104 | AE26: Tarjeta de Credito | AF26: =IFERROR(VLOOKUP(E26,Tabla3[],2,0),"No Registrado") -> Bravo, S.A.//Supermercados Bravo | AG26: Compra supermercado | AH26: casa
A27: 45660 | B27: =TEXT(Detalles2025[[#This Row],[Fecha]],"AAAA") -> 2025 | C27: =TEXT(Detalles2025[[#This Row],[Fecha]],"MMMM") -> enero | D27: =TEXT(Detalles2025[[#This Row],[Fecha]],"DDDD") -> viernes | E27: 101602465 | F27: 1 | G27: 2 | H27: =IF(G27=1,Leyenda!$C$3,IF(G27=2,Leyenda!$C$4,IF(G27=3,Leyenda!$C$5,IF(G27=4,Leyenda!$C$6,IF(G27=5,Leyenda!$C$7,IF(G27=6,Leyenda!$C$8,IF(G27=7,Leyenda!$C$9,IF(G27=8,Leyenda!$C$10," "))))))))&IF(G27=9,Leyenda!$C$11,IF(G27=10,Leyenda!$C$12,IF(G27=11,Leyenda!$C$13,IF(G27=12,Leyenda!$C$14," ")))) -> GASTOS POR TRABAJOS, SUMINISTROS Y SERVICIOS | I27: E310006487720 | K27: =IF($G27=0," ",$K$2) -> 202501 | L27: 3 | O27: 0 | P27: =735-73.23 -> 661.77 | Q27: =SUM(O27:P27) -> 661.77 | R27: 73.23 | U27: 0 | V27: 0 | W27: 0 | X27: 0 | Y27: 0 | Z27: 0 | AA27: 0 | AB27: 0 | AC27: 0 | AD27: =SUM(Detalles2025[[#This Row],[Monto Facturado]:[Monto Propina Legal]]) -> 735 | AE27: Tarjeta de Credito | AF27: =IFERROR(VLOOKUP(E27,Tabla3[],2,0),"No Registrado") -> Bravo, S.A.//Supermercados Bravo | AG27: Compra supermercado | AH27: casa
A28: 45661 | B28: =TEXT(Detalles2025[[#This Row],[Fecha]],"AAAA") -> 2025 | C28: =TEXT(Detalles2025[[#This Row],[Fecha]],"MMMM") -> enero | D28: =TEXT(Detalles2025[[#This Row],[Fecha]],"DDDD") -> sábado | E28: 101602465 | F28: 1 | G28: 2 | H28: =IF(G28=1,Leyenda!$C$3,IF(G28=2,Leyenda!$C$4,IF(G28=3,Leyenda!$C$5,IF(G28=4,Leyenda!$C$6,IF(G28=5,Leyenda!$C$7,IF(G28=6,Leyenda!$C$8,IF(G28=7,Leyenda!$C$9,IF(G28=8,Leyenda!$C$10," "))))))))&IF(G28=9,Leyenda!$C$11,IF(G28=10,Leyenda!$C$12,IF(G28=11,Leyenda!$C$13,IF(G28=12,Leyenda!$C$14," ")))) -> GASTOS POR TRABAJOS, SUMINISTROS Y SERVICIOS | I28: E310006487814 | K28: =IF($G28=0," ",$K$2) -> 202501 | L28: 4 | O28: 0 | P28: =3435-218.55 -> 3216.45 | Q28: =SUM(O28:P28) -> 3216.45 | R28: 218.55 | U28: 0 | V28: 0 | W28: 0 | X28: 0 | Y28: 0 | Z28: 0 | AA28: 0 | AB28: 0 | AC28: 0 | AD28: =SUM(Detalles2025[[#This Row],[Monto Facturado]:[Monto Propina Legal]]) -> 3435 | AE28: Tarjeta de Credito | AF28: =IFERROR(VLOOKUP(E28,Tabla3[],2,0),"No Registrado") -> Bravo, S.A.//Supermercados Bravo | AG28: Compra supermercado | AH28: casa
A29: 45666 | B29: =TEXT(Detalles2025[[#This Row],[Fecha]],"AAAA") -> 2025 | C29: =TEXT(Detalles2025[[#This Row],[Fecha]],"MMMM") -> enero | D29: =TEXT(Detalles2025[[#This Row],[Fecha]],"DDDD") -> jueves | E29: 101651555 | F29: 1 | G29: 4 | H29: =IF(G29=1,Leyenda!$C$3,IF(G29=2,Leyenda!$C$4,IF(G29=3,Leyenda!$C$5,IF(G29=4,Leyenda!$C$6,IF(G29=5,Leyenda!$C$7,IF(G29=6,Leyenda!$C$8,IF(G29=7,Leyenda!$C$9,IF(G29=8,Leyenda!$C$10," "))))))))&IF(G29=9,Leyenda!$C$11,IF(G29=10,Leyenda!$C$12,IF(G29=11,Leyenda!$C$13,IF(G29=12,Leyenda!$C$14," ")))) -> GASTOS DE ACTIVOS FIJO | I29: B0100048709 | K29: =IF($G29=0," ",$K$2) -> 202501 | L29: 9 | O29: 0 | P29: =5646-861.25 -> 4784.75 | Q29: =SUM(O29:P29) -> 4784.75 | R29: 861.25 | U29: 0 | V29: 0 | W29: 0 | X29: 0 | Y29: 0 | Z29: 0 | AA29: 0 | AB29: 0 | AC29: 0 | AD29: =SUM(Detalles2025[[#This Row],[Monto Facturado]:[Monto Propina Legal]]) -> 5646 | AE29: Tarjeta de Credito | AF29: =IFERROR(VLOOKUP(E29,Tabla3[],2,0),"No Registrado") -> INDY PLAZA | AG29: Mantenimiento Hilux | AH29: HILUX
A30: 45673 | B30: =TEXT(Detalles2025[[#This Row],[Fecha]],"AAAA") -> 2025 | C30: =TEXT(Detalles2025[[#This Row],[Fecha]],"MMMM") -> enero | D30: =TEXT(Detalles2025[[#This Row],[Fecha]],"DDDD") -> jueves | E30: 132345657 | F30: 1 | G30: 2 | H30: =IF(G30=1,Leyenda!$C$3,IF(G30=2,Leyenda!$C$4,IF(G30=3,Leyenda!$C$5,IF(G30=4,Leyenda!$C$6,IF(G30=5,Leyenda!$C$7,IF(G30=6,Leyenda!$C$8,IF(G30=7,Leyenda!$C$9,IF(G30=8,Leyenda!$C$10," "))))))))&IF(G30=9,Leyenda!$C$11,IF(G30=10,Leyenda!$C$12,IF(G30=11,Leyenda!$C$13,IF(G30=12,Leyenda!$C$14," ")))) -> GASTOS POR TRABAJOS, SUMINISTROS Y SERVICIOS | I30: E310000002078 | K30: =IF($G30=0," ",$K$2) -> 202501 | L30: 16 | O30: 0 | P30: 9060 | Q30: =SUM(O30:P30) -> 9060 | R30: 1630.8 | U30: 0 | V30: 0 | W30: 0 | X30: 0 | Y30: 0 | Z30: 0 | AA30: 0 | AB30: 0 | AC30: 906 | AD30: =SUM(Detalles2025[[#This Row],[Monto Facturado]:[Monto Propina Legal]]) -> 11596.8 | AE30: Tarjeta de Credito | AF30: =IFERROR(VLOOKUP(E30,Tabla3[],2,0),"No Registrado") -> MARYSOF IS GOOD SRL | AG30: Cumpleaños de Javier | AH30: Restorant
A31: 45676 | B31: =TEXT(Detalles2025[[#This Row],[Fecha]],"AAAA") -> 2025 | C31: =TEXT(Detalles2025[[#This Row],[Fecha]],"MMMM") -> enero | D31: =TEXT(Detalles2025[[#This Row],[Fecha]],"DDDD") -> domingo | E31: 101013834 | F31: 1 | G31: 2 | H31: =IF(G31=1,Leyenda!$C$3,IF(G31=2,Leyenda!$C$4,IF(G31=3,Leyenda!$C$5,IF(G31=4,Leyenda!$C$6,IF(G31=5,Leyenda!$C$7,IF(G31=6,Leyenda!$C$8,IF(G31=7,Leyenda!$C$9,IF(G31=8,Leyenda!$C$10," "))))))))&IF(G31=9,Leyenda!$C$11,IF(G31=10,Leyenda!$C$12,IF(G31=11,Leyenda!$C$13,IF(G31=12,Leyenda!$C$14," ")))) -> GASTOS POR TRABAJOS, SUMINISTROS Y SERVICIOS | I31: E310000652384 | K31: =IF($G31=0," ",$K$2) -> 202501 | L31: 19 | O31: 0 | P31: 7933.59 | Q31: =SUM(O31:P31) -> 7933.59 | R31: 1392.41 | U31: 0 | V31: 0 | W31: 0 | X31: 0 | Y31: 0 | Z31: 0 | AA31: 0 | AB31: 0 | AC31: 0 | AD31: =SUM(Detalles2025[[#This Row],[Monto Facturado]:[Monto Propina Legal]]) -> 9326 | AE31: Tarjeta de Credito | AF31: =IFERROR(VLOOKUP(E31,Tabla3[],2,0),"No Registrado") -> Almacenes Unidos, S.A.S. | AG31: tienda | AH31: casa
A32: 45678 | B32: =TEXT(Detalles2025[[#This Row],[Fecha]],"AAAA") -> 2025 | C32: =TEXT(Detalles2025[[#This Row],[Fecha]],"MMMM") -> enero | D32: =TEXT(Detalles2025[[#This Row],[Fecha]],"DDDD") -> martes | E32: 101602465 | F32: 1 | G32: 2 | H32: =IF(G32=1,Leyenda!$C$3,IF(G32=2,Leyenda!$C$4,IF(G32=3,Leyenda!$C$5,IF(G32=4,Leyenda!$C$6,IF(G32=5,Leyenda!$C$7,IF(G32=6,Leyenda!$C$8,IF(G32=7,Leyenda!$C$9,IF(G32=8,Leyenda!$C$10," "))))))))&IF(G32=9,Leyenda!$C$11,IF(G32=10,Leyenda!$C$12,IF(G32=11,Leyenda!$C$13,IF(G32=12,Leyenda!$C$14," ")))) -> GASTOS POR TRABAJOS, SUMINISTROS Y SERVICIOS | I32: E310006679660 | K32: =IF($G32=0," ",$K$2) -> 202501 | L32: 21 | O32: 0 | P32: =13155-913.56 -> 12241.44 | Q32: =SUM(O32:P32) -> 12241.44 | R32: 913.56 | U32: 0 | V32: 0 | W32: 0 | X32: 0 | Y32: 0 | Z32: 0 | AA32: 0 | AB32: 0 | AC32: 0 | AD32: =SUM(Detalles2025[[#This Row],[Monto Facturado]:[Monto Propina Legal]]) -> 13155 | AE32: Tarjeta de Credito | AF32: =IFERROR(VLOOKUP(E32,Tabla3[],2,0),"No Registrado") -> Bravo, S.A.//Supermercados Bravo | AG32: Compra supermercado | AH32: casa
A33: 45660 | B33: =TEXT(Detalles2025[[#This Row],[Fecha]],"AAAA") -> 2025 | C33: =TEXT(Detalles2025[[#This Row],[Fecha]],"MMMM") -> enero | D33: =TEXT(Detalles2025[[#This Row],[Fecha]],"DDDD") -> viernes | E33: 130196796 | F33: 1 | G33: 2 | H33: =IF(G33=1,Leyenda!$C$3,IF(G33=2,Leyenda!$C$4,IF(G33=3,Leyenda!$C$5,IF(G33=4,Leyenda!$C$6,IF(G33=5,Leyenda!$C$7,IF(G33=6,Leyenda!$C$8,IF(G33=7,Leyenda!$C$9,IF(G33=8,Leyenda!$C$10," "))))))))&IF(G33=9,Leyenda!$C$11,IF(G33=10,Leyenda!$C$12,IF(G33=11,Leyenda!$C$13,IF(G33=12,Leyenda!$C$14," ")))) -> GASTOS POR TRABAJOS, SUMINISTROS Y SERVICIOS | I33: B0100069506 | K33: =IF($G33=0," ",$K$2) -> 202501 | L33: 3 | O33: 3195 | P33: 0 | Q33: =SUM(O33:O33) -> 3195 | R33: 0 | U33: 0 | V33: 0 | W33: 0 | X33: 0 | Y33: 0 | Z33: 0 | AA33: 0 | AB33: 0 | AC33: 0 | AD33: =SUM(Detalles2025[[#This Row],[Monto Facturado]:[Monto Propina Legal]]) -> 3195 | AE33: Tarjeta de Credito | AF33: =IFERROR(VLOOKUP(E33,Tabla3[],2,0),"No Registrado") -> ACADEMIA EUROPEA | AG33: Ingles | AH33: Lorena
A34: 45658 | B34: =TEXT(Detalles2025[[#This Row],[Fecha]],"AAAA") -> 2025 | C34: =TEXT(Detalles2025[[#This Row],[Fecha]],"MMMM") -> enero | D34: =TEXT(Detalles2025[[#This Row],[Fecha]],"DDDD") -> miércoles | E34: 130196796 | F34: 1 | G34: 2 | H34: =IF(G34=1,Leyenda!$C$3,IF(G34=2,Leyenda!$C$4,IF(G34=3,Leyenda!$C$5,IF(G34=4,Leyenda!$C$6,IF(G34=5,Leyenda!$C$7,IF(G34=6,Leyenda!$C$8,IF(G34=7,Leyenda!$C$9,IF(G34=8,Leyenda!$C$10," "))))))))&IF(G34=9,Leyenda!$C$11,IF(G34=10,Leyenda!$C$12,IF(G34=11,Leyenda!$C$13,IF(G34=12,Leyenda!$C$14," ")))) -> GASTOS POR TRABAJOS, SUMINISTROS Y SERVICIOS | I34: B0100069579 | K34: =IF($G34=0," ",$K$2) -> 202501 | L34: 1 | O34: 8672 | P34: 0 | Q34: =SUM(O34:O34) -> 8672 | R34: 0 | U34: 0 | V34: 0 | W34: 0 | X34: 0 | Y34: 0 | Z34: 0 | AA34: 0 | AB34: 0 | AC34: 0 | AD34: =SUM(Detalles2025[[#This Row],[Monto Facturado]:[Monto Propina Legal]]) -> 8672 | AE34: Tarjeta de Credito | AF34: =IFERROR(VLOOKUP(E34,Tabla3[],2,0),"No Registrado") -> ACADEMIA EUROPEA | AG34: Ingles | AH34: Andres
A35: 45665 | B35: =TEXT(Detalles2025[[#This Row],[Fecha]],"AAAA") -> 2025 | C35: =TEXT(Detalles2025[[#This Row],[Fecha]],"MMMM") -> enero | D35: =TEXT(Detalles2025[[#This Row],[Fecha]],"DDDD") -> miércoles | E35: 430030341 | F35: 1 | G35: 2 | H35: =IF(G35=1,Leyenda!$C$3,IF(G35=2,Leyenda!$C$4,IF(G35=3,Leyenda!$C$5,IF(G35=4,Leyenda!$C$6,IF(G35=5,Leyenda!$C$7,IF(G35=6,Leyenda!$C$8,IF(G35=7,Leyenda!$C$9,IF(G35=8,Leyenda!$C$10," "))))))))&IF(G35=9,Leyenda!$C$11,IF(G35=10,Leyenda!$C$12,IF(G35=11,Leyenda!$C$13,IF(G35=12,Leyenda!$C$14," ")))) -> GASTOS POR TRABAJOS, SUMINISTROS Y SERVICIOS | I35: B0100015374 | K35: =IF($G35=0," ",$K$2) -> 202501 | L35: 8 | O35: 7600 | P35: 0 | Q35: =SUM(O35:P35) -> 7600 | R35: 0 | U35: 0 | V35: 0 | W35: 0 | X35: 0 | Y35: 0 | Z35: 0 | AA35: 0 | AB35: 0 | AC35: 0 | AD35: =SUM(Detalles2025[[#This Row],[Monto Facturado]:[Monto Propina Legal]]) -> 7600 | AE35: Tarjeta de Credito | AF35: =IFERROR(VLOOKUP(E35,Tabla3[],2,0),"No Registrado") -> COLEGIO SANTA ROSA DE LIMA | AG35: Colegio | AH35: Yahelis
A36: 45665 | B36: =TEXT(Detalles2025[[#This Row],[Fecha]],"AAAA") -> 2025 | C36: =TEXT(Detalles2025[[#This Row],[Fecha]],"MMMM") -> enero | D36: =TEXT(Detalles2025[[#This Row],[Fecha]],"DDDD") -> miércoles | E36: 430030341 | F36: 1 | G36: 2 | H36: =IF(G36=1,Leyenda!$C$3,IF(G36=2,Leyenda!$C$4,IF(G36=3,Leyenda!$C$5,IF(G36=4,Leyenda!$C$6,IF(G36=5,Leyenda!$C$7,IF(G36=6,Leyenda!$C$8,IF(G36=7,Leyenda!$C$9,IF(G36=8,Leyenda!$C$10," "))))))))&IF(G36=9,Leyenda!$C$11,IF(G36=10,Leyenda!$C$12,IF(G36=11,Leyenda!$C$13,IF(G36=12,Leyenda!$C$14," ")))) -> GASTOS POR TRABAJOS, SUMINISTROS Y SERVICIOS | I36: B0100015375 | K36: =IF($G36=0," ",$K$2) -> 202501 | L36: 8 | O36: 7300 | P36: 0 | Q36: =SUM(O36:P36) -> 7300 | R36: 0 | U36: 0 | V36: 0 | W36: 0 | X36: 0 | Y36: 0 | Z36: 0 | AA36: 0 | AB36: 0 | AC36: 0 | AD36: =SUM(Detalles2025[[#This Row],[Monto Facturado]:[Monto Propina Legal]]) -> 7300 | AE36: Tarjeta de Credito | AF36: =IFERROR(VLOOKUP(E36,Tabla3[],2,0),"No Registrado") -> COLEGIO SANTA ROSA DE LIMA | AG36: Colegio | AH36: Javier
A37: 45665 | B37: =TEXT(Detalles2025[[#This Row],[Fecha]],"AAAA") -> 2025 | C37: =TEXT(Detalles2025[[#This Row],[Fecha]],"MMMM") -> enero | D37: =TEXT(Detalles2025[[#This Row],[Fecha]],"DDDD") -> miércoles | E37: 430030341 | F37: 1 | G37: 2 | H37: =IF(G37=1,Leyenda!$C$3,IF(G37=2,Leyenda!$C$4,IF(G37=3,Leyenda!$C$5,IF(G37=4,Leyenda!$C$6,IF(G37=5,Leyenda!$C$7,IF(G37=6,Leyenda!$C$8,IF(G37=7,Leyenda!$C$9,IF(G37=8,Leyenda!$C$10," "))))))))&IF(G37=9,Leyenda!$C$11,IF(G37=10,Leyenda!$C$12,IF(G37=11,Leyenda!$C$13,IF(G37=12,Leyenda!$C$14," ")))) -> GASTOS POR TRABAJOS, SUMINISTROS Y SERVICIOS | I37: B0100015376 | K37: =IF($G37=0," ",$K$2) -> 202501 | L37: 8 | O37: 7300 | P37: 0 | Q37: =SUM(O37:P37) -> 7300 | R37: 0 | U37: 0 | AA37: 0 | AB37: 0 | AD37: =SUM(Detalles2025[[#This Row],[Monto Facturado]:[Monto Propina Legal]]) -> 7300 | AE37: Tarjeta de Credito | AF37: =IFERROR(VLOOKUP(E37,Tabla3[],2,0),"No Registrado") -> COLEGIO SANTA ROSA DE LIMA | AG37: Colegio | AH37: Lorena
A38: 45687 | B38: =TEXT(Detalles2025[[#This Row],[Fecha]],"AAAA") -> 2025 | C38: =TEXT(Detalles2025[[#This Row],[Fecha]],"MMMM") -> enero | D38: =TEXT(Detalles2025[[#This Row],[Fecha]],"DDDD") -> jueves | E38: 430030341 | F38: 2 | G38: 2 | H38: =IF(G38=1,Leyenda!$C$3,IF(G38=2,Leyenda!$C$4,IF(G38=3,Leyenda!$C$5,IF(G38=4,Leyenda!$C$6,IF(G38=5,Leyenda!$C$7,IF(G38=6,Leyenda!$C$8,IF(G38=7,Leyenda!$C$9,IF(G38=8,Leyenda!$C$10," "))))))))&IF(G38=9,Leyenda!$C$11,IF(G38=10,Leyenda!$C$12,IF(G38=11,Leyenda!$C$13,IF(G38=12,Leyenda!$C$14," ")))) -> GASTOS POR TRABAJOS, SUMINISTROS Y SERVICIOS | I38: B0100015534 | K38: =IF($G38=0," ",$K$2) -> 202501 | L38: 30 | O38: 7600 | Q38: =SUM(O38:P38) -> 7600 | R38: 0 | U38: 0 | AA38: 0 | AB38: 0 | AC38: 0 | AD38: =SUM(Detalles2025[[#This Row],[Monto Facturado]:[Monto Propina Legal]]) -> 7600 | AE38: Tarjeta de Credito | AF38: =IFERROR(VLOOKUP(E38,Tabla3[],2,0),"No Registrado") -> COLEGIO SANTA ROSA DE LIMA | AG38: Colegio | AH38: Yahelis
A39: 45687 | B39: =TEXT(Detalles2025[[#This Row],[Fecha]],"AAAA") -> 2025 | C39: =TEXT(Detalles2025[[#This Row],[Fecha]],"MMMM") -> enero | D39: =TEXT(Detalles2025[[#This Row],[Fecha]],"DDDD") -> jueves | E39: 430030341 | F39: 1 | G39: 2 | H39: =IF(G39=1,Leyenda!$C$3,IF(G39=2,Leyenda!$C$4,IF(G39=3,Leyenda!$C$5,IF(G39=4,Leyenda!$C$6,IF(G39=5,Leyenda!$C$7,IF(G39=6,Leyenda!$C$8,IF(G39=7,Leyenda!$C$9,IF(G39=8,Leyenda!$C$10," "))))))))&IF(G39=9,Leyenda!$C$11,IF(G39=10,Leyenda!$C$12,IF(G39=11,Leyenda!$C$13,IF(G39=12,Leyenda!$C$14," ")))) -> GASTOS POR TRABAJOS, SUMINISTROS Y SERVICIOS | I39: B0100015535 | K39: =IF($G39=0," ",$K$2) -> 202501 | L39: 30 | O39: 7300 | Q39: =SUM(O39:P39) -> 7300 | R39: 0 | AA39: 0 | AB39: 0 | AD39: =SUM(Detalles2025[[#This Row],[Monto Facturado]:[Monto Propina Legal]]) -> 7300 | AE39: Tarjeta de Credito | AF39: =IFERROR(VLOOKUP(E39,Tabla3[],2,0),"No Registrado") -> COLEGIO SANTA ROSA DE LIMA | AG39: Colegio | AH39: Javier
A40: 45687 | B40: =TEXT(Detalles2025[[#This Row],[Fecha]],"AAAA") -> 2025 | C40: =TEXT(Detalles2025[[#This Row],[Fecha]],"MMMM") -> enero | D40: =TEXT(Detalles2025[[#This Row],[Fecha]],"DDDD") -> jueves | E40: 430030341 | F40: 1 | G40: 2 | H40: =IF(G40=1,Leyenda!$C$3,IF(G40=2,Leyenda!$C$4,IF(G40=3,Leyenda!$C$5,IF(G40=4,Leyenda!$C$6,IF(G40=5,Leyenda!$C$7,IF(G40=6,Leyenda!$C$8,IF(G40=7,Leyenda!$C$9,IF(G40=8,Leyenda!$C$10," "))))))))&IF(G40=9,Leyenda!$C$11,IF(G40=10,Leyenda!$C$12,IF(G40=11,Leyenda!$C$13,IF(G40=12,Leyenda!$C$14," ")))) -> GASTOS POR TRABAJOS, SUMINISTROS Y SERVICIOS | I40: B0100015536 | K40: =IF($G40=0," ",$K$2) -> 202501 | L40: 30 | O40: 7300 | Q40: =SUM(O40:P40) -> 7300 | R40: 0 | AA40: 0 | AB40: 0 | AD40: =SUM(Detalles2025[[#This Row],[Monto Facturado]:[Monto Propina Legal]]) -> 7300 | AE40: Tarjeta de Credito | AF40: =IFERROR(VLOOKUP(E40,Tabla3[],2,0),"No Registrado") -> COLEGIO SANTA ROSA DE LIMA | AG40: Colegio | AH40: Lorena
A41: 45687 | B41: 2025 | C41: enero | D41: jueves | E41: 430030341 | F41: 1 | G41: 2 | H41: GASTOS POR TRABAJOS, SUMINISTROS Y SERVICIOS | I41: B0100015536 | J41: 202501 | K41: =IF($G41=0," ",$K$2) -> 202501 | L41: 30 | N41: 7300 | O41: 0 | P41: 0 | Q41: 0 | R41: 0 | T41: 7300 | U41: 0 | V41: COLEGIO SANTA ROSA DE LIMA | W41: Colegio | X41: Lorena | AA41: 0 | AB41: 0 | AC41: 0 | AD41: 0 | AE41: Tarjeta de Credito | AF41: =IFERROR(VLOOKUP(E41,Tabla3[],2,0),"No Registrado") -> COLEGIO SANTA ROSA DE LIMA | AG41: Colegio | AH41: Andres
A42: 45688 | B42: =TEXT(Detalles2025[[#This Row],[Fecha]],"AAAA") -> 2025 | C42: =TEXT(Detalles2025[[#This Row],[Fecha]],"MMMM") -> enero | D42: =TEXT(Detalles2025[[#This Row],[Fecha]],"DDDD") -> viernes | E42: 130196796 | F42: 1 | G42: 2 | H42: =IF(G42=1,Leyenda!$C$3,IF(G42=2,Leyenda!$C$4,IF(G42=3,Leyenda!$C$5,IF(G42=4,Leyenda!$C$6,IF(G42=5,Leyenda!$C$7,IF(G42=6,Leyenda!$C$8,IF(G42=7,Leyenda!$C$9,IF(G42=8,Leyenda!$C$10," "))))))))&IF(G42=9,Leyenda!$C$11,IF(G42=10,Leyenda!$C$12,IF(G42=11,Leyenda!$C$13,IF(G42=12,Leyenda!$C$14," ")))) -> GASTOS POR TRABAJOS, SUMINISTROS Y SERVICIOS | I42: B0100069864 | K42: =IF($G42=0," ",$K$2) -> 202501 | L42: 31 | O42: 5801 | Q42: =SUM(O42:P42) -> 5801 | R42: 0 | AA42: 0 | AB42: 0 | AD42: =SUM(Detalles2025[[#This Row],[Monto Facturado]:[Monto Propina Legal]]) -> 5801 | AE42: Tarjeta de Credito | AF42: =IFERROR(VLOOKUP(E42,Tabla3[],2,0),"No Registrado") -> ACADEMIA EUROPEA | AG42: ingles | AH42: Javier
A43: 45681 | B43: =TEXT(Detalles2025[[#This Row],[Fecha]],"AAAA") -> 2025 | C43: =TEXT(Detalles2025[[#This Row],[Fecha]],"MMMM") -> enero | D43: =TEXT(Detalles2025[[#This Row],[Fecha]],"DDDD") -> viernes | E43: 130196796 | F43: 1 | G43: 2 | H43: =IF(G43=1,Leyenda!$C$3,IF(G43=2,Leyenda!$C$4,IF(G43=3,Leyenda!$C$5,IF(G43=4,Leyenda!$C$6,IF(G43=5,Leyenda!$C$7,IF(G43=6,Leyenda!$C$8,IF(G43=7,Leyenda!$C$9,IF(G43=8,Leyenda!$C$10," "))))))))&IF(G43=9,Leyenda!$C$11,IF(G43=10,Leyenda!$C$12,IF(G43=11,Leyenda!$C$13,IF(G43=12,Leyenda!$C$14," ")))) -> GASTOS POR TRABAJOS, SUMINISTROS Y SERVICIOS | I43: B0100069761 | K43: =IF($G43=0," ",$K$2) -> 202501 | L43: 24 | O43: 3190 | Q43: =SUM(O43:P43) -> 3190 | R43: 0 | AA43: 0 | AB43: 0 | AD43: =SUM(Detalles2025[[#This Row],[Monto Facturado]:[Monto Propina Legal]]) -> 3190 | AE43: Tarjeta de Credito | AF43: =IFERROR(VLOOKUP(E43,Tabla3[],2,0),"No Registrado") -> ACADEMIA EUROPEA | AG43: Ingles | AH43: Andres
A44: 45664 | B44: =TEXT(Detalles2025[[#This Row],[Fecha]],"AAAA") -> 2025 | C44: =TEXT(Detalles2025[[#This Row],[Fecha]],"MMMM") -> enero | D44: =TEXT(Detalles2025[[#This Row],[Fecha]],"DDDD") -> martes | E44: 101001577 | F44: 1 | G44: 2 | H44: =IF(G44=1,Leyenda!$C$3,IF(G44=2,Leyenda!$C$4,IF(G44=3,Leyenda!$C$5,IF(G44=4,Leyenda!$C$6,IF(G44=5,Leyenda!$C$7,IF(G44=6,Leyenda!$C$8,IF(G44=7,Leyenda!$C$9,IF(G44=8,Leyenda!$C$10," "))))))))&IF(G44=9,Leyenda!$C$11,IF(G44=10,Leyenda!$C$12,IF(G44=11,Leyenda!$C$13,IF(G44=12,Leyenda!$C$14," ")))) -> GASTOS POR TRABAJOS, SUMINISTROS Y SERVICIOS | I44: E310010838524 | K44: =IF($G44=0," ",$K$2) -> 202501 | L44: 7 | O44: 1153.08 | Q44: =SUM(O44:P44) -> 1153.08 | R44: 207.55 | AA44: 115.31 | AB44: 23.06 | AD44: =SUM(Detalles2025[[#This Row],[Monto Facturado]:[Monto Propina Legal]]) -> 1499 | AE44: Tarjeta de Credito | AF44: =IFERROR(VLOOKUP(E44,Tabla3[],2,0),"No Registrado") -> CLARO//CODETEL | AG44: Telefono | AH44: casa
A45: 45664 | B45: =TEXT(Detalles2025[[#This Row],[Fecha]],"AAAA") -> 2025 | C45: =TEXT(Detalles2025[[#This Row],[Fecha]],"MMMM") -> enero | D45: =TEXT(Detalles2025[[#This Row],[Fecha]],"DDDD") -> martes | E45: 101001577 | F45: 1 | G45: 2 | H45: =IF(G45=1,Leyenda!$C$3,IF(G45=2,Leyenda!$C$4,IF(G45=3,Leyenda!$C$5,IF(G45=4,Leyenda!$C$6,IF(G45=5,Leyenda!$C$7,IF(G45=6,Leyenda!$C$8,IF(G45=7,Leyenda!$C$9,IF(G45=8,Leyenda!$C$10," "))))))))&IF(G45=9,Leyenda!$C$11,IF(G45=10,Leyenda!$C$12,IF(G45=11,Leyenda!$C$13,IF(G45=12,Leyenda!$C$14," ")))) -> GASTOS POR TRABAJOS, SUMINISTROS Y SERVICIOS | I45: E310010835663 | K45: =IF($G45=0," ",$K$2) -> 202501 | L45: 7 | O45: 2407.69 | Q45: =SUM(O45:P45) -> 2407.69 | R45: 433.39 | AA45: 240.77 | AB45: 48.15 | AD45: =SUM(Detalles2025[[#This Row],[Monto Facturado]:[Monto Propina Legal]]) -> 3130 | AE45: Tarjeta de Credito | AF45: =IFERROR(VLOOKUP(E45,Tabla3[],2,0),"No Registrado") -> CLARO//CODETEL | AG45: Celular | AH45: Ernesto
A46: 45677 | B46: =TEXT(Detalles2025[[#This Row],[Fecha]],"AAAA") -> 2025 | C46: =TEXT(Detalles2025[[#This Row],[Fecha]],"MMMM") -> enero | D46: =TEXT(Detalles2025[[#This Row],[Fecha]],"DDDD") -> lunes | E46: 101820217 | F46: 1 | G46: 2 | H46: =IF(G46=1,Leyenda!$C$3,IF(G46=2,Leyenda!$C$4,IF(G46=3,Leyenda!$C$5,IF(G46=4,Leyenda!$C$6,IF(G46=5,Leyenda!$C$7,IF(G46=6,Leyenda!$C$8,IF(G46=7,Leyenda!$C$9,IF(G46=8,Leyenda!$C$10," "))))))))&IF(G46=9,Leyenda!$C$11,IF(G46=10,Leyenda!$C$12,IF(G46=11,Leyenda!$C$13,IF(G46=12,Leyenda!$C$14," ")))) -> GASTOS POR TRABAJOS, SUMINISTROS Y SERVICIOS | I46: E310000046093 | K46: =IF($G46=0," ",$K$2) -> 202501 | L46: 20 | O46: 3849.79 | Q46: =SUM(O46:P46) -> 3849.79 | AD46: =SUM(Detalles2025[[#This Row],[Monto Facturado]:[Monto Propina Legal]]) -> 3849.79 | AE46: Tarjeta de Credito | AF46: =IFERROR(VLOOKUP(E46,Tabla3[],2,0),"No Registrado") -> EDEESTE | AG46: Luz | AH46: casa
A47: 45684 | B47: =TEXT(Detalles2025[[#This Row],[Fecha]],"AAAA") -> 2025 | C47: =TEXT(Detalles2025[[#This Row],[Fecha]],"MMMM") -> enero | D47: =TEXT(Detalles2025[[#This Row],[Fecha]],"DDDD") -> lunes | E47: 00000000 | F47: 1 | G47: 12 | H47: =IF(G47=1,Leyenda!$C$3,IF(G47=2,Leyenda!$C$4,IF(G47=3,Leyenda!$C$5,IF(G47=4,Leyenda!$C$6,IF(G47=5,Leyenda!$C$7,IF(G47=6,Leyenda!$C$8,IF(G47=7,Leyenda!$C$9,IF(G47=8,Leyenda!$C$10," "))))))))&IF(G47=9,Leyenda!$C$11,IF(G47=10,Leyenda!$C$12,IF(G47=11,Leyenda!$C$13,IF(G47=12,Leyenda!$C$14," ")))) -> GASTOS MENORES | I47: 0 | K47: =IF($G47=0," ",$K$2) -> 202501 | L47: 27 | O47: 0 | P47: 2000 | Q47: =SUM(O47:P47) -> 2000 | AD47: =SUM(Detalles2025[[#This Row],[Monto Facturado]:[Monto Propina Legal]]) -> 2000 | AE47: Transferencia Bancaria | AF47: =IFERROR(VLOOKUP(E47,Tabla3[],2,0),"No Registrado") -> No Registrado | AG47: Liga Baseball | AH47: Andres
A48: 45684 | B48: =TEXT(Detalles2025[[#This Row],[Fecha]],"AAAA") -> 2025 | C48: =TEXT(Detalles2025[[#This Row],[Fecha]],"MMMM") -> enero | D48: =TEXT(Detalles2025[[#This Row],[Fecha]],"DDDD") -> lunes | E48: 00000000 | F48: 1 | G48: 12 | H48: =IF(G48=1,Leyenda!$C$3,IF(G48=2,Leyenda!$C$4,IF(G48=3,Leyenda!$C$5,IF(G48=4,Leyenda!$C$6,IF(G48=5,Leyenda!$C$7,IF(G48=6,Leyenda!$C$8,IF(G48=7,Leyenda!$C$9,IF(G48=8,Leyenda!$C$10," "))))))))&IF(G48=9,Leyenda!$C$11,IF(G48=10,Leyenda!$C$12,IF(G48=11,Leyenda!$C$13,IF(G48=12,Leyenda!$C$14," ")))) -> GASTOS MENORES | I48: 0 | K48: =IF($G48=0," ",$K$2) -> 202501 | L48: 27 | O48: 0 | P48: 2000 | Q48: =SUM(O48:P48) -> 2000 | AD48: =SUM(Detalles2025[[#This Row],[Monto Facturado]:[Monto Propina Legal]]) -> 2000 | AE48: Transferencia Bancaria | AF48: =IFERROR(VLOOKUP(E48,Tabla3[],2,0),"No Registrado") -> No Registrado | AG48: Liga Baseball | AH48: Javier
A49: 45677 | B49: =TEXT(Detalles2025[[#This Row],[Fecha]],"AAAA") -> 2025 | C49: =TEXT(Detalles2025[[#This Row],[Fecha]],"MMMM") -> enero | D49: =TEXT(Detalles2025[[#This Row],[Fecha]],"DDDD") -> lunes | E49: 101602465 | F49: 1 | G49: 12 | H49: =IF(G49=1,Leyenda!$C$3,IF(G49=2,Leyenda!$C$4,IF(G49=3,Leyenda!$C$5,IF(G49=4,Leyenda!$C$6,IF(G49=5,Leyenda!$C$7,IF(G49=6,Leyenda!$C$8,IF(G49=7,Leyenda!$C$9,IF(G49=8,Leyenda!$C$10," "))))))))&IF(G49=9,Leyenda!$C$11,IF(G49=10,Leyenda!$C$12,IF(G49=11,Leyenda!$C$13,IF(G49=12,Leyenda!$C$14," ")))) -> GASTOS MENORES | I49: 0 | K49: =IF($G49=0," ",$K$2) -> 202501 | L49: 20 | O49: 0 | P49: 1390 | Q49: =SUM(O49:P49) -> 1390 | R49: 0 | U49: 0 | AA49: 0 | AB49: 0 | AC49: 0 | AD49: =SUM(Detalles2025[[#This Row],[Monto Facturado]:[Monto Propina Legal]]) -> 1390 | AE49: Tarjeta de Credito | AF49: =IFERROR(VLOOKUP(E49,Tabla3[],2,0),"No Registrado") -> Bravo, S.A.//Supermercados Bravo | AG49: Gimnasio | AH49: Yahelis
A50: 45674 | B50: =TEXT(Detalles2025[[#This Row],[Fecha]],"AAAA") -> 2025 | C50: =TEXT(Detalles2025[[#This Row],[Fecha]],"MMMM") -> enero | D50: =TEXT(Detalles2025[[#This Row],[Fecha]],"DDDD") -> viernes | E50: 430078549 | F50: 2 | G50: 12 | H50: =IF(G50=1,Leyenda!$C$3,IF(G50=2,Leyenda!$C$4,IF(G50=3,Leyenda!$C$5,IF(G50=4,Leyenda!$C$6,IF(G50=5,Leyenda!$C$7,IF(G50=6,Leyenda!$C$8,IF(G50=7,Leyenda!$C$9,IF(G50=8,Leyenda!$C$10," "))))))))&IF(G50=9,Leyenda!$C$11,IF(G50=10,Leyenda!$C$12,IF(G50=11,Leyenda!$C$13,IF(G50=12,Leyenda!$C$14," ")))) -> GASTOS MENORES | I50: 0 | K50: =IF($G50=0," ",$K$3) -> 202501 | L50: 17 | O50: 0 | P50: 1000 | Q50: =SUM(O50:P50) -> 1000 | R50: 0 | U50: 0 | AA50: 0 | AB50: 0 | AC50: 0 | AD50: =SUM(Detalles2025[[#This Row],[Monto Facturado]:[Monto Propina Legal]]) -> 1000 | AE50: Tarjeta de Credito | AF50: =IFERROR(VLOOKUP(E50,Tabla3[],2,0),"No Registrado") -> Fundacion Cristiana de Consolacion y Ayuda | AG50: Odontologo | AH50: Yahelis
A51: 45677 | B51: =TEXT(Detalles2025[[#This Row],[Fecha]],"AAAA") -> 2025 | C51: =TEXT(Detalles2025[[#This Row],[Fecha]],"MMMM") -> enero | D51: =TEXT(Detalles2025[[#This Row],[Fecha]],"DDDD") -> lunes | E51: 101010020 | F51: 1 | G51: 12 | H51: =IF(G51=1,Leyenda!$C$3,IF(G51=2,Leyenda!$C$4,IF(G51=3,Leyenda!$C$5,IF(G51=4,Leyenda!$C$6,IF(G51=5,Leyenda!$C$7,IF(G51=6,Leyenda!$C$8,IF(G51=7,Leyenda!$C$9,IF(G51=8,Leyenda!$C$10," "))))))))&IF(G51=9,Leyenda!$C$11,IF(G51=10,Leyenda!$C$12,IF(G51=11,Leyenda!$C$13,IF(G51=12,Leyenda!$C$14," ")))) -> GASTOS MENORES | I51: 0 | K51: =IF($G51=0," ",$K$2) -> 202501 | L51: 20 | O51: 1364 | P51: 0 | Q51: =SUM(O51:P51) -> 1364 | R51: 0 | U51: 0 | AA51: 0 | AB51: 0 | AC51: 0 | AD51: =SUM(Detalles2025[[#This Row],[Monto Facturado]:[Monto Propina Legal]]) -> 1364 | AE51: Tarjeta de Credito | AF51: =IFERROR(VLOOKUP(E51,Tabla3[],2,0),"No Registrado") -> No Registrado | AG51: Netflix | AH51: casa
A52: 45667 | B52: =TEXT(Detalles2025[[#This Row],[Fecha]],"AAAA") -> 2025 | C52: =TEXT(Detalles2025[[#This Row],[Fecha]],"MMMM") -> enero | D52: =TEXT(Detalles2025[[#This Row],[Fecha]],"DDDD") -> viernes | E52: 020101011 | F52: 1 | G52: 12 | H52: =IF(G52=1,Leyenda!$C$3,IF(G52=2,Leyenda!$C$4,IF(G52=3,Leyenda!$C$5,IF(G52=4,Leyenda!$C$6,IF(G52=5,Leyenda!$C$7,IF(G52=6,Leyenda!$C$8,IF(G52=7,Leyenda!$C$9,IF(G52=8,Leyenda!$C$10," "))))))))&IF(G52=9,Leyenda!$C$11,IF(G52=10,Leyenda!$C$12,IF(G52=11,Leyenda!$C$13,IF(G52=12,Leyenda!$C$14," ")))) -> GASTOS MENORES | I52: 0 | K52: =IF($G52=0," ",$K$2) -> 202501 | L52: 10 | O52: 1085.01 | P52: 0 | Q52: =SUM(O52:P52) -> 1085.01 | R52: 0 | U52: 0 | AA52: 0 | AB52: 0 | AC52: 0 | AD52: =SUM(Detalles2025[[#This Row],[Monto Facturado]:[Monto Propina Legal]]) -> 1085.01 | AE52: Tarjeta de Credito | AF52: =IFERROR(VLOOKUP(E52,Tabla3[],2,0),"No Registrado") -> No Registrado | AG52: Celular | AH52: Yajaira
A53: 45667 | B53: =TEXT(Detalles2025[[#This Row],[Fecha]],"AAAA") -> 2025 | C53: =TEXT(Detalles2025[[#This Row],[Fecha]],"MMMM") -> enero | D53: =TEXT(Detalles2025[[#This Row],[Fecha]],"DDDD") -> viernes | E53: 0000000011 | F53: 1 | G53: 12 | H53: =IF(G53=1,Leyenda!$C$3,IF(G53=2,Leyenda!$C$4,IF(G53=3,Leyenda!$C$5,IF(G53=4,Leyenda!$C$6,IF(G53=5,Leyenda!$C$7,IF(G53=6,Leyenda!$C$8,IF(G53=7,Leyenda!$C$9,IF(G53=8,Leyenda!$C$10," "))))))))&IF(G53=9,Leyenda!$C$11,IF(G53=10,Leyenda!$C$12,IF(G53=11,Leyenda!$C$13,IF(G53=12,Leyenda!$C$14," ")))) -> GASTOS MENORES | I53: 0 | K53: =IF($G53=0," ",$K$2) -> 202501 | L53: 19 | O53: 3720 | P53: 0 | Q53: =SUM(O53:P53) -> 3720 | R53: 0 | U53: 0 | AA53: 0 | AB53: 0 | AC53: 0 | AD53: =SUM(Detalles2025[[#This Row],[Monto Facturado]:[Monto Propina Legal]]) -> 3720 | AE53: Tarjeta de Credito | AF53: =IFERROR(VLOOKUP(E53,Tabla3[],2,0),"No Registrado") -> No Registrado | AG53: Chatgpt | AH53: Ernesto
A54: =DATE(LEFT(K54,4),RIGHT(K54,2),L54) -> 45692 | B54: =TEXT(Detalles2025[[#This Row],[Fecha]],"AAAA") -> 2025 | C54: =TEXT(Detalles2025[[#This Row],[Fecha]],"MMMM") -> febrero | D54: =TEXT(Detalles2025[[#This Row],[Fecha]],"DDDD") -> martes | E54: 101008172 | F54: 1 | G54: 2 | H54: =IF(G54=1,Leyenda!$C$3,IF(G54=2,Leyenda!$C$4,IF(G54=3,Leyenda!$C$5,IF(G54=4,Leyenda!$C$6,IF(G54=5,Leyenda!$C$7,IF(G54=6,Leyenda!$C$8,IF(G54=7,Leyenda!$C$9,IF(G54=8,Leyenda!$C$10," "))))))))&IF(G54=9,Leyenda!$C$11,IF(G54=10,Leyenda!$C$12,IF(G54=11,Leyenda!$C$13,IF(G54=12,Leyenda!$C$14," ")))) -> GASTOS POR TRABAJOS, SUMINISTROS Y SERVICIOS | I54: B0108657107 | K54: 202502 | L54: 4 | O54: 0 | P54: 1458 | Q54: =SUM(O54:P54) -> 1458 | R54: 0 | U54: 0 | AA54: 0 | AB54: 0 | AC54: 0 | AD54: =SUM(Detalles2025[[#This Row],[Monto Facturado]:[Monto Propina Legal]]) -> 1458 | AE54: Tarjeta de Credito | AF54: =IFERROR(VLOOKUP(E54,Tabla3[],2,0),"No Registrado") -> Isla Dominicana de Petroleo, Corp. | AG54: Gas Propano | AH54: casa
A55: =DATE(LEFT(K55,4),RIGHT(K55,2),L55) -> 45693 | B55: =TEXT(Detalles2025[[#This Row],[Fecha]],"AAAA") -> 2025 | C55: =TEXT(Detalles2025[[#This Row],[Fecha]],"MMMM") -> febrero | D55: =TEXT(Detalles2025[[#This Row],[Fecha]],"DDDD") -> miércoles | E55: 130794987 | F55: 1 | G55: 4 | H55: =IF(G55=1,Leyenda!$C$3,IF(G55=2,Leyenda!$C$4,IF(G55=3,Leyenda!$C$5,IF(G55=4,Leyenda!$C$6,IF(G55=5,Leyenda!$C$7,IF(G55=6,Leyenda!$C$8,IF(G55=7,Leyenda!$C$9,IF(G55=8,Leyenda!$C$10," "))))))))&IF(G55=9,Leyenda!$C$11,IF(G55=10,Leyenda!$C$12,IF(G55=11,Leyenda!$C$13,IF(G55=12,Leyenda!$C$14," ")))) -> GASTOS DE ACTIVOS FIJO | I55: B0101366307 | K55: =IF($G55=0," ",$K$54) -> 202502 | L55: 5 | O55: 0 | P55: 3429 | Q55: =SUM(O55:P55) -> 3429 | R55: 0 | U55: 0 | AA55: 0 | AB55: 0 | AC55: 0 | AD55: =SUM(Detalles2025[[#This Row],[Monto Facturado]:[Monto Propina Legal]]) -> 3429 | AE55: Tarjeta de Credito | AF55: =IFERROR(VLOOKUP(E55,Tabla3[],2,0),"No Registrado") -> Strata, S.R.L. | AG55: Gasolina | AH55: CRV
A56: =DATE(LEFT(K56,4),RIGHT(K56,2),L56) -> 45714 | B56: =TEXT(Detalles2025[[#This Row],[Fecha]],"AAAA") -> 2025 | C56: =TEXT(Detalles2025[[#This Row],[Fecha]],"MMMM") -> febrero | D56: =TEXT(Detalles2025[[#This Row],[Fecha]],"DDDD") -> miércoles | E56: 000000001 | F56: 1 | G56: 12 | H56: =IF(G56=1,Leyenda!$C$3,IF(G56=2,Leyenda!$C$4,IF(G56=3,Leyenda!$C$5,IF(G56=4,Leyenda!$C$6,IF(G56=5,Leyenda!$C$7,IF(G56=6,Leyenda!$C$8,IF(G56=7,Leyenda!$C$9,IF(G56=8,Leyenda!$C$10," "))))))))&IF(G56=9,Leyenda!$C$11,IF(G56=10,Leyenda!$C$12,IF(G56=11,Leyenda!$C$13,IF(G56=12,Leyenda!$C$14," ")))) -> GASTOS MENORES | I56: 0 | K56: =IF($G56=0," ",$K$54) -> 202502 | L56: 26 | O56: 0 | P56: 6000 | Q56: =SUM(O56:P56) -> 6000 | R56: 0 | S56: 0 | T56: 0 | U56: 0 | V56: 0 | W56: 0 | X56: 0 | Y56: 0 | Z56: 0 | AA56: 0 | AB56: 0 | AC56: 0 | AD56: =SUM(Detalles2025[[#This Row],[Monto Facturado]:[Monto Propina Legal]]) -> 6000 | AE56: Transferencia Bancaria | AF56: =IFERROR(VLOOKUP(E56,Tabla3[],2,0),"No Registrado") -> No Registrado | AG56: Mesada | AH56: Yajaira
A57: =DATE(LEFT(K57,4),RIGHT(K57,2),L57) -> 45714 | B57: =TEXT(Detalles2025[[#This Row],[Fecha]],"AAAA") -> 2025 | C57: =TEXT(Detalles2025[[#This Row],[Fecha]],"MMMM") -> febrero | D57: =TEXT(Detalles2025[[#This Row],[Fecha]],"DDDD") -> miércoles | E57: 000000002 | F57: 1 | G57: 12 | H57: =IF(G57=1,Leyenda!$C$3,IF(G57=2,Leyenda!$C$4,IF(G57=3,Leyenda!$C$5,IF(G57=4,Leyenda!$C$6,IF(G57=5,Leyenda!$C$7,IF(G57=6,Leyenda!$C$8,IF(G57=7,Leyenda!$C$9,IF(G57=8,Leyenda!$C$10," "))))))))&IF(G57=9,Leyenda!$C$11,IF(G57=10,Leyenda!$C$12,IF(G57=11,Leyenda!$C$13,IF(G57=12,Leyenda!$C$14," ")))) -> GASTOS MENORES | I57: 0 | K57: =IF($G57=0," ",$K$54) -> 202502 | L57: 26 | O57: 0 | P57: 3000 | Q57: =SUM(O57:P57) -> 3000 | R57: 0 | S57: 0 | T57: 0 | U57: 0 | V57: 0 | W57: 0 | X57: 0 | Y57: 0 | Z57: 0 | AA57: 0 | AB57: 0 | AC57: 0 | AD57: =SUM(Detalles2025[[#This Row],[Monto Facturado]:[Monto Propina Legal]]) -> 3000 | AE57: Transferencia Bancaria | AF57: =IFERROR(VLOOKUP(E57,Tabla3[],2,0),"No Registrado") -> No Registrado | AG57: Mesada | AH57: Yahelis
A58: =DATE(LEFT(K58,4),RIGHT(K58,2),L58) -> 45714 | B58: =TEXT(Detalles2025[[#This Row],[Fecha]],"AAAA") -> 2025 | C58: =TEXT(Detalles2025[[#This Row],[Fecha]],"MMMM") -> febrero | D58: =TEXT(Detalles2025[[#This Row],[Fecha]],"DDDD") -> miércoles | E58: 000000003 | F58: 1 | G58: 12 | H58: =IF(G58=1,Leyenda!$C$3,IF(G58=2,Leyenda!$C$4,IF(G58=3,Leyenda!$C$5,IF(G58=4,Leyenda!$C$6,IF(G58=5,Leyenda!$C$7,IF(G58=6,Leyenda!$C$8,IF(G58=7,Leyenda!$C$9,IF(G58=8,Leyenda!$C$10," "))))))))&IF(G58=9,Leyenda!$C$11,IF(G58=10,Leyenda!$C$12,IF(G58=11,Leyenda!$C$13,IF(G58=12,Leyenda!$C$14," ")))) -> GASTOS MENORES | I58: 0 | K58: =IF($G58=0," ",$K$54) -> 202502 | L58: 26 | O58: 0 | P58: 1500 | Q58: =SUM(O58:P58) -> 1500 | R58: 0 | S58: 0 | T58: 0 | U58: 0 | V58: 0 | W58: 0 | X58: 0 | Y58: 0 | Z58: 0 | AA58: 0 | AB58: 0 | AC58: 0 | AD58: =SUM(Detalles2025[[#This Row],[Monto Facturado]:[Monto Propina Legal]]) -> 1500 | AE58: Efectivo | AF58: =IFERROR(VLOOKUP(E58,Tabla3[],2,0),"No Registrado") -> No Registrado | AG58: Mesada | AH58: Javier
A59: =DATE(LEFT(K59,4),RIGHT(K59,2),L59) -> 45714 | B59: =TEXT(Detalles2025[[#This Row],[Fecha]],"AAAA") -> 2025 | C59: =TEXT(Detalles2025[[#This Row],[Fecha]],"MMMM") -> febrero | D59: =TEXT(Detalles2025[[#This Row],[Fecha]],"DDDD") -> miércoles | E59: 000000004 | F59: 1 | G59: 12 | H59: =IF(G59=1,Leyenda!$C$3,IF(G59=2,Leyenda!$C$4,IF(G59=3,Leyenda!$C$5,IF(G59=4,Leyenda!$C$6,IF(G59=5,Leyenda!$C$7,IF(G59=6,Leyenda!$C$8,IF(G59=7,Leyenda!$C$9,IF(G59=8,Leyenda!$C$10," "))))))))&IF(G59=9,Leyenda!$C$11,IF(G59=10,Leyenda!$C$12,IF(G59=11,Leyenda!$C$13,IF(G59=12,Leyenda!$C$14," ")))) -> GASTOS MENORES | I59: 0 | K59: =IF($G59=0," ",$K$54) -> 202502 | L59: 26 | O59: 0 | P59: 500 | Q59: =SUM(O59:P59) -> 500 | R59: 0 | S59: 0 | T59: 0 | U59: 0 | V59: 0 | W59: 0 | X59: 0 | Y59: 0 | Z59: 0 | AA59: 0 | AB59: 0 | AC59: 0 | AD59: =SUM(Detalles2025[[#This Row],[Monto Facturado]:[Monto Propina Legal]]) -> 500 | AE59: Efectivo | AF59: =IFERROR(VLOOKUP(E59,Tabla3[],2,0),"No Registrado") -> No Registrado | AG59: Mesada | AH59: Lorena
A60: =DATE(LEFT(K60,4),RIGHT(K60,2),L60) -> 45714 | B60: =TEXT(Detalles2025[[#This Row],[Fecha]],"AAAA") -> 2025 | C60: =TEXT(Detalles2025[[#This Row],[Fecha]],"MMMM") -> febrero | D60: =TEXT(Detalles2025[[#This Row],[Fecha]],"DDDD") -> miércoles | E60: 000000005 | F60: 1 | G60: 12 | H60: =IF(G60=1,Leyenda!$C$3,IF(G60=2,Leyenda!$C$4,IF(G60=3,Leyenda!$C$5,IF(G60=4,Leyenda!$C$6,IF(G60=5,Leyenda!$C$7,IF(G60=6,Leyenda!$C$8,IF(G60=7,Leyenda!$C$9,IF(G60=8,Leyenda!$C$10," "))))))))&IF(G60=9,Leyenda!$C$11,IF(G60=10,Leyenda!$C$12,IF(G60=11,Leyenda!$C$13,IF(G60=12,Leyenda!$C$14," ")))) -> GASTOS MENORES | I60: 0 | K60: =IF($G60=0," ",$K$54) -> 202502 | L60: 26 | O60: 0 | P60: 500 | Q60: =SUM(O60:P60) -> 500 | R60: 0 | S60: 0 | T60: 0 | U60: 0 | V60: 0 | W60: 0 | X60: 0 | Y60: 0 | Z60: 0 | AA60: 0 | AB60: 0 | AC60: 0 | AD60: =SUM(Detalles2025[[#This Row],[Monto Facturado]:[Monto Propina Legal]]) -> 500 | AE60: Efectivo | AF60: =IFERROR(VLOOKUP(E60,Tabla3[],2,0),"No Registrado") -> No Registrado | AG60: Mesada | AH60: Andres
A61: =DATE(LEFT(K61,4),RIGHT(K61,2),L61) -> 45700 | B61: =TEXT(Detalles2025[[#This Row],[Fecha]],"AAAA") -> 2025 | C61: =TEXT(Detalles2025[[#This Row],[Fecha]],"MMMM") -> febrero | D61: =TEXT(Detalles2025[[#This Row],[Fecha]],"DDDD") -> miércoles | E61: 130794987 | F61: 1 | G61: 4 | H61: =IF(G61=1,Leyenda!$C$3,IF(G61=2,Leyenda!$C$4,IF(G61=3,Leyenda!$C$5,IF(G61=4,Leyenda!$C$6,IF(G61=5,Leyenda!$C$7,IF(G61=6,Leyenda!$C$8,IF(G61=7,Leyenda!$C$9,IF(G61=8,Leyenda!$C$10," "))))))))&IF(G61=9,Leyenda!$C$11,IF(G61=10,Leyenda!$C$12,IF(G61=11,Leyenda!$C$13,IF(G61=12,Leyenda!$C$14," ")))) -> GASTOS DE ACTIVOS FIJO | I61: B0101369091 | K61: =IF($G61=0," ",$K$54) -> 202502 | L61: 12 | O61: 0 | P61: 4722 | Q61: =SUM(O61:P61) -> 4722 | R61: 0 | U61: 0 | AA61: 0 | AB61: 0 | AC61: 0 | AD61: =SUM(Detalles2025[[#This Row],[Monto Facturado]:[Monto Propina Legal]]) -> 4722 | AE61: Tarjeta de Credito | AF61: =IFERROR(VLOOKUP(E61,Tabla3[],2,0),"No Registrado") -> Strata, S.R.L. | AG61: Diesel | AH61: HILUX
A62: =DATE(LEFT(K62,4),RIGHT(K62,2),L62) -> 45707 | B62: =TEXT(Detalles2025[[#This Row],[Fecha]],"AAAA") -> 2025 | C62: =TEXT(Detalles2025[[#This Row],[Fecha]],"MMMM") -> febrero | D62: =TEXT(Detalles2025[[#This Row],[Fecha]],"DDDD") -> miércoles | E62: 130794987 | F62: 1 | G62: 4 | H62: =IF(G62=1,Leyenda!$C$3,IF(G62=2,Leyenda!$C$4,IF(G62=3,Leyenda!$C$5,IF(G62=4,Leyenda!$C$6,IF(G62=5,Leyenda!$C$7,IF(G62=6,Leyenda!$C$8,IF(G62=7,Leyenda!$C$9,IF(G62=8,Leyenda!$C$10," "))))))))&IF(G62=9,Leyenda!$C$11,IF(G62=10,Leyenda!$C$12,IF(G62=11,Leyenda!$C$13,IF(G62=12,Leyenda!$C$14," ")))) -> GASTOS DE ACTIVOS FIJO | I62: B0101370926 | K62: =IF($G62=0," ",$K$54) -> 202502 | L62: 19 | O62: 0 | P62: 3400 | Q62: =SUM(O62:P62) -> 3400 | R62: 0 | U62: 0 | AA62: 0 | AB62: 0 | AC62: 0 | AD62: =SUM(Detalles2025[[#This Row],[Monto Facturado]:[Monto Propina Legal]]) -> 3400 | AE62: Tarjeta de Credito | AF62: =IFERROR(VLOOKUP(E62,Tabla3[],2,0),"No Registrado") -> Strata, S.R.L. | AG62: Gasolina | AH62: CRV
A63: =DATE(LEFT(K63,4),RIGHT(K63,2),L63) -> 45701 | B63: =TEXT(Detalles2025[[#This Row],[Fecha]],"AAAA") -> 2025 | C63: =TEXT(Detalles2025[[#This Row],[Fecha]],"MMMM") -> febrero | D63: =TEXT(Detalles2025[[#This Row],[Fecha]],"DDDD") -> jueves | E63: 131233465 | F63: 1 | G63: 2 | H63: =IF(G63=1,Leyenda!$C$3,IF(G63=2,Leyenda!$C$4,IF(G63=3,Leyenda!$C$5,IF(G63=4,Leyenda!$C$6,IF(G63=5,Leyenda!$C$7,IF(G63=6,Leyenda!$C$8,IF(G63=7,Leyenda!$C$9,IF(G63=8,Leyenda!$C$10," "))))))))&IF(G63=9,Leyenda!$C$11,IF(G63=10,Leyenda!$C$12,IF(G63=11,Leyenda!$C$13,IF(G63=12,Leyenda!$C$14," ")))) -> GASTOS POR TRABAJOS, SUMINISTROS Y SERVICIOS | I63: B0100045296 | K63: =IF($G63=0," ",$K$54) -> 202502 | L63: 13 | O63: 0 | P63: 500 | Q63: =SUM(O63:P63) -> 500 | R63: 90 | U63: 0 | AA63: 0 | AB63: 0 | AC63: 50 | AD63: =SUM(Detalles2025[[#This Row],[Monto Facturado]:[Monto Propina Legal]]) -> 640 | AE63: Tarjeta de Credito | AF63: =IFERROR(VLOOKUP(E63,Tabla3[],2,0),"No Registrado") -> NOCCIOLA FOOD HALL SRL | AG63: Café | AH63: Ernesto
A64: =DATE(LEFT(K64,4),RIGHT(K64,2),L64) -> 45693 | B64: =TEXT(Detalles2025[[#This Row],[Fecha]],"AAAA") -> 2025 | C64: =TEXT(Detalles2025[[#This Row],[Fecha]],"MMMM") -> febrero | D64: =TEXT(Detalles2025[[#This Row],[Fecha]],"DDDD") -> miércoles | E64: 131341136 | F64: 1 | G64: 2 | H64: =IF(G64=1,Leyenda!$C$3,IF(G64=2,Leyenda!$C$4,IF(G64=3,Leyenda!$C$5,IF(G64=4,Leyenda!$C$6,IF(G64=5,Leyenda!$C$7,IF(G64=6,Leyenda!$C$8,IF(G64=7,Leyenda!$C$9,IF(G64=8,Leyenda!$C$10," "))))))))&IF(G64=9,Leyenda!$C$11,IF(G64=10,Leyenda!$C$12,IF(G64=11,Leyenda!$C$13,IF(G64=12,Leyenda!$C$14," ")))) -> GASTOS POR TRABAJOS, SUMINISTROS Y SERVICIOS | I64: B0100703870 | K64: =IF($G64=0," ",$K$54) -> 202502 | L64: 5 | O64: 0 | P64: 593.22 | Q64: =SUM(O64:P64) -> 593.22 | R64: 106.78 | U64: 0 | AA64: 0 | AB64: 0 | AC64: 0 | AD64: =SUM(Detalles2025[[#This Row],[Monto Facturado]:[Monto Propina Legal]]) -> 700 | AE64: Tarjeta de Credito | AF64: =IFERROR(VLOOKUP(E64,Tabla3[],2,0),"No Registrado") -> Little Ceasars Pizza Alma Rosa | AG64: Cena Familiar | AH64: Restorant
A65: =DATE(LEFT(K65,4),RIGHT(K65,2),L65) -> 45704 | B65: =TEXT(Detalles2025[[#This Row],[Fecha]],"AAAA") -> 2025 | C65: =TEXT(Detalles2025[[#This Row],[Fecha]],"MMMM") -> febrero | D65: =TEXT(Detalles2025[[#This Row],[Fecha]],"DDDD") -> domingo | E65: 130647811 | F65: 1 | G65: 2 | H65: =IF(G65=1,Leyenda!$C$3,IF(G65=2,Leyenda!$C$4,IF(G65=3,Leyenda!$C$5,IF(G65=4,Leyenda!$C$6,IF(G65=5,Leyenda!$C$7,IF(G65=6,Leyenda!$C$8,IF(G65=7,Leyenda!$C$9,IF(G65=8,Leyenda!$C$10," "))))))))&IF(G65=9,Leyenda!$C$11,IF(G65=10,Leyenda!$C$12,IF(G65=11,Leyenda!$C$13,IF(G65=12,Leyenda!$C$14," ")))) -> GASTOS POR TRABAJOS, SUMINISTROS Y SERVICIOS | I65: B0100008568 | K65: =IF($G65=0," ",$K$54) -> 202502 | L65: 16 | O65: 0 | P65: 1750 | Q65: =SUM(O65:P65) -> 1750 | R65: 315 | U65: 0 | AA65: 0 | AB65: 0 | AC65: 0 | AD65: =SUM(Detalles2025[[#This Row],[Monto Facturado]:[Monto Propina Legal]]) -> 2065 | AE65: Tarjeta de Credito | AF65: =IFERROR(VLOOKUP(E65,Tabla3[],2,0),"No Registrado") -> EL CORRIDO TAQUERIA RESTAURANT | AG65: Cena Familiar | AH65: Restorant
A66: =DATE(LEFT(K66,4),RIGHT(K66,2),L66) -> 45696 | B66: =TEXT(Detalles2025[[#This Row],[Fecha]],"AAAA") -> 2025 | C66: =TEXT(Detalles2025[[#This Row],[Fecha]],"MMMM") -> febrero | D66: =TEXT(Detalles2025[[#This Row],[Fecha]],"DDDD") -> sábado | E66: 130064423 | F66: 1 | G66: 2 | H66: =IF(G66=1,Leyenda!$C$3,IF(G66=2,Leyenda!$C$4,IF(G66=3,Leyenda!$C$5,IF(G66=4,Leyenda!$C$6,IF(G66=5,Leyenda!$C$7,IF(G66=6,Leyenda!$C$8,IF(G66=7,Leyenda!$C$9,IF(G66=8,Leyenda!$C$10," "))))))))&IF(G66=9,Leyenda!$C$11,IF(G66=10,Leyenda!$C$12,IF(G66=11,Leyenda!$C$13,IF(G66=12,Leyenda!$C$14," ")))) -> GASTOS POR TRABAJOS, SUMINISTROS Y SERVICIOS | I66: B0102092152 | K66: =IF($G66=0," ",$K$54) -> 202502 | L66: 8 | O66: 0 | P66: 1600 | Q66: =SUM(O66:P66) -> 1600 | R66: 0 | U66: 0 | AA66: 0 | AB66: 0 | AC66: 0 | AD66: =SUM(Detalles2025[[#This Row],[Monto Facturado]:[Monto Propina Legal]]) -> 1600 | AE66: Tarjeta de Credito | AF66: =IFERROR(VLOOKUP(E66,Tabla3[],2,0),"No Registrado") -> Farmacía Medicar GBC, A. H. | AG66: Salud | AH66: Salud
A67: =DATE(LEFT(K67,4),RIGHT(K67,2),L67) -> 45692 | B67: =TEXT(Detalles2025[[#This Row],[Fecha]],"AAAA") -> 2025 | C67: =TEXT(Detalles2025[[#This Row],[Fecha]],"MMMM") -> febrero | D67: =TEXT(Detalles2025[[#This Row],[Fecha]],"DDDD") -> martes | E67: 131039499 | F67: 1 | G67: 2 | H67: =IF(G67=1,Leyenda!$C$3,IF(G67=2,Leyenda!$C$4,IF(G67=3,Leyenda!$C$5,IF(G67=4,Leyenda!$C$6,IF(G67=5,Leyenda!$C$7,IF(G67=6,Leyenda!$C$8,IF(G67=7,Leyenda!$C$9,IF(G67=8,Leyenda!$C$10," "))))))))&IF(G67=9,Leyenda!$C$11,IF(G67=10,Leyenda!$C$12,IF(G67=11,Leyenda!$C$13,IF(G67=12,Leyenda!$C$14," ")))) -> GASTOS POR TRABAJOS, SUMINISTROS Y SERVICIOS | I67: B0100097038 | K67: =IF($G67=0," ",$K$54) -> 202502 | L67: 4 | O67: 0 | P67: 373 | Q67: =SUM(O67:P67) -> 373 | R67: 0 | U67: 0 | AA67: 0 | AB67: 0 | AC67: 0 | AD67: =SUM(Detalles2025[[#This Row],[Monto Facturado]:[Monto Propina Legal]]) -> 373 | AE67: Tarjeta de Credito | AF67: =IFERROR(VLOOKUP(E67,Tabla3[],2,0),"No Registrado") -> Farmacia VIP Mendo SRL | AG67: salud | AH67: Salud
A68: =DATE(LEFT(K68,4),RIGHT(K68,2),L68) -> 45704 | B68: =TEXT(Detalles2025[[#This Row],[Fecha]],"AAAA") -> 2025 | C68: =TEXT(Detalles2025[[#This Row],[Fecha]],"MMMM") -> febrero | D68: =TEXT(Detalles2025[[#This Row],[Fecha]],"DDDD") -> domingo | E68: 101043598 | F68: 1 | G68: 7 | H68: =IF(G68=1,Leyenda!$C$3,IF(G68=2,Leyenda!$C$4,IF(G68=3,Leyenda!$C$5,IF(G68=4,Leyenda!$C$6,IF(G68=5,Leyenda!$C$7,IF(G68=6,Leyenda!$C$8,IF(G68=7,Leyenda!$C$9,IF(G68=8,Leyenda!$C$10," "))))))))&IF(G68=9,Leyenda!$C$11,IF(G68=10,Leyenda!$C$12,IF(G68=11,Leyenda!$C$13,IF(G68=12,Leyenda!$C$14," ")))) -> GASTOS FINANCIEROS | I68: E310000175557 | K68: =IF($G68=0," ",$K$54) -> 202502 | L68: 16 | O68: 0 | P68: 48000 | Q68: =SUM(O68:P68) -> 48000 | R68: 0 | U68: 0 | AA68: 0 | AB68: 0 | AC68: 0 | AD68: =SUM(Detalles2025[[#This Row],[Monto Facturado]:[Monto Propina Legal]]) -> 48000 | AE68: Transferencia Bancaria | AF68: =IFERROR(VLOOKUP(E68,Tabla3[],2,0),"No Registrado") -> Banco Dominicano del Progreso, S. A.//Banco Multiple | AG68: Hipoteca | AH68: Prestamo
